Workbook
Name _____xlnm._FilterDatabase: #REF!
Name _____xlnm.Print_Titles: #REF!
Name _____xlnm.Print_Titles_1: #REF!
Name ____xlnm._FilterDatabase: #REF!
Name ____xlnm.Print_Titles: #REF!
Name ____xlnm.Print_Titles_1: #REF!
Name ___xlnm._FilterDatabase: #REF!
Name ___xlnm.Print_Titles: #REF!
Name ___xlnm.Print_Titles_1: #REF!
Name __xlnm._FilterDatabase: #REF!
Name __xlnm.Print_Titles: #REF!
Name __xlnm.Print_Titles_1: #REF!
Name A: #REF!
Name ACT_FIJOS_VALOR: #REF!
Name AJUSTE_REAJ_FIS_AF: #REF!
Name año: #REF!
Name cajaç: #REF!
Name CALDECNM: #REF!
Name Caracter: #REF!
Name CIIU: #REF!
Name CIIUNM: #REF!
Name CLASEDEC: #REF!
Name CLASEDECNM: #REF!
Name CODADMONNM: #REF!
Name CODDOCSNM: #REF!
Name Codigos: #REF!
Name Comprobantes: #REF!
Name convencion: #REF!
Name cxc: #REF!
Name DEPTOSNM: #REF!
Name DIVIPOL: #REF!
Name DIVIPOL1: #REF!
Name DIVIPOLCOD: #REF!
Name DIVIPOLNM: #REF!
Name Excel_BuiltIn_Print_Titles: #REF!
Name Excel_BuiltIn_Print_Titles_1: #REF!
Name G: #REF!
Name gActEcono: #REF!
Name gAdmon: #REF!
Name gAño: #REF!
Name gApe1Dec: #REF!
Name gApe1Rev: #REF!
Name gApe2Dec: #REF!
Name gApe2Rev: #REF!
Name GB: #REF!
Name gCalDec: #REF!
Name gCedDec: #REF!
Name gCedRev: #REF!
Name gClaseDec: #REF!
Name gDeclaraPrimerVez: #REF!
Name gDepto: #REF!
Name gDireccion: #REF!
Name gExentoRtaPres: #REF!
Name gFechaDecCor: #REF!
Name gMetValInv: #REF!
Name gMun: #REF!
Name gNIT: #REF!
Name gNom1Dec: #REF!
Name gNom1Rev: #REF!
Name gNom2Dec: #REF!

Sheet Eventos de riesgos
B1: REFERENCIA | C1: Año | D1: Mes | E1: FECHA INICIO | F1: FECHA FINALIZACION | G1: FECHA DESCUBRIMIENTO | H1: DESCRIPCION EVENTO | I1: CUANTIA | J1: CUANTIA TOTAL RECUPERADA | K1: CUANTIA RECUPERADA SEGUROS | L1: CLASE EVENTO NIVEL 1 | M1: CLASE EVENTO NIVEL 2 | N1: CLASE EVENTO NIVEL 3 | O1: CUENTA CONTABLE | P1: FECHA CONTABILIZACION | Q1: SERVICIO / PRODUCTO | R1: CANAL ATENCION CLIENTE | S1: NIT FUNCIONARIO REPORTE EVENTO | T1: NOMBRE FUNCIONARIO REPORTE EVENTO | U1: EMAIL FUNCIONARIO REPORTE EVENTO | V1: ESTADO EVENTO | W1: REVISION EVENTO | X1: CATEGORÍA 4 (Interna) | Y1: RIESGOS | Z1: TAREAS | AA1: PERDIDA TOTAL | AB1: DESCRIPCIÓN DE RIESGO | AC1: EVENTO (Qué pasó) | AD1: CAUSA (Por qué ocurrió) | AE1: CONSECUENCIA (Impactos)
B2: 1 | C2: 2021 | D2: Dic | E2: 44440.835 | F2: 44531.835 | G2: 44531.835 | H2: Caso Febor tiene contratado los servicios de Visionamos para operaciones electrónicas. El pasado 1 de septiembre de 2020, Visionamos ejecutó un proceso en cola de aplicación de nomina erróneamente, este proceso se ejecutó más de una vez debido a desconexiones tecnológicas donde no se evidenció la corrida del proceso inicial y se procedió a correrlo 2 veces mas, ocasionando aumento en los saldos y obligando a reprocesar con reversiones de saldos. En este proceso se afectó 137 asociados por un valor total de $ 344.885.519, no hubo pérdidas económicas ya que los dineros abonados no habían sido retirados de las cuentas por parte de los asociados. Desde Febor se operó un reintegro masivo para recuperar los dineros, sin embargo, siendo Visionamos el responsable material, se observó que no intervino en el reproceso y que por otro lado se identificó la falla hasta diciembre de 2021 por parte del área operativa (1 año y 3 meses después), esto genera alertas tales como: Riesgo operativo de terceros, fallas en la comunicación y flujos operativos con terceros, reputación y credibilidad de la Cooperativa. Acciones Reversión de saldos Realizar reversión de las operaciones erradas. Monitoreo permanente de las operaciones electrónicas, puede que las desconexiones de interface se repitan pero la Cooperativa debe conocerlo inmediatamente. Es necesario soporte permanente también desde visionamos. Jefe de Operaciones | I2: 344885519 | J2: 344885519 | K2: 0 | L2: 7 - Ejecución y Administración de Procesos | M2: 76 - Proveedores | N2: 763 - Incumplimiento de las Actividades Contratadas | P2: 44561 | Q2: Ahorros voluntarios | R2: Ninguno | S2: 52974192 | T2: Ingrid Yamile Polo Caita | U2: operaciones@febor.coop | V2: Aprobado | W2: 16/02/2022 20:08:19: Riesgo. Pérdidas económicas por fallas operativas que implica la relación e intervención con proveedores y/o terceros y pérdida de imagen y confianza de los asociados si se ven afectados sus productos financieros a causa de actividades erradas desde la Cooperativa. | X2: Falla en operaciones electrónicas originadas por el proveedor | Z2: =+COUNTIF('Eventos-Tareas'!$D$22:$D$1048576,'Eventos de riesgos'!$B2) -> 1 | AA2: =+'Eventos de riesgos'!$I2-'Eventos de riesgos'!$J2-'Eventos de riesgos'!$K2 -> 0 | AB2: El proveedor Visionamos ejecutó múltiples veces un proceso de aplicación de nómina por desconexiones tecnológicas, afectando los saldos de 137 asociados por $344.885.519. La falla no fue detectada oportunamente por el área operativa, generando riesgo reputacional y operativo. | AC2: El proveedor Visionamos ejecutó erróneamente el proceso de aplicación de nómina en múltiples ocasiones, generando incrementos indebidos en los saldos de 137 asociados por un valor total de $344.885.519. | AD2: Desconexiones tecnológicas en los sistemas del proveedor impidieron verificar la ejecución inicial del proceso, llevando a su repetición. La falla no fue identificada por el área operativa de Febor sino hasta 15 meses después del evento. | AE2: Afectación de saldos de 137 asociados. Aunque no hubo pérdida económica definitiva, se requirió un reintegro masivo. Se generaron alertas de riesgo operativo con terceros, fallas en comunicación y riesgo reputacional para la Cooperativa.
B3: 2 | C3: 2021 | D3: Oct | E3: 44286 | F3: 44286 | G3: 44489 | H3: Caso Sobre los primeros días de marzo de 2021, 35 asociados hicieron operaciones con su tarjeta débito que en total sumó $7.943.416. Se presentó fallas tecnológicas, desconexión entre los aplicativos y dichas operaciones nunca fueron descontadas de los ahorros voluntarios de los asociados. Por otro lado, se añade que al momento de realizar conciliaciones, no se verificó estas operaciones y en el mes de octubre cuando se detectó la falla, varios asociados ya no tenían este dinero es sus cuentas de ahorro para realizar el cobro correspondiente. Acciones De los $7.943.416 que sumó el total de las transacciones, se recuperó $4.365.767 quedando un valor por recuperar de $3.607.649. Revisar las operaciones de los asociados afectados, conciliar y recuperar los dineros de las cuentas de ahorro voluntario y para quienes ya no contaban con el recurso ir recuperando de manera paulatina. | I3: 7943416 | J3: 4365767 | K3: 0 | L3: 6 - Fallas Tecnologicas | M3: 61 - Sistemas | N3: 614 - Interrupción en el Suministro de un Servicio Público que Ocasiones Falla en los Sistemas | P3: 44500 | Q3: Ahorros voluntarios | R3: Ninguno | S3: 52974192 | T3: INGRID YAMILE POLO CAITA | U3: operaciones@febor.coop | V3: Aprobado | W3: 18/02/2022 15:52:17: Riesgo identificado - Pérdidas económicas por fallas tecnológicas entra los aplicativos que conectan la operación de la Cooperativa. | X3: Falla en operaciones electrónicas originadas por el proveedor | Z3: =+COUNTIF('Eventos-Tareas'!$D$22:$D$1048576,'Eventos de riesgos'!$B3) -> 1 | AA3: =+'Eventos de riesgos'!$I3-'Eventos de riesgos'!$J3-'Eventos de riesgos'!$K3 -> 3577649 | AB3: Fallas tecnológicas en la conexión entre aplicativos impidieron que 35 operaciones con tarjeta débito por $7.943.416 fueran descontadas de las cuentas de ahorro voluntario. La falla no fue detectada en las conciliaciones, generando una pérdida no recuperada de $3.577.649. | AC3: 35 asociados realizaron operaciones con tarjeta débito por un total de $7.943.416, las cuales no fueron descontadas de sus cuentas de ahorro voluntario debido a una falla en la conexión entre aplicativos. | AD3: Falla tecnológica por desconexión entre los sistemas transaccionales. Adicionalmente, las conciliaciones periódicas no detectaron oportunamente las operaciones pendientes de aplicar. | AE3: Pérdida económica de $3.577.649 no recuperada. Se logró recuperar $4.365.767 de los $7.943.416 totales. Varios asociados ya no contaban con los saldos suficientes al momento del descubrimiento.
B4: 3 | C4: 2021 | D4: Dic | E4: 44529 | F4: 44533 | G4: 44533 | H4: Caso El 29 de noviembre, el área de operaciones ejecutó el proceso acostumbrado de aplicación de nominas de Colpensiones, tomando la plantilla oficial publicada en la página Web de Colpensiones. El 3 de diciembre, cuando el área de operaciones verificó el proceso junto con el área contable se hallaron diferencias con el reporte aplicado Se evidenció que la plantilla utilizada para dicha operación era errada, (error que reconoció Colpensiones y posteriormente publicó la plantilla corregida) y que faltaba información por suministrar. En este proceso se procedió a realizar el cargue nuevamente y no se generaron pérdidas económicas para la Cooperativa. Acciones Corregir las operaciones ejecutadas de manera errónea, de forma urgente. Medida de autocontrol por parte del analista, debe revisar plantillas y versiones oficiales antes de los cargues | I4: 0 | J4: 0 | K4: 0 | L4: 7 - Ejecución y Administración de Procesos | M4: 71 - Recepción, Ejecución y Mantenimiento de Operaciones | N4: 717 - Problema en el Mantenimiento de Datos de Referencia | P4: 44561 | Q4: Varios tipos de crédito | R4: Ninguno | S4: 52974192 | T4: INGRID YAMILE POLO CAITA | U4: operaciones@febor.coop | V4: Aprobado | W4: 18/02/2022 15:59:23: Identificación de riesgo- Pérdidas económicas por operaciones erradas en la aplicación de nomina. | X4: Error en aplicación de nómina Colpensiones | Z4: =+COUNTIF('Eventos-Tareas'!$D$22:$D$1048576,'Eventos de riesgos'!$B4) -> 1 | AA4: =+'Eventos de riesgos'!$I4-'Eventos de riesgos'!$J4-'Eventos de riesgos'!$K4 -> 0 | AB4: El área de operaciones aplicó la nómina de Colpensiones usando una plantilla errónea publicada por la entidad, lo que generó diferencias contables. Se realizó el reproceso sin pérdidas económicas para la Cooperativa. | AC4: Se aplicó la nómina de Colpensiones utilizando una plantilla incorrecta publicada en la página web oficial de Colpensiones, generando diferencias en el reporte aplicado detectadas días después por el área de operaciones y contabilidad. | AD4: Colpensiones publicó una plantilla con errores en su página web oficial, la cual fue utilizada por el área de operaciones de Febor sin validación previa de su versión o vigencia. | AE4: Necesidad de reprocesar el cargue de nómina. No se generaron pérdidas económicas para la Cooperativa, pero el evento evidenció la necesidad de controles de autocontrol en la verificación de plantillas antes del procesamiento.
B5: 4 | C5: 1900 | D5: Ene | H5: Prueba eliminada por verificación en proceso de implementación SARO SIAR | L5: Prueba | M5: Prueba | Q5: Ninguno | R5: Ninguno | Z5: =+COUNTIF('Eventos-Tareas'!$D$22:$D$1048576,'Eventos de riesgos'!$B5) -> 0 | AA5: =+'Eventos de riesgos'!$I5-'Eventos de riesgos'!$J5-'Eventos de riesgos'!$K5 -> 0 | AB5: 0 | AC5: 0 | AD5: 0 | AE5: 0
B6: 5 | C6: 2022 | D6: Ene | E6: 44562 | F6: 44562 | G6: 44562 | H6: Caso Personas inescrupulosas crearon una página web www.coopfebor.com falsa para ofrecer préstamos de libre inversión, aprovechándose del buen nombre de Febor. Realizaron publicidad de oferta de servicios mediante cartas dirigidas y por la línea de WhatsApp 3123312790 donde solicitan envío de información al correo de gerencia@coopfebor.com con el fin de obtener tal servicio. En dicha pagina web se publicó la dirección real de Febor para crear confianza, Febor acudió inmediatamente a la publicación oficial de la novedad por los canales oficiales dirigida a los asociados y tramitó las denuncias correspondientes. El proceso de suplantación no surgió efecto, no se identifican asociados víctimas de fraude en este evento. Acciones Comunicación y alerta inmediata a través de los canales oficiales de la Cooperativa para prevenir a los asociados de ser victimas de fraude. Verificación permanente de sitios web sospechosos con información básica de Febor. | I6: 0 | J6: 0 | K6: 0 | L6: 2 - Fraude Externo | M6: 22 - Hurto y Fraude | N6: 222 - Falsificación | P6: 44592 | Q6: Crédito de libre inversión | R6: Canales de comunicación virtual | S6: 1033706838 | T6: Diana Maribel Fonseca Gómez | U6: direccion.riesgos@febor.coop | V6: Aprobado | W6: 18/02/2022 16:14:05: Transacción de riesgo- Pérdida de imagen y reputación debido a suplantaciones realizadas por personas inescrupulosas. | X6: Suplantación de página web de Febor | Z6: =+COUNTIF('Eventos-Tareas'!$D$22:$D$1048576,'Eventos de riesgos'!$B6) -> 1 | AA6: =+'Eventos de riesgos'!$I6-'Eventos de riesgos'!$J6-'Eventos de riesgos'!$K6 -> 0 | AB6: Terceros crearon una página web falsa suplantando a Febor para ofrecer préstamos, utilizando el nombre, dirección real y canales de comunicación de la Cooperativa. No se identificaron asociados víctimas, pero se generó riesgo reputacional. | AC6: Personas inescrupulosas crearon la página web www.coopfebor.com suplantando a Febor para ofrecer préstamos de libre inversión, difundiendo la oferta mediante cartas y WhatsApp con datos reales de la Cooperativa. | AD6: Aprovechamiento del buen nombre de Febor por parte de terceros con fines fraudulentos, mediante la creación de canales digitales falsos con información oficial de la Cooperativa. | AE6: Riesgo reputacional para la Cooperativa. No se identificaron asociados víctimas de fraude. Febor realizó alertas por canales oficiales y radicó las denuncias correspondientes.
B7: 6 | C7: 1900 | D7: Ene | H7: Prueba eliminada por verificación en proceso de implementación SARO SIAR | L7: Prueba | M7: Prueba | O7: Ninguna | Q7: Ninguno | R7: Ninguno | Z7: =+COUNTIF('Eventos-Tareas'!$D$22:$D$1048576,'Eventos de riesgos'!$B7) -> 0 | AA7: =+'Eventos de riesgos'!$I7-'Eventos de riesgos'!$J7-'Eventos de riesgos'!$K7 -> 0 | AB7: 0 | AC7: 0 | AD7: 0 | AE7: 0
B8: 7 | C8: 1900 | D8: Ene | H8: Prueba eliminada por verificación en proceso de implementación SARO SIAR | L8: Prueba | M8: Prueba | O8: Ninguna | Q8: Ninguno | R8: Ninguno | Z8: =+COUNTIF('Eventos-Tareas'!$D$22:$D$1048576,'Eventos de riesgos'!$B8) -> 0 | AA8: =+'Eventos de riesgos'!$I8-'Eventos de riesgos'!$J8-'Eventos de riesgos'!$K8 -> 0 | AB8: 0 | AC8: 0 | AD8: 0 | AE8: 0
B9: 8 | C9: 2022 | D9: Feb | E9: 43870 | F9: 43871 | G9: 44602 | H9: Caso El 09 de febrero de 2022 se presentaron fallas en la conexión de internet y en el PBX a partir de las 6:00pm, ocasionado por un daño en el switch (un dispositivo de interconexión utilizado para conectar equipos en red). Se realizó el proceso de restablecimiento del sistema y opera con normalidad a partir de las 8:30 am del 10 de febrero 2022. Para garantizar continuidad de la operación, se reemplazará el dispositivo de interconexión con los recursos presupuestados para el mantenimiento preventivo y/o correctivo de equipos e infraestructura tecnológica. No se registran pérdidas económicas que deba asumir la Cooperativa. Acciones Reemplazar el switch dañado para garantizar nuevamente la conectividad. | I9: 0 | J9: 0 | K9: 0 | L9: 6 - Fallas Tecnologicas | M9: 61 - Sistemas | N9: 613 - Pérdida por Fallas en Telecomunicaciones | O9: Ninguna | P9: 44620 | Q9: Ninguno | R9: Comunicación por PBX | S9: 53166187 | T9: Johana Paola Cortés Gómez | U9: direccion.sas@febor.coop | V9: Aprobado | W9: 18/02/2022 16:53:31: Transacción de riesgo - Insatisfacción de los asociados por no prestar oportunamente los servicios mediante los canales telefónicos dado que las fallas tecnológicas interrumpen este medio de comunicación. | X9: Indisponibilidad PBX | Z9: =+COUNTIF('Eventos-Tareas'!$D$22:$D$1048576,'Eventos de riesgos'!$B9) -> 1 | AA9: =+'Eventos de riesgos'!$I9-'Eventos de riesgos'!$J9-'Eventos de riesgos'!$K9 -> 0 | AB9: Daño en el switch de interconexión de red provocó la indisponibilidad del servicio de internet y PBX durante aproximadamente 14 horas, afectando la prestación del servicio a los asociados y la operación de la Cooperativa. | AC9: El 9 de febrero de 2022, a partir de las 6:00 p.m., se presentó falla en la conexión de internet y en el PBX de la Cooperativa, ocasionada por el daño en el switch de interconexión de red. El servicio fue restablecido a las 8:30 a.m. del día siguiente. | AD9: Daño físico en el switch de interconexión de red, dispositivo que conecta los equipos a la red interna y externa de la Cooperativa. | AE9: Indisponibilidad del servicio de internet y PBX durante aproximadamente 14,5 horas. No se registraron pérdidas económicas, pero se generó insatisfacción por la interrupción en la atención telefónica a los asociados.
B10: 9 | C10: 2022 | D10: Feb | E10: 44606 | F10: 44607 | G10: 44606 | H10: Caso El día 14 de febrero 2022 el asociado José Neira Ochoa identificado con CC 170562291 reportó sobre las 4:30 pm a Febor que intentaban extraer dinero de su cuenta de ahorros voluntarios sin su consentimiento. Al indagar y averiguar la situación expuesta por el asociado, se logró identificar dos personas que intentaban extraer $12 millones de pesos, y se bloqueó la aplicación del retiro inmediatamente, de igual al día siguiente, el asociado reportó que en la madrugada del 15 de febrero también tuvo intento de robo por $20 millones por uno de las personas identificadas. El Asociado José Neira argumenta que esta persona es un asesor de una empresa de telefonía donde solicitó un servicio, y él confiado entregó su celular, por tal motivo este asesor tuvo acceso a su App móvil transaccional e inicio sus intentos de fraude. Febor hizo los bloqueos correspondientes sobre los productos del asociado para evitar este hurto y brindó la información pertinente para que pudiera iniciar un proceso de denuncia formal ante las autoridades competentes. Acciones Realizar el bloqueo inmediato de las cuentas y productos del asociado, asesorar al asociado para el restablecimiento de contraseñas Comunicar y alertar de manera preventiva a los asociados para que cuiden su información y equipos de uso personal. Brindar información al asociado con respecto de los intentos de fraude y asesoramiento para que presente la denuncia correspondiente. | I10: 0 | J10: 0 | K10: 0 | L10: 2 - Fraude Externo | M10: 22 - Hurto y Fraude | N10: 221 - Robo o Hurto | O10: Ninguna | P10: 44620 | Q10: Ahorros voluntarios | R10: Aplicación móvil (App Febor) | S10: 1016071699 | T10: JOHAN SANTIAGO CRUZ MARTÍN | U10: Analista.operativo2@febor.coop | V10: Aprobado | W10: 18/02/2022 16:58:10: Transacción de riesgo- Pérdida de imagen y credibilidad con respecto de la seguridad de nuestros mecanismos de seguridad tecnológica y oportunidad de respuesta ante situaciones de posible fraude. | X10: Suplantación y fraude a asociados | Z10: =+COUNTIF('Eventos-Tareas'!$D$22:$D$1048576,'Eventos de riesgos'!$B10) -> 2 | AA10: =+'Eventos de riesgos'!$I10-'Eventos de riesgos'!$J10-'Eventos de riesgos'!$K10 -> 0 | AB10: Terceros accedieron de forma no autorizada a la App móvil transaccional de un asociado e intentaron realizar retiros por $32 millones desde su cuenta de ahorros voluntarios. Los intentos fueron bloqueados oportunamente. | AC10: El asociado José Neira Ochoa reportó intentos de retiro no autorizados por $12 millones y posteriormente $20 millones desde su cuenta de ahorros voluntarios a través de la App móvil transaccional. Los retiros fueron bloqueados de manera oportuna. | AD10: El asociado entregó su celular a un asesor de telefonía quien accedió a la App móvil transaccional. La falta de control sobre el dispositivo personal del asociado expuso sus credenciales y acceso a los productos financieros. | AE10: No se registraron pérdidas económicas. Se realizaron bloqueos inmediatos sobre los productos del asociado. Se generó riesgo reputacional relacionado con la seguridad de los mecanismos tecnológicos y la capacidad de respuesta ante fraudes.
B11: 10 | C11: 2022 | D11: Ene | E11: 44556 | F11: 44564 | G11: 44564 | H11: Caso No se programó el débito automático de la asociada Olaine Salas Fuentes de su producto Línea temporal con un saldo e $6.500.000 y una cuota de $110.500, debido a que el proceso de programación de débitos automáticos no está automatizado, se realiza de forma manual agregando un listado oficial en Excel y por olvido del analista que administra dicha información, no se incorporó la programación del débito para esta obligación. La obligación vencía el 26 de diciembre /21 y se aplicó el débito hasta el día 3 de enero/22. Acciones Programar y ejecutar de manera inmediata el débito automático. Auditoría a los procesos de gestión de operaciones para identificar oportunidades de mejora en los diferentes procesos. | I11: 110500 | J11: 110500 | K11: 0 | L11: 7 - Ejecución y Administración de Procesos | M11: 71 - Recepción, Ejecución y Mantenimiento de Operaciones | N11: 711 - Exceso de Manualidad | O11: Ninguna | P11: 44592 | Q11: Crédito de consumo | R11: Ninguno | S11: 1016071699 | T11: JOHAN SANTIAGO CRUZ MARTÍN | U11: Analista.operativo2@febor.coop | V11: Aprobado | W11: 18/02/2022 16:48:20: Transacción de riesgo- Aumento de la cartera en mora por no aplicar oportunamente los descuentos de recaudo autorizados 18/02/2022 16:58:57: Transacción de riesgo- Aumento de la cartera en mora por no aplicar oportunamente los descuentos de recaudo autorizados | X11: Error en débitos automáticos | Z11: =+COUNTIF('Eventos-Tareas'!$D$22:$D$1048576,'Eventos de riesgos'!$B11) -> 1 | AA11: =+'Eventos de riesgos'!$I11-'Eventos de riesgos'!$J11-'Eventos de riesgos'!$K11 -> 0 | AB11: El débito automático de la cuota de una obligación crediticia no fue programado por error humano del analista responsable, generando un retraso de 8 días en el cobro y un vencimiento de la obligación. | AC11: No se programó el débito automático correspondiente a la cuota de $110.500 de la línea temporal de la asociada Olaine Salas Fuentes, cuya obligación vencía el 26 de diciembre de 2021. El débito fue aplicado hasta el 3 de enero de 2022. | AD11: El proceso de programación de débitos automáticos se realiza de forma manual mediante un listado en Excel. El analista responsable omitió incluir esta obligación en dicho listado. | AE11: Retraso de 8 días en el recaudo de la cuota. La obligación quedó registrada como vencida. El evento evidenció una debilidad en los controles del proceso manual de programación de débitos automáticos.
B12: 11 | C12: 2021 | D12: Dic | E12: 44535 | F12: 44536 | G12: 44536 | H12: Caso Se sobregiraron las cuentas de ahorros de aproximadamente 30 asociados por un total de $41.000.000 debido a que se realizaron operaciones de retiro el domingo 5 de diciembre/21 y la conexión entre Wog-Visionamos -Empacto no reflejó oportunamente aquellos giros efectuados. Las actualizaciones no quedan inmediatamente, se hacen 3 veces al día, pero el día del evento era fin de semana y el día siguiente, lunes 6 de diciembre/21 al realizar dichas actualizaciones se detecto el sobregiro. No se registra pérdidas económicas asumidas por la Cooperativa, se toman acciones inmediatas para la recuperación del dinero. Acciones Identificar los asociados con sobregiro para proceder a la recuperación de la operación o solicitud de la devolución del dinero. | I12: 41000000 | J12: 41000000 | K12: 0 | L12: 7 - Ejecución y Administración de Procesos | M12: 76 - Proveedores | N12: 763 - Incumplimiento de las Actividades Contratadas | O12: Ninguna | P12: 44561 | Q12: Ahorros voluntarios | R12: Ninguno | S12: 1016071699 | T12: JOHAN SANTIAGO CRUZ MARTÍN | U12: Analista.operativo2@febor.coop | V12: Aprobado | W12: 18/02/2022 16:43:37: Transacción de riesgo - Pérdidas económicas, de imagen y credibilidad en la ejecución de operaciones y transacciones, originado por fallas tecnológicas entre los aplicativos que conectan la operación de la Cooperativa. 18/02/2022 16:59:46: Transacción de riesgo- Pérdidas económicas, de imagen y credibilidad en la ejecución de operaciones y transacciones, originado por fallas tecnológicas entre los aplicativos que conectan la operación de la Cooperativa. | X12: Sobregiro de cuentas de ahorro voluntario | Z12: =+COUNTIF('Eventos-Tareas'!$D$22:$D$1048576,'Eventos de riesgos'!$B12) -> 1 | AA12: =+'Eventos de riesgos'!$I12-'Eventos de riesgos'!$J12-'Eventos de riesgos'!$K12 -> 0 | AB12: Falla en la conexión entre Wog, Visionamos y Empacto durante un fin de semana permitió retiros que generaron sobregiros en las cuentas de aproximadamente 30 asociados por $41 millones, detectados al día hábil siguiente. | AC12: El domingo 5 de diciembre de 2021, operaciones de retiro realizadas por aproximadamente 30 asociados no fueron reflejadas oportunamente en los sistemas por falla en la conexión entre Wog, Visionamos y Empacto, generando sobregiros por $41 millones. | AD12: La sincronización de operaciones se ejecuta tres veces al día, y al tratarse de un fin de semana, las actualizaciones no se realizaron con la oportunidad requerida, dejando pasar retiros que superaban los saldos reales disponibles. | AE12: Sobregiro en las cuentas de aproximadamente 30 asociados por un total de $41 millones. No se registraron pérdidas económicas asumidas por la Cooperativa, pero se requirieron acciones inmediatas para la recuperación del dinero.
B13: 12 | C13: 2022 | D13: Feb | E13: 44609.585 | F13: 44610.594 | G13: 44609.594 | H13: Caso El asociado WULFRAN ENRIQUE LOPEZ OJEDA identificado con cédula de ciudadanía 3726870, realizó un proceso de compra de cartera con la entidad Excelcredit, valiéndose de un paz y salvo valiéndose de la falsificación de un paz y salvo a nombre de Febor sobre los productos de crédito 1192902 y 111977 firmado por una persona que no trabaja en la Cooperativa (Beatriz Elene Henao Quintero). El jue, 17 feb 2022 a las 16:50, Ángela Carrillo (<acarrillo@excelcredit.co>) escribió a Febor: Cordial Saludo, Solicito su amable colaboración, procediendo con la suspensión o baja de descuento, del cliente en relación; teniendo en cuenta que le generamos compra de cartera. *Se adjunta soporte de pago y paz y salvo Cliente: WULFRAN ENRIQUE LOPEZ OJEDA C.c :3726870 Pagaduría: COLPENSIONES Febor responde lo siguiente: Buenas tardes Por medio de la presente nos permitimos informar que: 1.El paz y salvo adjunto no fue emitido por esta entidad cooperativa, ya que el asociado Wulfran Enrique lopez c.c. 3726870 tiene vigente el crédito Nª1192902 2.La persona que firma el certificado no es funcionario de Febor entidad cooperativa Por lo anterior no es procedente la solicitud en mención Acciones de la Cooperativa La Cooperativa mediante la jefatura jurídica inicia el debido proceso disciplinario con el asociado mencionado y se comunica a los funcionarios algunas recomendaciones importantes: 1 Recordemos que toda información de nuestros asociados es privada por tanto a ninguna persona, entidad, alto funcionario o quien quiera que solicite copias de cédulas, información de saldos, números de teléfono o demás NO es posible que lo brindemos incurrimos en una grave violación al deber de cuidado que tenemos con la autorización que nos brindan para proteger sus datos personales 2 Recordemos que las únicas firmas autorizadas para expedir certificaciones, paz y salvos y demás de este tipo son la dela Directora de Servicio al Asociado y el Gerente, por tanto generemos alerta inmediata cuando reciban llamadas para corroborar datos de este tipo de preguntar: fecha de la certificación, y quien la firma. Para control de todos considero importante que puedan incluir en pie de firma quien elaboró la certificación. 3 Proceso disciplinario - llamado de atención evaluado por la Junta de Vigilancia y el Consejo de Administración. 4 El Consejo de Administración decidió hacerle proceso de exclusión una vez que esté en firme el embargo de la mesada pensional. Sesión de Consejo 26 de noviembre 2022 | I13: 0 | J13: 0 | K13: 0 | L13: 1 - Fraude Interno | M13: 12 - Hurto y Fraude | N13: 125 Falsificación | O13: Ninguna | P13: 44620 | Q13: Crédito de consumo | R13: Canales de comunicación virtual | S13: 1020809741 | T13: Laura Nataly Arévalo Agredo | U13: asesor.sas9@febor.coop | V13: Aprobado | W13: 21/02/2022 14:24:58: Es importante en cada gestión que se realice en casos similares, tener las precauciones de revisar detalladamente la información y documentación recibida, confirmar hasta estar completamente seguro de que el proceso es real y transparente, dado que podrían existir métodos de falsificación de mayor nivel con dificultad de detección. | X13: Falsificación de documentos por parte de un asociado | Z13: =+COUNTIF('Eventos-Tareas'!$D$22:$D$1048576,'Eventos de riesgos'!$B13) -> 1 | AA13: =+'Eventos de riesgos'!$I13-'Eventos de riesgos'!$J13-'Eventos de riesgos'!$K13 -> 0 | AB13: Un asociado presentó paz y salvo falsificado ante la entidad Excelcredit para gestionar compra de cartera, utilizando firmas de personas ajenas a Febor. El documento fue validado sin detección del fraude, exponiendo a la Cooperativa a riesgo de cartera. | AC13: El asociado Wulfran Enrique López Ojeda presentó ante Excelcredit un paz y salvo falsificado a nombre de Febor sobre dos productos de crédito, firmado por una persona que no pertenece a la Cooperativa, con el fin de realizar una compra de cartera. | AD13: Falsificación de documentos por parte del asociado, aprovechando la ausencia de controles cruzados entre Febor y terceras entidades en la validación de paz y salvos para procesos de compra de cartera. | AE13: Riesgo de cartera para Febor por la posible suspensión del descuento de nómina. Exposición reputacional por uso fraudulento de documentos institucionales. Se requirió tramitación jurídica para aclarar la situación.
B14: 13 | C14: 2022 | D14: Abr | E14: 44655.406 | F14: 44656.406 | G14: 44655.406 | H14: Caso El día 4 de abril se detectaron errores en el sistema transaccional y en general de varios módulos de operación en Wog, debido a que este sistema tuvo cambio de versión el fin de semana (2 y 3 de abril) por la incorporación del modelo de originación en la fabrica de créditos. No se presentaron pérdidas económicas, ni se afectaron productos de los asociados ya que durante la ocurrencia se daba solución a las novedades por parte del área de tecnología y operaciones. Acciones Comunicación inmediata con el proveedor para la corrección de reportes y módulos afectados. El proveedor debe informar las actualizaciones y cambios de versión antes y prevenir a la entidad de los posibles daños. | I14: 0 | J14: 0 | K14: 0 | L14: 6 - Fallas Tecnologicas | M14: 61 - Sistemas | N14: 611 - Pérdida por Problemas en Software | O14: Ninguna | P14: 44681 | Q14: Ninguno | R14: Ninguno | S14: 1033706838 | T14: Diana Maribel Fonseca Gómez | U14: direccion.riesgos@febor.coop | V14: Aprobado | W14: 05/04/2022 09:47:50: Evento registrado desde el área de riesgos | X14: Errores por actualizaciones en Wog | Z14: =+COUNTIF('Eventos-Tareas'!$D$22:$D$1048576,'Eventos de riesgos'!$B14) -> 1 | AA14: =+'Eventos de riesgos'!$I14-'Eventos de riesgos'!$J14-'Eventos de riesgos'!$K14 -> 0 | AB14: El cambio de versión del sistema Wog durante el fin de semana generó errores en múltiples módulos operativos el día hábil siguiente, afectando temporalmente la operación. No se presentaron pérdidas ni afectación de productos de asociados. | AC14: El 4 de abril se detectaron errores en el sistema transaccional Wog y en varios módulos de operación, como consecuencia de un cambio de versión realizado durante el fin de semana del 2 y 3 de abril por la incorporación del modelo de originación en la fábrica de créditos. | AD14: Actualización de versión del sistema Wog sin pruebas previas suficientes ni comunicación anticipada a las áreas usuarias sobre los posibles impactos y errores esperados tras la implementación. | AE14: Errores en múltiples módulos del sistema transaccional durante el día hábil posterior al cambio. No se registraron pérdidas económicas ni afectación de productos de asociados, pero se generó sobrecarga operativa en las áreas de tecnología y operaciones.
B15: 14 | C15: 2022 | D15: May | E15: 44686.899 | F15: 44687.899 | G15: 44687.899 | H15: Caso Se presenta un caso de inconformidad por fallas en el proceso de consignación por cheque y tiempo de espera en la liberación de canje el 6 de mayo 2022. Mensaje del asociado Marco a la Gerencia: El pasado lunes, aproximadamente a la una de la tarde, consigné en la oficina de Febor del edificio anexo un cheque de gerencia para ser abonado a la cuenta de ahorros voluntarios, por valor de 82 millones. Considerando que el canje debe tardar, a lo sumo, 3 días, ayer jueves en la tarde le solicité vía WhatsApp a Jorge Lievano que del producto de esa consignación me hiciera el favor de hacer un pago por $80 millones a capital del crédito de reestructuración solidaria, Jorge me contesta después de unos minutos que el cheque todavía no ha sido confirmado el canje, yo le hice la observación en el sentido que consideraba que desde el lunes no era razonable que el canje no se hubiera dado, cuando se sabe que el canje normalmente demora 2 días. Hoy viernes alrededor de medio día volví a preguntarle a Jorge sobre la operación, me comentó que él estaba pendiente, pero que contabilidad, u operaciones todavía no le daba conformidad sobre el canje del cheque, a lo que volví a hacerle la observación sobre que no encontraba razonable tanta demora en el canje. Ante esta nueva situación, decidí llamar a Teresita y pedirle que me colaborara, hasta que finalmente hace un rato Jorge me confirmó que la operación de pago al crédito se hizo. El caso es que si yo no estoy pendiente e indagando, la plata queda depositada en la cuenta de Febor por varios días, sin aplicar ni a mi cuenta de ahorros voluntarios, ni para hacer el pago al crédito y por supuesto al no darse ese pago se causan intereses sobre mi crédito sin tener en cuenta que la plata ya está en poder de Febor desde hace varios días; sino hubiera estado yo pendiente la operación hubiera quedado para la semana entrante. En mi caso, porque tengo la posibilidad de llamar a Teresita y solicitarle colaboración, veo que Jorge no tiene culpa, porque el fué diligente cuando yo le hice la solicitud, simplemente él no podía hacer la operación mientras no le dieran la conformidad del canje. ________________ Se evalúa con el área de operaciones si el canje lo libera automáticamente el sistema, y si tiene un funcionario responsable de su verificación, además de definir el tiempo que debe durar en canje el cheque, que sea estrictamente lo necesario (máx. 3 días) Acciones El sistema tiene programados los días de liberar los cheques de canje (3 días), se ordena por parte de Gerencia disminuir los días a (1) en el sistema | I15: 0 | J15: 0 | K15: 0 | L15: 7 - Ejecución y Administración de Procesos | M15: 71 - Recepción, Ejecución y Mantenimiento de Operaciones | N15: 713 - Incumplimiento de Plazos o Responsabilidades | O15: Ninguna | P15: 44712 | Q15: Ahorros voluntarios | R15: Buzón Quejas y Reclamos | S15: 1033706838 | T15: Diana Maribel Fonseca Gómez | U15: direccion.riesgos@febor.coop | V15: Aprobado | W15: 07/05/2022 21:38:37: Información tomada de la presentación del caso por el grupo de dirección en WhatsApp por parte de la Gerencia | X15: Demoras en canje de cheques de asociados | Z15: =+COUNTIF('Eventos-Tareas'!$D$22:$D$1048576,'Eventos de riesgos'!$B15) -> 1 | AA15: =+'Eventos de riesgos'!$I15-'Eventos de riesgos'!$J15-'Eventos de riesgos'!$K15 -> 0 | AB15: Un asociado expresó inconformidad ante la Gerencia por demoras en la liberación del canje de un cheque de $82 millones consignado en la oficina. El proceso de consignación presentó fallas en el tiempo de respuesta y en la comunicación con el asociado. | AC15: El asociado Marco manifestó inconformidad por fallas en el proceso de consignación de un cheque de gerencia por $82 millones y por el tiempo de espera en la liberación del canje, que superó los 3 días habituales. | AD15: Demoras en el proceso de confirmación del canje bancario y falta de comunicación proactiva hacia el asociado sobre el estado de su operación, generando insatisfacción y escalamiento a la Gerencia. | AE15: Inconformidad del asociado y afectación en la percepción del servicio. El asociado no pudo realizar operaciones con los recursos de la consignación dentro del tiempo esperado, evidenciando debilidades en el proceso de canje y en los tiempos de respuesta al cliente.
B16: 15 | C16: 2022 | D16: Abr | E16: 44679.722 | F16: 44679.722 | G16: 44679.722 | H16: Caso El señor Luis Eduardo Rosales, ciudadano no asociado a la Cooperativa presento una queja ante la SES , inconforme por recibir correos con extractos bancarios que no le corresponden, pero que si le corresponden al asociado Luis Eduardo Rosales. La confusión consiste en envio de correo errado a luiseduardorosales@gmail.com y el correcto es luiseduardorosales08@gmail.com. Acciones A. La funcionaria Rina Herrera se comunicó con el asociado Luis Eduardo Rosales y efectivamente el correo de él es luiseduardorosales08@gmail.com, adicional contactará al señor Luis Rosales y se le indicará que no va a volver a recibir estos correos por parte de Febor Entidad Cooperativa. Se verifica sistema de encriptación frente a Base social, para que el problema sea solucionado de raíz, actualizándolo en el sistema Wog. Se verifica uno a uno los asociados a los que se les envío extractos de tarjeta crédito, para constatar que no hubo más inconsistencias, lo cual solo se presentó con este asociado. Se dio respuesta a la queja del ciudadano con conocimiento de la Junta de vigilancia y con copia a la Superintendencia de Economía Solidaria. | I16: 0 | J16: 0 | K16: 0 | L16: 7 - Ejecución y Administración de Procesos | M16: 71 - Recepción, Ejecución y Mantenimiento de Operaciones | N16: 719 - Seguridad de la Información | O16: Ninguna | P16: 44681 | Q16: Tarjeta crédito | R16: Buzón Quejas y Reclamos | S16: 1033706838 | T16: Diana Maribel Fonseca Gómez | U16: direccion.riesgos@febor.coop | V16: Aprobado | W16: 24/05/2022 17:21:30: La queja respuesta se proyecta, se traslada a junta de vigilancia para ser respondida al ciudadano con copia a la SES | X16: Manejo de datos personales | Z16: =+COUNTIF('Eventos-Tareas'!$D$22:$D$1048576,'Eventos de riesgos'!$B16) -> 2 | AA16: =+'Eventos de riesgos'!$I16-'Eventos de riesgos'!$J16-'Eventos de riesgos'!$K16 -> 0 | AB16: Se envió por error extractos bancarios de un asociado al correo de un tercero no vinculado a Febor, quien presentó queja ante la SES por recibir información que no le correspondía, evidenciando una falla en la gestión de datos de contacto. | AC16: Extractos bancarios del asociado Luis Eduardo Rosales fueron enviados al correo incorrecto luiseduardorosales@gmail.com en lugar del correcto luiseduardorosales08@gmail.com, siendo recibidos por un ciudadano no asociado que radicó queja ante la SES. | AD16: Error en el registro del correo electrónico del asociado en el sistema, sumado a la ausencia de controles de validación en el proceso de envío de extractos. | AE16: Exposición de información financiera confidencial de un asociado a un tercero no autorizado. Queja ante la SES por parte del ciudadano afectado. Riesgo de incumplimiento normativo en protección de datos personales.
B17: 16 | C17: 2022 | D17: May | E17: 44702.542 | F17: 44703.438 | G17: 44705.875 | H17: Caso Se presenta desconexión del servicio entre visionamos - Empacto - WOG el día 21 de mayo de 2022, que produce que las operaciones que los asociados realizaron con su tarjeta debito, su cuenta de ahorro, o sus cupos rotativos y avance no fueran registradas en el producto pero si fueron ejecutadas correctamente por visionamos y compensadas a Febor un total de 42 asociados. Diariamente se validan que las operaciones del día anterior sean ejecutadas en su totalidad en los productos correspondientes, el día Lunes 23 de mayo de 2022 se evidencian operaciones que presentan diferencias por lo cual se procede a remitir la información a contabilidad para validar si estas fueron compensadas por visionamos a febor. por parte de wog el 24 solicitan el envió el archivo AUT por medio del cual registran las operaciones que reporta visionamos y son cargados a los productos en WOG, una vez identifican las diferencias proceden a aplicarlas en producto con fecha 24 al cierre del día y en la descripción se diligencia que corresponden al 21 de mayo de 2022. Se debe validar la forma como monitorear en linea las desconexiones entre visionamos - Empacto - WOG, con el fin de realizar las acciones correctivas con mayor prontitud. Acciones Identifican las diferencias en los saldos y aplicar correcciones en el producto. | I17: 9649785 | J17: 9649785 | K17: 0 | L17: 6 - Fallas Tecnologicas | M17: 61 - Sistemas | N17: 614 - Interrupción en el Suministro de un Servicio Público que Ocasiones Falla en los Sistemas | O17: Ninguna | P17: 44712 | Q17: Ahorros voluntarios | R17: Ninguno | S17: 1018433978 | T17: Nataly Malagón | U17: operaciones@febor.coop | V17: Aprobado | W17: 25/05/2022 15:55:14: Reporte Evento SARO link 26/05/2022 12:36:41: Caso recibido, revisado por Dirección Riesgos | X17: Falla en operaciones electrónicas originadas por el proveedor | Z17: =+COUNTIF('Eventos-Tareas'!$D$22:$D$1048576,'Eventos de riesgos'!$B17) -> 1 | AA17: =+'Eventos de riesgos'!$I17-'Eventos de riesgos'!$J17-'Eventos de riesgos'!$K17 -> 0 | AB17: Desconexión entre Visionamos, Empacto y Wog el 21 de mayo de 2022 impidió que 42 operaciones realizadas con tarjeta débito, ahorros y cupos rotativos fueran registradas oportunamente en los productos correspondientes de los asociados. | AC17: El 21 de mayo de 2022 se presentó desconexión entre los sistemas Visionamos, Empacto y Wog, lo que impidió que las operaciones realizadas por 42 asociados con tarjeta débito, cuenta de ahorro y cupos rotativos fueran registradas correctamente en sus productos. | AD17: Falla en la integración tecnológica entre los sistemas transaccionales de los proveedores Visionamos, Empacto y el core Wog, lo que generó diferencias entre las operaciones compensadas y las registradas. | AE17: 42 asociados vieron afectado el registro de sus operaciones en los productos financieros. Se requirió intervención del área contable y de operaciones para conciliar y corregir los movimientos afectados.
B18: 17 | C18: 2022 | D18: May | E18: 44704.5 | F18: 44712.792 | G18: 44704.542 | H18: Caso El pasado lunes 23 de mayo, nuestra cajera de Mazuren Laura Nataly Arevalo tuvo un descuadre en cajera por $1.100.000- el mismo día al cierre luego de haber hecho todos los cruces respectivos informo del faltante y aseguro saber a que asociada le habia dado el dinero de mas, así mismo, informo que la llamo y la sra informo no tener el dinero de sobra. El martes 24 nuestra asociada se acerco a la oficina del centro y entrego un millón de pesos. Al revisar el video del momento de la atención en caja de la asociada, no se evidencia cual pudo haber sido la falla puntual, sin embargo considero que pudo darse por que la asesora tenia dinero en la maquina contadora. Valga le pena mencionar que es la primera vez que se presenta un descuadre en cabeza de nuestra asesora Laura Nataly Arevalo quien es la encargada de la caja desde 01 de septiembre en nuestra extensión de caja de Mazuren. Acciones Recuperación y devolución del dinero a la caja. Esta tarea la debe realizar la asesora Nataly Arévalo. | I18: 1100000 | J18: 1100000 | K18: 0 | L18: 7 - Ejecución y Administración de Procesos | M18: 71 - Recepción, Ejecución y Mantenimiento de Operaciones | N18: 718 - Error en Otras Tareas, Falla en la Entrega | O18: Ninguna | P18: 44712 | Q18: Ninguno | R18: Atención en oficina (caja) | S18: 53166187 | T18: Johana Cortés | U18: direccion.sas@febor.coop | V18: Aprobado | W18: 31/05/2022 07:37:29: Reporte Evento SARO link 01/06/2022 10:24:23: Se sugiere que el cajero tenga claro su procedimiento de operación en caja: 1. Se atiende un asociado a la vez 2. Se ingresa el dinero , se cuenta se guarda y se realiza la operación ( no dejar dinero en la maquina contadora) 3. Si se entrega dinero, grabar la operación, tomar el dinero, contarlo en la maquina, entregarlo y solicitar al asociado que confirme la cantidad entregada 4. Evitar distracciones durante las operaciones en caja (celulares, hablar con compañeros o demás visitantes etc.) | X18: Descuadre en caja | Z18: =+COUNTIF('Eventos-Tareas'!$D$22:$D$1048576,'Eventos de riesgos'!$B18) -> 1 | AA18: =+'Eventos de riesgos'!$I18-'Eventos de riesgos'!$J18-'Eventos de riesgos'!$K18 -> 0 | AB18: La cajera de la oficina Mazurén presentó un faltante de $1.100.000 al cierre del día por error en la entrega de efectivo a una asociada. El dinero fue recuperado parcialmente ($1.000.000) al día siguiente. | AC18: La cajera Laura Nataly Arévalo de la oficina Mazurén presentó un faltante de $1.100.000 al cierre del día 23 de mayo, identificando haber entregado por error dinero de más a una asociada. | AD18: Error humano en el manejo de efectivo durante la atención en caja, posiblemente asociado a la manipulación de dinero en la máquina contadora mientras se atendía a la asociada. | AE18: Faltante de $1.100.000 en caja. Se recuperaron $1.000.000 al día siguiente cuando la asociada los devolvió voluntariamente, quedando un faltante residual de $100.000.
B19: 18 | C19: 2022 | D19: May | E19: 44711.635 | F19: 44711.636 | G19: 44712.917 | H19: Caso Fallas en los sistemas retrasan la operación por casi dos horas, esto se debe a que se ejecutaron varios procesos masivos al tiempo y dado que los dos apuntan directamente a la base de datos, se estaban cargando créditos al mismo tiempo y adicionalmente se estaban procesando los archivos de Tarjeta de Crédito (que provienen de ASNET) los cuales generaron conflicto con el procesamiento del servidor. Al contactar con urgencia al proveedor WOG para solucionar el conflicto se tuvo los siguientes inconvenientes: Falta de soporte y prontitud del proveedor en las respuestas de solución. Burocracia en la toma de decisiones por parte del proveedor para la solución inmediata del problema. Esta afectación se evidencia por falta de monitoreo por parte del proveedor WOG, dado que ellos son los que administran la aplicación y determinan los procesos que afectan en gran escala al sistema. Acciones Comunicación inmediata con el proveedor para la corrección de reportes y módulos afectados Verificar la capacidad del servidor, evaluar lo que se requiere para que el rendimiento del sistema no disminuya por la ejecución de varios procesos. | I19: 0 | J19: 0 | K19: 0 | L19: 6 - Fallas Tecnologicas | M19: 61 - Sistemas | N19: 611 - Pérdida por Problemas en Software | O19: Ninguna | P19: 44712 | Q19: Varios tipos de crédito | R19: Ninguno | S19: 1010200415 | T19: Jasson Cepeda | U19: coordinador.informatica@febor.coop | V19: Aprobado | W19: 03/06/2022 12:24:42: Reporte Evento SARO link 05/06/2022 15:35:27: Desde el área de tecnología, se debe verificar la capacidad del servidor, evaluar lo que se requiere para que el rendimiento del sistema no disminuya por la ejecución de varios procesos. Se deben generar las recomendaciones preventivas para el buen manejo del sistema a los funcionarios con acceso a operaciones delicadas. | X19: Indisponibilidad Core Financiero Wog | Z19: =+COUNTIF('Eventos-Tareas'!$D$22:$D$1048576,'Eventos de riesgos'!$B19) -> 2 | AA19: =+'Eventos de riesgos'!$I19-'Eventos de riesgos'!$J19-'Eventos de riesgos'!$K19 -> 0 | AB19: La ejecución simultánea de múltiples procesos masivos sobre la base de datos del sistema WOG generó una interrupción de casi dos horas en la operación, agravada por la lentitud en la respuesta del proveedor para resolver la incidencia. | AC19: Se presentó una falla en el sistema Wog que detuvo la operación de la Cooperativa por casi dos horas, causada por la ejecución simultánea del cargue de créditos y el procesamiento de archivos de tarjeta de crédito provenientes de ASNET, generando conflicto en el servidor. | AD19: Ejecución de múltiples procesos masivos simultáneos que apuntaban directamente a la base de datos, sumada a la falta de monitoreo activo por parte del proveedor Wog y su demora en la atención y resolución de la incidencia. | AE19: Interrupción de la operación por aproximadamente dos horas. Afectación en la prestación del servicio a los asociados. Se evidenciaron debilidades en el soporte del proveedor Wog y en la coordinación ante contingencias tecnológicas.
B20: 19 | C20: 2022 | D20: May | E20: 44705.417 | F20: 44705.417 | G20: 44705.417 | H20: Caso El gerente Juan Pablo Vélez reporta como evento de riesgo la carencia y debilidad en el proceso de reporte de eventos de riesgo por parte de los funcionarios, a pesar de llevar a cabo capacitación al respecto, es necesario promover e intensificar el esfuerzo al respecto. Es necesario y obligatorio que todos los funcionarios conozcan el proceso y los medios para reportar eventos de riesgo y hacerlo de manera oportuna. Acciones Sensibilización a los funcionarios sobre el reporte de eventos de riesgo mediante cápsulas de conocimiento, reuniones con el personal y guía en la elaboración de reportes directamente a los jefes de área. | I20: 0 | J20: 0 | K20: 0 | L20: 7 - Ejecución y Administración de Procesos | M20: 72 - Seguimiento y Presentación de Informes | N20: 721 - Incumplimiento de la Obligación de Informar | O20: Ninguna | P20: 44712 | Q20: Ninguno | R20: Ninguno | S20: 72179606 | T20: Juan Pablo Vélez | U20: gerencia@febor.coop | V20: Aprobado | W20: 06/06/2022 14:19:46: El área de riesgos debe continuar fortaleciendo la cultura institucional basada en los procesos de riesgos. | X20: Empleados no reportan RO | Z20: =+COUNTIF('Eventos-Tareas'!$D$22:$D$1048576,'Eventos de riesgos'!$B20) -> 1 | AA20: =+'Eventos de riesgos'!$I20-'Eventos de riesgos'!$J20-'Eventos de riesgos'!$K20 -> 0 | AB20: Se identificó una debilidad estructural en el proceso de reporte de eventos de riesgo por parte de los funcionarios de Febor, a pesar de las capacitaciones realizadas, evidenciando baja apropiación de la cultura de gestión de riesgos. | AC20: La Gerencia identificó y reportó como evento de riesgo la carencia y debilidad en el proceso de reporte de eventos de riesgo por parte de los funcionarios, a pesar de las capacitaciones previas realizadas al respecto. | AD20: Insuficiente apropiación de la cultura de gestión de riesgos por parte del personal. Falta de sensibilización y conocimiento sobre los medios y la obligatoriedad del reporte oportuno de eventos. | AE20: Subregistro de eventos de riesgo que puede generar un panorama de riesgo incompleto para la Cooperativa. Dificultades para cumplir con las exigencias del SARO y para adoptar medidas preventivas y correctivas oportunas.
... B31: 30 | C31: 2022 | D31: Oct | E31: 44861.48 | F31: 44861.48 | G31: 44861.48 | H31: Caso Los asociados manifiestan que no pueden hacer pagos mediante la Cooperativa Digital porque no está en funcionamiento, no permite ingresar. Esta falla es escalada a Wog mediante la Jefe de Operaciones Nataly Malagón. (foto) Wog se encuentra en proceso de validación - pendiente cierre de la novedadSe activa el servicio nuevamente (foto) Acciones Reportar incidencia a Wog sobre las fallas presentadas en la Cooperativa Digital (Jefe de Operaciones) Seguimiento a la incidencia hasta comprobar que funcione correctamente la Cooperativa Digital (Jefe de Operaciones) | I31: 0 | J31: 0 | K31: 0 | L31: 6 - Fallas Tecnologicas | M31: 61 - Sistemas | N31: 611 - Pérdida por Problemas en Software | O31: Ninguna | P31: 44865 | Q31: Varios tipos de crédito | R31: Cooperativa Digital | S31: 53166187 | T31: JOHANA PAOLA CORTÉS GÓMEZ | U31: direccion.sas@febor.coop | V31: Aprobado | W31: 27/10/2022 11:32:36: Pendiente cambio de proceso afectado por configuración del sistema 27/10/2022 11:36:14: Cargue de seguimiento WOG 27/10/2022 11:53:27: Cierre de la falla operativa 27/10/2022 11:56:07: Cambio de canal afectado a Cooperativa Digital | X31: Fallas Cooperativa Digital | Z31: =+COUNTIF('Eventos-Tareas'!$D$22:$D$1048576,'Eventos de riesgos'!$B31) -> 2 | AA31: =+'Eventos de riesgos'!$I31-'Eventos de riesgos'!$J31-'Eventos de riesgos'!$K31 -> 0 | AB31: La plataforma Cooperativa Digital presentó fallas de acceso que impidieron a los asociados realizar pagos, afectando la prestación del servicio en el canal digital. La incidencia fue escalada a Wog para su solución. | AC31: Los asociados reportaron que no podían realizar pagos a través de la Cooperativa Digital debido a que la plataforma no permitía el ingreso, mostrando errores de acceso. | AD31: Falla técnica en la plataforma Cooperativa Digital administrada por el proveedor Wog, que generó indisponibilidad del canal para los asociados. | AE31: Imposibilidad de realizar pagos en línea para los asociados. Insatisfacción por la indisponibilidad del canal digital. Requirió escalamiento y seguimiento con el proveedor Wog para la reactivación del servicio.
B32: 31 | C32: 2022 | D32: Nov | E32: 44893.534 | F32: 44893.534 | G32: 44895.534 | H32: Caso Se recibió el retiro del asociado Helena Castro de Caicedo con CC 28.505.906 a razón del fallecimiento 10 de septiembre de 2022, cuya reclamación a la aseguradora fue aprobada a Febor el día 25 de noviembre, en el momento que se estaban realizando las validaciones correspondientes se evidencia que el día 28 de noviembre de 2022 se realizo un retiro de la cuenta del ahorro voluntario por valor de $1.143.000 a través de la cooperativa digital a la cuenta de Carmen Analida Caicedo Castro quien se encontraba inscrita como tercero de asociado fallecido. Por lo cual se evidencia que hay una suplantación de identidad y se conocían las credenciales de ingreso a la cooperativa digital con las cuales se realizo el fraude al asociado Q.E.P.D. Acciones Trámite jurídico, contacto con los familiares titulares (Jefe Jurídico) Modificación de procedimiento de retiro de asociados por fallecimiento, para analizar bloqueo de credenciales de asociados fallecidos para evitar transferencias de terceros por medio de la Cooperativa Digital.(Jefe de Operaciones) | I32: 1143000 | J32: 0 | K32: 0 | L32: 1 - Fraude Interno | M32: 11 - Actividades No Autorizadas | N32: 111 - Operaciones No Reveladas Intencionalmente | O32: Ninguna | P32: 44895 | Q32: Ahorros voluntarios | R32: Cooperativa Digital | S32: 1018433978 | T32: Natali Malagon Sierra | U32: operaciones@febor.coop | V32: Aprobado | X32: Retiro de ahorro de asociado fallecido | Z32: =+COUNTIF('Eventos-Tareas'!$D$22:$D$1048576,'Eventos de riesgos'!$B32) -> 2 | AA32: =+'Eventos de riesgos'!$I32-'Eventos de riesgos'!$J32-'Eventos de riesgos'!$K32 -> 1143000 | AB32: Se realizó un retiro fraudulento de $1.143.000 de la cuenta de ahorro de un asociado fallecido a través de la Cooperativa Digital, utilizando sus credenciales. El fraude fue ejecutado por un tercero inscrito como destinatario de transferencias. | AC32: El 28 de noviembre de 2022 se realizó un retiro de $1.143.000 desde la cuenta de ahorro voluntario del asociado fallecido Helena Castro de Caicedo a través de la Cooperativa Digital, hacia la cuenta de Carmen Analida Caicedo Castro, quien estaba inscrita como tercero. | AD32: Suplantación de identidad del asociado fallecido mediante el uso de sus credenciales de acceso a la Cooperativa Digital, posiblemente por un familiar que conocía los datos de acceso. | AE32: Pérdida de $1.143.000 de los recursos del asociado fallecido. Riesgo legal y reputacional para la Cooperativa. Se requirió trámite jurídico y contacto con los familiares para gestionar la situación.
B33: 32 | C33: 2022 | D33: Nov | E33: 44893.517 | F33: 44894.518 | G33: 44894.518 | H33: Caso El día 29 de noviembre el asociado Guillermo de comunicó a través del PBX sobre el medio día, informando que en la madrugada de ese mismo día se comunicaron de Coopcentral a confirmar si estaba realizando unas transferencias por 2 millones de pesos, donde el informó que no era él y de inmediato el banco le confirma el bloqueo de la cuenta. El banco le comenta que debe comunicarse con la cooperativa, al yo recibir la solicitud me acerque al área operativa para verificar la información y poderle brindar una respuesta al asociado el cual yo le informe que no se habían realizado las transferencias pero luego de realizar una verificación de movimientos se pudo corroborar que si se habían realizado dos retiros, le informe que monto tenía actualmente que correspondía a 800 mil pesos, efectivamente verificando Coopcentral había enviado un correo de aviso del fraude que se había evidenciado del asociado, le pregunté a Nataly jefe del área operativa que como podía manejar este caso en donde me responde que se va a reportar al banco para realizar seguimiento del caso y adicional que tocaba esperar la respuesta de ellos, luego el asociado me informo que precisamente el día de ayer (28 de noviembre) se había comunicado con una asesora de Febor para realizar el cambio de clave, le pregunte que si recordaba el nombre informando que no que le diera los nombres de mis compañeras y llegó a la conclusión de que lo atendió Laura Camila, y le realice varias preguntas sobre cómo había procedido Camila con el cambio de clave en donde me comenta que no recuerda si realizo el cambio de clave o le dejó la que ella le asignó, de igual manera le pregunte de que número se había comunicado el día anterior para poder buscar la conversación pero como se comunicó del teléfono del banco le informe que era un poco más complicado buscar dicha conversación pero que sin embargo íbamos a ponernos en la tarea de tratar de solucionar lo más pronto posible el inconveniente. Acciones Reconocimiento del dinero al asociado de manera inmediata para no generar mal malestar y mala imagen hacia Febor Tramitar con la aseguradora y Coopcentral para el retorno del dinero a Febor. El 04 de abril, la aseguradora solicitó a Febor los documentos que soportan la investigación del caso, el extracto de la cuenta de ahorros y la bitácora de movimientos, así como copia de las respuestas dadas por el Banco Cooperativo Concentrar y Visionamos. Tales documentos fueron recopilados y enviados a la aseguradora el 19 de abril bajo el radicado Siniestro Nro. 10270420 Caso OnBase 15918. A la fecha, no se ha obtenido respuesta. | I33: 4000000 | J33: 0 | K33: 0 | L33: 2 - Fraude Externo | M33: 22 - Hurto y Fraude | N33: 221 - Robo o Hurto | O33: Ninguna | P33: 44895 | Q33: Ahorros voluntarios | R33: Comunicación por PBX | S33: 1024558299 | T33: Manuela Vélez yara | U33: asesor.sas12@febor.coop | V33: Aprobado | X33: Suplantacion de Identidad y robo a asociados | Z33: =+COUNTIF('Eventos-Tareas'!$D$22:$D$1048576,'Eventos de riesgos'!$B33) -> 2 | AA33: =+'Eventos de riesgos'!$I33-'Eventos de riesgos'!$J33-'Eventos de riesgos'!$K33 -> 4000000 | AB33: Terceros realizaron transferencias no autorizadas de $1.200.000 desde la cuenta de ahorro del asociado Guillermo, mediante dos retiros sucesivos. El hecho fue reportado al asociado por Coopcentral y confirmado por Febor. | AC33: El 29 de noviembre, el asociado Guillermo reportó que en la madrugada se realizaron transferencias no autorizadas de su cuenta de ahorros voluntarios por un valor de $1.200.000 en dos retiros, hecho que fue alertado inicialmente por Coopcentral. | AD33: Acceso no autorizado a los productos del asociado por parte de terceros, quienes realizaron dos retiros sucesivos sin el conocimiento ni consentimiento del titular. | AE33: Pérdida de $1.200.000 de los recursos del asociado. El saldo restante en la cuenta era de $800.000. Se generó malestar en el asociado y riesgo reputacional para la Cooperativa por la seguridad de sus productos transaccionales.
B34: 33 | C34: 2022 | D34: Nov | E34: 44697.847 | F34: 45133.847 | G34: 44895.847 | H34: Caso a) El Crédito No. 1243992 fue desembolsado a la señora Carmen Valderrama de Borrero (QEPD), quien se identificaba con la Cédula de Ciudadanía No. 26612306, el 17 de diciembre del 2020 por cuantía de $65.000.000 pesos m/cte. b) Que, el pago del crédito en cita se difirió en 64 cuotas mensuales, con una Tasa Efectiva Anual (T.E.A) del 12,44% y su recaudo se estipuló mediante libranza o descuento directo por nómina. c) La señora Carmen Valderrama de Borrero falleció el 16 de mayo del 2022 en la ciudad de Neiva, hecho jurídico que consta en el Registro Civil de Defunción con Indicativo Serial No. 10697607 del 19 de mayo del 2022, expedido por la Notaría Segunda (02) del Círculo de Neiva. d) Que, a la fecha del deceso, la deudora tan solo pago 13 cuotas del crédito, quedando un saldo pendiente por pagar de $43.735.566 pesos m/cte. e) El 09 de junio del 2022 se formuló la reclamación del siniestro ante la Aseguradora La Equidad bajo el caso No. 133799. f) El 13 de junio del 2022, la Equidad Seguros O.C. comunicó a Febor que la indemnización fue definida y liquidada. De este modo, se elaboró una cuenta por cobrar por la suma de $43.735.566 a la Equidad Seguros y así proseguir con el pago de los ahorros a los herederos de la asociada. g) El 07 de julio del 2022, los herederos de la señora Carmen Valderrama de Borrero (QEPD) radicaron en Febor la reclamación del saldo acumulado en aportes, ahorros y depósitos a nombre de la difunta. La transacción a los herederos se llevó a cabo el 14 de julio del 2022 por el saldo evidenciado en el ahorro voluntario. h) El 26 de julio del 2022, La Equidad Seguros O.C. objetó parcialmente la reclamación por la suma de $23.735.566, toda vez que, al momento del fallecimiento, la asociada contaba con 91 años y, al interior de las condiciones de asegurabilidad de la póliza vida deudores AA002483, se estipuló que la cobertura para muerte, por cualquiera causa, de asociados mayores de 90 años, tendrá un límite de valor asegurado de $20.000.000 de pesos. i) En consecuencia, el saldo de $23.735.566 de pesos no se encuentra amparado por la póliza AA002483, de acuerdo con lo estipulado en el Artículo 1079 del Código de Comercio. j) Una vez consultados los registros de bienes que administra la Superintendencia de Notariado y Registro, se observa que no figuran inmuebles a nombre de la deudora. Acciones Tramite jurídico y proceso con aseguradora (Jefe Jurídico) | I34: 23735566 | J34: 0 | K34: 0 | L34: 7 - Ejecución y Administración de Procesos | M34: 75 - Contrapartes Comerciales | N34: 751 - Pérdida por Fallas con Contrapartes | O34: Ninguna | P34: 44895 | Q34: Crédito de consumo | R34: Ninguno | S34: 1016072548 | T34: Andrés Camilo Forero García | U34: juridica@febor.coop | V34: Aprobado | W34: 14/12/2022 20:22:26: Caso cerrado por reconocimiento de la aseguradora y concepto emitido | X34: Crédito sin cobertura de aseguradora | Z34: =+COUNTIF('Eventos-Tareas'!$D$22:$D$1048576,'Eventos de riesgos'!$B34) -> 1 | AA34: =+'Eventos de riesgos'!$I34-'Eventos de riesgos'!$J34-'Eventos de riesgos'!$K34 -> 23735566 | AB34: La aseguradora objetó la reclamación del siniestro por el crédito de una asociada fallecida por $65 millones, argumentando que la deudora presentaba una preexistencia médica no declarada al momento de la vinculación. | AC34: La aseguradora objetó la reclamación del siniestro correspondiente al crédito No. 1243992 por $65 millones de la señora Carmen Valderrama de Borrero (QEPD), quien falleció el 16 de mayo de 2022 tras haber pagado solo 13 de las 64 cuotas pactadas. | AD34: La aseguradora argumentó que la asociada fallecida presentaba preexistencias médicas no declaradas al momento de la vinculación, lo que dio lugar a la objeción del siniestro. | AE34: Exposición de Febor a una pérdida de $65 millones por el saldo insoluto del crédito. Se requirió gestión jurídica para controvertir la objeción de la aseguradora y defender el derecho al pago del siniestro.
B35: 34 | C35: 2022 | D35: Dic | E35: 44887.428 | F35: 44946.428 | G35: 44908.428 | H35: Caso Fue radicada la factura de renovación de la Póliza Multirriesgo por daño material el 17 de noviembre 2022 (20228000072812) la cual fue archivada por parte del asesor de gestión documental, de tal manera que no se continuo su tramite para finalizar su aprobación y pago. El 13 de diciembre se detecta el error en el área de riesgos, se solicita reactivar el trámite de pago de la póliza con la autorización de gerencia. La causa del error se ocasionó por falla humana del funcionario encargado, recientemente contratado el cuál desconocía el proceso total de tramite de facturación especialmente del flujo diseñado en el programa de Gestión Documental Orfeo. El funcionario tuvo retroalimentación por parte de la Dirección de Riesgos para que pueda prevenirse organizar su gestión en los próximos trámites de facturas. Acciones Informar de manera inmediata al Analista de Gestión Documental sobre los pasos a seguir cuando llegan facturas y el medio por el cual las recibirá. (Directora de Riesgos) Gestionar el pago de la factura pendiente (Directora de Riesgos) | I35: 0 | J35: 0 | K35: 0 | L35: 7 - Ejecución y Administración de Procesos | M35: 71 - Recepción, Ejecución y Mantenimiento de Operaciones | N35: 716 - Falla en la Gestión Documental | O35: Ninguna | P35: 44926 | Q35: Ninguno | R35: Ninguno | S35: 1033706838 | T35: Diana Maribel Fonseca Gómez | U35: direccion.riesgos@febor.coop | V35: Aprobado | W35: 20/12/2022 10:30:32: Reportado - Riesgos | X35: Falla operativa en pago de pólizas | Z35: =+COUNTIF('Eventos-Tareas'!$D$22:$D$1048576,'Eventos de riesgos'!$B35) -> 2 | AA35: =+'Eventos de riesgos'!$I35-'Eventos de riesgos'!$J35-'Eventos de riesgos'!$K35 -> 0 | AB35: La factura de renovación de la Póliza Multirriesgo fue archivada por un funcionario sin continuar el trámite de aprobación y pago, generando un retraso en la renovación de la póliza y dejando temporalmente sin cobertura aseguradora a la Cooperativa. | AC35: La factura de renovación de la Póliza Multirriesgo radicada el 17 de noviembre de 2022 fue archivada por el funcionario de gestión documental sin continuar el trámite, lo que suspendió el proceso de aprobación y pago. El error fue detectado el 13 de diciembre. | AD35: Falla humana de un funcionario recientemente contratado que desconocía el proceso de tramitación de facturas en el sistema de Gestión Documental Orfeo, llevándolo a archivar la factura sin ejecutar los pasos subsiguientes. | AE35: Retraso de 26 días en el trámite de renovación de la póliza de seguros. Riesgo de desprotección aseguradora para la Cooperativa durante el periodo de interrupción. Se requirió gestión urgente para reactivar el proceso con autorización de la Gerencia.
B36: 35 | C36: 2023 | D36: Ene | E36: 44950.475 | F36: 44950.475 | G36: 44950.475 | H36: Se reporto interrupción del canal PBX de la coopertariva, una interupción del servicio por dos (2) horas,Las causas fueron:1. Se identificó que el problema se originó por una caída del Canal de TIGO-UNE.2. Se identificó que la salida y PBX de la oficina del Centro está únicamente habilitada por el canal de TIGO-UNE.3. No se cuenta con un esquema de alta disponibilidad activo-activo para los canales de internet. En el proceso de verificación, se identificaron tambien:1. Se evidencio un error en la configuración de los DNS actuales de Febor. | I36: 0 | J36: 0 | K36: 0 | L36: 6 - Fallas Tecnologicas | M36: 61 - Sistemas | N36: 613 - Pérdida por Fallas en Telecomunicaciones | O36: Ninguna | P36: 44957 | Q36: Ninguno | R36: Comunicación por PBX | S36: 88217241 | T36: Fabian Manuel Jordan vargas | U36: direccion.informatica@febor.coop | V36: Aprobado | W36: 06/02/2023 09:33:41: Revisar Plan de Acción o Contingencia con la Dirección de TI 06/02/2023 09:34:06: Pasa a lista aprobado | X36: Indisponibilidad PBX | Z36: =+COUNTIF('Eventos-Tareas'!$D$22:$D$1048576,'Eventos de riesgos'!$B36) -> 2 | AA36: =+'Eventos de riesgos'!$I36-'Eventos de riesgos'!$J36-'Eventos de riesgos'!$K36 -> 0 | AB36: Interrupción del canal PBX y de internet de la Cooperativa durante dos horas por caída del canal de TIGO-UNE, sin esquema de alta disponibilidad activo-activo. Se identificaron además errores en la configuración de los DNS de Febor. | AC36: Se presentó una interrupción del canal PBX e internet de la Cooperativa por dos horas, originada por la caída del canal de TIGO-UNE, único canal habilitado para la salida de la oficina Centro. | AD36: Caída del canal de TIGO-UNE, único proveedor habilitado para internet y PBX en la oficina Centro. Ausencia de esquema de alta disponibilidad activo-activo para los canales de internet y errores en la configuración de los DNS. | AE36: Interrupción del servicio de PBX e internet por dos horas. Imposibilidad de atender llamadas entrantes durante el evento. Se identificaron vulnerabilidades en la infraestructura de conectividad de la Cooperativa.
B37: 36 | C37: 2023 | D37: Feb | E37: 44941.69 | F37: 44956.692 | G37: 44958.69 | H37: Caso El lunes 30 de enero el asociado DARIO FERNANDO GOEZ OSPINA C.C. 70.072.472 se comunico a través del pbx a informar que desconocía una transferencia hecha el día 18 de enero del año en curso por valor de $ 1'450.000, razón por la que solicita el reintegro de este valor a su cuenta de ahorros voluntarios, el asesor que atendió la llamada indico al asociado que se realizaría el respectivo escalamiento y bloqueo de la cooperativa digital. Durante estos días se pudo validar que previo a realizar la transacción hubo una actualización de datos por coop digital, también se evidencio que operaciones llamo a confirmar al número que aparecía en nuestro sistema (número actualizado recientemente) hubo un intento donde no contestaron y luego devuelven la llamada indicando que era correcta la transaccción...Jefe de operaciones puede ampliar la info del control aplicado. El 31 de enero Dir SAS se comunica con el asociado para darle un parte de tranquilidad, indicandole que estabamos haciendo todas las validaciones del caso, pregunte discretamente si de pronto alguien mas conocia sus claves, a lo que el sr responde que abosultamente nadie, que ni siquiera su hija que es abogada magistrada. Acciones Devolver el dinero al asociado (Jefe Jurídico) En comunicación del 05 de abril, la aseguradora niega el reconocimiento al no encontrarse amparado el siniestro en la póliza contratada. Ante esto, el señor Darío Goez interpone un derecho de petición ante la junta de vigilancia para que inste a la administración a reconocer el dinero. En respuesta del 03 de mayo del 2023, la Junta de Vigilancia responde al asociado que no encuentra verificada la existencia de los elementos de la responsabilidad civil que pretende endilgar a Febor Entidad Cooperativa toda vez que la custodia de las credenciales de acceso a la Cooperativa Digital son de uso exclusivo y personal de cada asociado, motivo por el cual, no hay lugar al reconocimiento de devolución alguna. Correo: Re: Estado Eventos de Riesgos - Tareas en proceso Investigar. Solicitar a Wog rastreo de las operaciones con IP para determinar el origen de la operación.(Dirección TI y Operaciones) Asesoría Jurídica al Asociado para el tratamiento de su caso(Jefe Jurídico) El señor fue asesorado por el Jefe Jurídico para presentar los documentos correspondientes para la reclamación ante la aseguradora, el asociado los pasó y está en trámite. Revisar el rastreo de operaciones y uso de la plataforma de Cooperativa Digital En el proceso de investigación desde Operaciones, se analizó la trazabilidad de uso de la Cooperativa digital, se detecto que el asociado no había hecho cambio de claves durante el año2022, estos cambios se presentaron en 27 y 30 de enero 2023 y nuevamente el 2 febrero 2023. En cuanto al rastreo de IP donde se efectuaron transacciones se identificó que son de movistar y genera ubicación es Soacha, sin embargo, dado que son publicas, no se puede tener certeza o acercamiento a la persona causante del fraude. Correo: Re: Estado Eventos de Riesgos - Tareas en proceso | I37: 1450000 | J37: 0 | K37: 0 | L37: 2 - Fraude Externo | M37: 22 - Hurto y Fraude | N37: 221 - Robo o Hurto | O37: Ninguna | P37: 44985 | Q37: Ahorros voluntarios | R37: Comunicación por PBX | S37: 53166187 | T37: Johana Paola Cortés Gomez | U37: direccion.sas@febor.coop | V37: Aprobado | W37: 06/02/2023 09:37:30: Revisar controles y acciones a tomar con la Dirección de TI 06/02/2023 12:15:11: Comité Gerencia 06 febrero 2023. Durante el Comité se debatieron varias opciones tales como: Crear mecanismo de alerta mediante mensajes de texto que avise al asociado los movimientos que hace en la Cooperativa, generar códigos OTP para confirmar operaciones, limitar actualizaciones de datos de contacto en plataformas digitales, programar preguntas de seguridad. Desde Jurídica, asesorarlo para que formule una denuncia, Febor Le devolverá el dinero al asociado, la Dirección de TI solicitó a Wog rastreo de las operaciones con IP para determinar el origen de la operación. 06/02/2023 12:24:28: Actualización campo cuenta contable 23/02/2023 10:10:27: En el proceso de investigación desde Operaciones, se analizó la trazabilidad de uso de la Cooperativa digital, se detecto que el asociado no había hecho cambio de claves durante el año2022, estos cambios se presentaron en 27 y 30 de enero 2023 y nuevamente el 2 febrero 2023. En cuanto al rastreo de IP donde se efectuaron transacciones se identificó que son de movistar y genera ubicación es Soacha, sin embargo, dado que son publicas, no se puede tener certeza o acercamiento a la persona causante del fraude. El señor fue asesorado por el Jefe Jurídico para presentar los documentos correspondientes para la reclamación ante la aseguradora, el asociado los pasó y está en trámite. 07/03/2023 12:03:43: Se ordena que todas las transacciones a terceros deben ser confirmadas sin importar los montos debido a los casos de fraude presentados. | X37: Suplantacion de Identidad y robo a asociados | Z37: =+COUNTIF('Eventos-Tareas'!$D$22:$D$1048576,'Eventos de riesgos'!$B37) -> 4 | AA37: =+'Eventos de riesgos'!$I37-'Eventos de riesgos'!$J37-'Eventos de riesgos'!$K37 -> 1450000 | AB37: Se realizó una transferencia no autorizada de $1.450.000 desde la cuenta del asociado Darío Goez Ospina a través de la Cooperativa Digital, precedida de una actualización de datos no reconocida por el asociado. | AC37: El 18 de enero, el asociado Darío Fernando Goez Ospina reportó una transferencia no autorizada de $1.450.000 desde su cuenta de ahorros voluntarios a través de la Cooperativa Digital, hecho que fue descubierto al comunicarse con Febor el 30 de enero. | AD37: Acceso fraudulento a la Cooperativa Digital del asociado, precedido de una actualización de datos no reconocida por él. La verificación de la transacción fue realizada al número actualizado recientemente, que pertenecía al defraudador. | AE37: Pérdida de $1.450.000 del asociado. La verificación de seguridad resultó inefectiva al haberse actualizado previamente el número de contacto. Se requirió bloqueo de la Cooperativa Digital y gestión de reintegro.
B38: 37 | C38: 2023 | D38: Feb | E38: 44977.479 | F38: 44977.479 | G38: 44977.48 | H38: Caso La Directora Johana Cortés recibió el siguiente mensaje 'El señor Diego Mauricio Vásquez Escobar que constituyó hace unos meses un CDAT a dos años (según me dice al 7.5% EA). El llamó a averiguar por la causación de intereses y al parecer le informaron mal y está muy preocupado porque le dijeron que era un error del software.' El señor Diego Vásquez identificado con CC 71668299 constituyó un CDAT n° 01322000000001624 a 720 días con tasa EA del 7.5% de febrero 2022 a febrero 2024 al momento de consultar cuanto tenía causado en intereses en febrero 2023, aparecía registrado $7.458.296 millones cuando debía ser $13.950.000. Se revisó la totalidad de CDATS constituidos de todos los asociados para descubrir que el origen de la falla y se detectó que el problema radica en un parámetro asociado a los CDATs de 720 días a los que les seleccionaron periodicidad de 'Dos años'. En cuanto a otros CDATs con 720 días parametrizados 'Al vencimiento' y CDATs de diferentes días parametrizados para pago mensual no presentaron este error en la causación. Este inconveniente fue trasladado al proveedor Wog para su inspección y arreglo definitivo en el sistema. El impacto en la diferencia de costos por causación de intereses es aproximadamente $320 millones los cuales tendrán reconocimiento total en el mes de febrero 2023. Los funcionarios encargados de crear el CDAT en el sistema deberán tener en cuenta no marcar el parámetro “Dos años” mientras el proveedor Wog genera una solución definitiva. Es necesario diseñar plantillas estándar para el calculo de intereses de los productos de tal manera que, sirva para auditar e identificar que el sistema esté calculando correctamente. Acciones Revisar el detalle del error en la liquidación de intereses Se revisó la totalidad de CDATS constituidos de todos los asociados para descubrir que el origen de la falla y se detectó que el problema radica en un parámetro asociado a los CDATs de 720 días a los que les seleccionaron periodicidad de 'Dos años'. En cuanto a otros CDATs con 720 días parametrizados 'Al vencimiento' y CDATs de diferentes días parametrizados para pago mensual no presentaron este error en la causación. Solicitar a Wog, la atención sobre esta falla revisando la parametrización directa del sistema Wog confirmó que fue arreglada la parametrización de la variable de periodicidad 'DOS AÑOS ' en el proceso de creación de CDATs de tal manera que calcule correctamente como esta definido para la variable de periodicidad 'AL VENCIMIENTO' Retroalimentar a los funcionarios que crean CDATs sobre la correcta creación de estos productos Creación productos de 720 días con periodicidad 'Al Vencimiento' Respuesta formal al asociado. Certificar el valor de intereses del CDAT. Directora SAS, atendió el caso Causación de intereses faltante de CDATs que presentaron inconveniente en su creación En comité de gerencia del 7 de marzo de 2023 se tomó la decisión de causar la totalidad afectando los estados financieros corte de febrero 2023 Es necesario diseñar plantillas estándar para el cálculo de intereses de los productos de tal manera que, sirva para auditar e identificar que el sistema esté calculando correctamente.(Jefe de Operaciones). | I38: 6491704 | J38: 0 | K38: 0 | L38: 7 - Ejecución y Administración de Procesos | M38: 71 - Recepción, Ejecución y Mantenimiento de Operaciones | N38: 712 - Errores en Digitación de Datos, Mantenimiento o Descarga | O38: Ninguna | P38: 44985.48 | Q38: CDAT | R38: Comunicación por PBX | S38: 1033706838 | T38: DIANA MARIBEL FONSECA GÓMEZ | U38: direccion.riesgos@febor.coop | V38: Aprobado | W38: 22/02/2023 11:31:29: No se contempla que sea pérdida económica porque son intereses de los CDATs a reconocer, no gastos. | X38: Error en liquidación de Intereses de CDATS | Z38: =+COUNTIF('Eventos-Tareas'!$D$22:$D$1048576,'Eventos de riesgos'!$B38) -> 7 | AA38: =+'Eventos de riesgos'!$I38-'Eventos de riesgos'!$J38-'Eventos de riesgos'!$K38 -> 6491704 | AB38: Un error en la parametrización del sistema Wog generó el cálculo incorrecto de intereses en los CDAT, afectando a múltiples asociados. El caso fue descubierto cuando un asociado consultó sus intereses causados y encontró valores inconsistentes. | AC38: El asociado Diego Vásquez detectó que su CDAT No. 01322000000001624 a 720 días al 7.5% EA mostraba intereses causados de $7.458.296 en lugar de $13.950.000. La revisión total evidenció que el problema afectaba la parametrización de todos los CDAT del sistema. | AD38: Error en un parámetro del sistema Wog que afectó el cálculo automático de los intereses de los CDAT constituidos por los asociados. | AE38: Cálculo incorrecto de intereses en los CDAT de múltiples asociados. Generación de desconfianza e incertidumbre en los asociados afectados. Se requirió revisión masiva y corrección del parámetro en el sistema.
B39: 38 | C39: 2023 | D39: Feb | E39: 44984.478 | F39: 44984.478 | G39: 44984.478 | H39: Caso La Asociada MARIA EUGENIA SERNA CAICEDO identificada con CC 51.741.094 fue víctima de fraude por terceros hoy 27 de febrero. Intentaron transferencias a DAVIPLATA y Banco DAVIVIENDA por un total de $7.067.000, de los cuales se logró recuperar $5.000.000 debido a que por error la persona que intentaba hacer la transferencia no agregó numero de cuenta si no que repitió el número de cédula, por tal motivo se genero el rechazo. En cuanto a las otras transacciones si fueron exitosas por un total de $2.067.000. La persona que realizó el fraude, ingresó el 21 de febrero a la Cooperativa Digital y cambió el número de celular de la asociada y el 25 de febrero hizo cambio de correo. TABLA Al contactar a la asociada ella indicó que el viernes 24 de febrero 5:20 pm tuvo que hacer cambios de respuestas seguridad y clave, luego hizo pago de los 7 millones para su cupo avance. Tenía el teléfono suspendido supuestamente por falta de pago, pero resulta que fue hackeado para que no le notificaran los mensajes de cambio de datos. Hay un correo desde menitaserna@hotmail.com el día 27 de febrero solicitando cambio de numero de celular de 3106961947 a 3114401335, eso fue confirmado con la asociada, ella indica que nunca lo envío y que ha sido hackeada por todo lado. Este correo ya había sido cambiado desde la Cooperativa Digital el 25 de febrero, modificaron el correo electrónico menitaserna@hotmail.com por flaviodaza2@gmail.com. Se le preguntó que hace cuanto había actualizado datos y ella dijo ha hace mucho tiempo y que no recordaba, que normalmente entra a la Cooperativa Digital por el equipo de Banco o el personal. El asesor que recuerda es Juan Esteban, con el que ha tenido contacto más frecuente, pero ha sido de forma presencial. Las acciones tomadas inmediatamente: Verificación de transacciones afectadas y los números de cédula y celular asociados al fraude de la asociada. TABLA Se verificaron las personas que cambiaron datos recientemente para confirmar con los asociados que realmente sean ellos los que están actualizando su información. Total 5 personas. Acciones Área de Operaciones (a cargo de la Jefe de Operaciones) confirmará antes de aprobar las transacciones los datos actualizados como celular y email mientras se soluciona definitivamente las alternativas de autenticación. Correo Re: Estado Eventos de Riesgos - Tareas en proceso (5 jun 2023) Desde el área de operaciones se está utilizando el sistema de evidente para el proceso de transferencias Toda transacción a tercero se confirmará sin importar el monto. Se brinda asesoría para que el asociado afectado sea quien instaura la demanda a su nombre. Llamado de atención a funcionarios que omitieron controles de verificación (a cargo del jefe jurídico) Realizado a las funcionarias Andrea Caicedo y María Fernanda Moncaleano Es necesario hacer verificación telefónica y hacer el evidente de DataCrédito. Se citó a Experiam sobre los productos que ofrece.(Dir SAS) El 7 de marzo 2023 se realizó reunión con Experian para conocer las opciones que ofrece para implementar el evidente en Febor. La Cooperativa tiene un plan llamado MARTER + OTP con Experiam que podrá activar y definir a que procesos aplicarlo. Se debe capacitar a los funcionarios en el manejo de esta herramienta y tramitar su implementación. Se debe capacitar a los funcionarios en el manejo de esta herramienta y tramitar su implementación. Ultima reunión de avance abril 2023 (ok) Hacer campaña de seguridad informática Correo comunicaciones@febor.coop.⚠️ ¡OJO!👀 Con los ataques 🫤 de los Ciberdelincuentes 19 mayo 2023. Fwd: POST de ciberseguridad 15 de mayo 2023 | I39: 7067000 | J39: 5000000 | K39: 0 | L39: 2 - Fraude Externo | M39: 22 - Hurto y Fraude | N39: 221 - Robo o Hurto | O39: Ninguna | P39: 44985.486 | Q39: Ahorros voluntarios | R39: Cooperativa Digital | S39: 1018433978 | T39: EDNA NATALY MALAGON | U39: operaciones@febor.coop | V39: Aprobado | W39: 27/02/2023 12:47:38: Primera parte registrada 06/03/2023 08:56:45: Actualización de información referente al evento 07/03/2023 12:18:31: Comité de gerencia se definen acciones y responsables | X39: Suplantacion de Identidad y robo a asociados | Z39: =+COUNTIF('Eventos-Tareas'!$D$22:$D$1048576,'Eventos de riesgos'!$B39) -> 8 | AA39: =+'Eventos de riesgos'!$I39-'Eventos de riesgos'!$J39-'Eventos de riesgos'!$K39 -> 2067000 | AB39: Terceros accedieron a la Cooperativa Digital de la asociada María Eugenia Serna Caicedo mediante cambio previo de datos de contacto, logrando transferir $2.067.000 de los $7.067.000 intentados, con recuperación parcial de $5.000.000. | AC39: El 27 de febrero, la asociada María Eugenia Serna Caicedo fue víctima de fraude: terceros que habían ingresado previamente a la Cooperativa Digital para cambiar su número celular y correo electrónico intentaron transferir $7.067.000, logrando ejecutar $2.067.000. | AD39: Acceso fraudulento a la Cooperativa Digital mediante ingeniería social, donde el defraudador obtuvo las claves de acceso de la asociada. Previamente realizó cambios en los datos de contacto para tomar control de las credenciales. | AE39: Pérdida neta de $2.067.000 para la asociada. Se recuperaron $5.000.000 debido a un error del defraudador al registrar el número de cuenta. Riesgo reputacional por vulneración de la seguridad en el canal digital.
B40: 39 | C40: 2023 | D40: Mar | E40: 44989.558 | F40: 44991.56 | G40: 44989.559 | H40: Caso El asociado Jesús Antonio Rodríguez Roa identificado con CC 11430770 se comunicó al área de operaciones indicando lo siguiente 'El sábado 14 de marzo siendo las 9:15 de la mañana, fui victima de un atraco en la carrera 15 con 74, fui amenazado y obligado a entregar mi tarjeta débito junto con la clave. Me pidieron el teléfono y lo bloquearon , por lo tanto no fue posible actuar rápido para llamas y bloquear la tarjeta. Cuando logré comunicarme ya había transcurrido algo más de media hora pero me hicieron 13 retiros de $600.000 dejando prácticamente la cuenta desocupada, intenté hacer el denuncio por plataforma pero ésta no trabajó correctamente, fui a un CAI de policía y ellos me dijeron que debía presentar el denuncio en la fiscalía, me presente a la URI de la granja y allí me dijeron que solamente atienden denuncias de lunes a viernes. Por lo anterior, acudo a ustedes para saber que hacer y preguntar ¿porqué hicieron todos los retiros que quisieron sin tener ninguna seguridad?' Acciones Durante el comité de gerencia del 7 de marzo 2023 se determinó lo siguiente: 1. Indicarle al asociado que los topes transaccionales diarios por defecto son: cantidad 20 y hasta un total de $ 20 millones; sin embargo, é puede configurar sus topes transaccionales por cantidad y monto mediante la Cooperativa Digital de acuerdo a su necesidad. A cargo de Jefe de Operaciones Directora SAS, confirma que mediante la Coop Digital no es posible la configuración de Topes, esto lo debe realizar Febor 2. Asesorar al asociado y tramitar el reconocimiento del dinero por parte de la aseguradora (póliza de hurto).A cargo de Jefe Jurídico La aseguradora respondio con 2 millones de pesos como limite de cobertura 3. Como regla general, se debe sugerir a los asociados personalizar los topes transaccionales de acuerdo a su necesidad, cuando se haga entrega de la tarjeta débito. (A cargo de Dir SAS) La configuración se hace internamente | I40: 7800000 | J40: 0 | K40: 0 | L40: 2 - Fraude Externo | M40: 22 - Hurto y Fraude | N40: 221 - Robo o Hurto | O40: Ninguna | P40: 45016.567 | Q40: Ahorros voluntarios | R40: Atención en oficina | S40: 1018433978 | T40: EDNA NATALY MALAGÓN | U40: operaciones@febor.coop | V40: Aprobado | W40: 07/03/2023 13:44:29: Registro de evento comentado en comité de gerencia 09/03/2023 16:43:46: Evento de riesgo socializado en comité de gerencia 7 de marzo 2023 4/03/2023 10:32:29: Reclasificación del Evento de Riesgo a categoría Asociados - Clientes | X40: Suplantacion de Identidad y robo a asociados | Z40: =+COUNTIF('Eventos-Tareas'!$D$22:$D$1048576,'Eventos de riesgos'!$B40) -> 3 | AA40: =+'Eventos de riesgos'!$I40-'Eventos de riesgos'!$J40-'Eventos de riesgos'!$K40 -> 7800000 | AB40: El asociado Jesús Rodríguez fue víctima de atraco con amenaza, siendo obligado a entregar su tarjeta débito y clave. Los delincuentes realizaron 13 retiros de $600.000 por un total de $7.800.000 antes de que pudiera efectuarse el bloqueo. | AC40: El sábado 14 de marzo, el asociado Jesús Antonio Rodríguez Roa fue víctima de atraco, siendo obligado bajo amenaza a entregar su tarjeta débito y clave, así como su celular bloqueado. Los delincuentes realizaron 13 retiros de $600.000, dejando la cuenta prácticamente vacía. | AD40: Hurto mediante violencia física (atraco) al asociado. La demora en el bloqueo de la tarjeta se debió al control del celular por parte de los delincuentes, impidiendo al asociado comunicarse oportunamente con Febor. | AE40: Pérdida de $7.800.000 del asociado por retiros fraudulentos. Imposibilidad de interponer denuncia de forma digital. Trauma psicológico del asociado. Se gestionó el bloqueo y asesoría para la denuncia formal ante la Fiscalía.
B41: 40 | C41: 2023 | D41: Mar | E41: 45006.832 | F41: 45006.832 | G41: 45010.832 | H41: Asociado informa su inconformidad mediante la PQRSF N1461.Buenos días señores consejeros, ante la no respuesta por las directivas de la cooperativa, les comento que desde el mes de enero de 2023, realice unos CDAT con periodo de vencimiento a 6 meses, solicite los títulos físicos que me fueran enviados a Febor a la oficina en Medellín, uno de los títulos fue expedido a 1 año y solicite la aclaración con el asesor, ante la no respuesta hable con la señora Johana que quedo de resolver el impase y de remitir los títulos físicos y hasta la fecha no he recibido respuesta alguna y el CDAT sigue sin su corrección, ya no se quien hablar por esta razón me dirijo a ustedes para ver que se puede hacer. Muchas gracias por su colaboración. Proyección de respuesta - presentada al Consejo de Administración en sesión del 23 de marzo 2023.Apreciado Asociado, Jorge MartínezReciba un cordial saludo Para Febor Entidad Cooperativa, la razón de ser son ustedes nuestros asociados y estamos siempre atentos a sus inquietudes y notificaciones, En atención a la queja remitida, queremos que sepa que entendemos totalmente su malestar, así mismo manifestarle que tal y como le informo la Dirección de servicio al asociado vía telefónica, desde el momento mismo en el que esta se recibió, se realizaron las verificaciones correspondientes a fin de determinar lo ocurrido con la renovación de los títulos relacionados en su correo (20127 y 20140).Teniendo en cuenta que por error humano el título Cdat Nro. 20140 no fue renovado según sus indicaciones, tal y como se le informo vía telefónica; la liquidación de este se hará con las condiciones de plazo y tasa solicitadas por nuestro asociado. Condiciones descritas en el certificado que se envió a través de correo electrónico, Whatsapp, y que se entregará en físico el sábado 25 de marzo en la Asamblea General de Delegados 2023, así como Don Jorge lo solicito.Le expresamos nuestras sinceras disculpas por la situación que generó su inconformidad, hemos tomado los correctivos necesarios para dichas situaciones no se presenten con ninguno de nuestros asociados. | I41: 0 | J41: 0 | K41: 0 | L41: 4 - Asociados o Clientes | M41: 43 - Productos o Servicios Defectuosos | N41: 431 - Defectos del Producto | O41: Ninguna | P41: 45016.833 | Q41: CDAT | R41: Buzón Quejas y Reclamos | S41: 1033706838 | T41: DIANA MARIBEL FONSECA GÓMEZ | U41: direccion.riesgos@febor.coop | V41: Aprobado | W41: 27/03/2023 20:01:15: Registro de primera parte del evento de riesgo 28/03/2023 09:33:18: Se añade más información del evento de riesgo 28/03/2023 09:36:24: . | X41: Error en creación de productos | Z41: =+COUNTIF('Eventos-Tareas'!$D$22:$D$1048576,'Eventos de riesgos'!$B41) -> 2 | AA41: =+'Eventos de riesgos'!$I41-'Eventos de riesgos'!$J41-'Eventos de riesgos'!$K41 -> 0 | AB41: Un asociado recibió un CDAT con plazo de 1 año en lugar del plazo de 6 meses solicitado, sin obtener corrección oportuna pese a múltiples comunicaciones. La queja fue escalada al Consejo de Administración por falta de respuesta. | AC41: Un asociado solicitó CDATs a 6 meses e identificó que uno fue creado a 1 año. A pesar de haber reportado la novedad y recibido compromiso de solución, no obtuvo respuesta ni corrección, lo que lo llevó a escalar la queja ante el Consejo de Administración mediante la PQRSF N1461. | AD41: Error en la creación del producto CDAT con un plazo diferente al solicitado por el asociado. Falta de seguimiento y respuesta oportuna por parte de las áreas responsables al escalamiento del caso. | AE41: Insatisfacción del asociado y pérdida de confianza en el servicio de la Cooperativa. Escalamiento de la queja al Consejo de Administración. Afectación de la tasa de interés aplicable por el plazo incorrecto del producto.
B42: 41 | C42: 2023 | D42: Mar | E42: 45006.836 | F42: 45006.836 | G42: 45006.836 | H42: Buenas tardes Me permito reportar que el formato de la impresión de los cheques esta desajustado nuevamente, este es un error por parte de WOG que constantemente esta sucediendo, se reporta y por parte de proveedor medio lo arreglan y vuelven a desajustarse; la última vez que se reportó no arreglaron el error y fuimos nosotros que pudimos buscar una solución temporal pero ahora nuevamente esta desajustado y en esta ocasión ni imprimiendo en formato carta o A4 se logra obtener la impresión correcta. Agradezco a ustedes gestionar de forma urgente y definitiva el arreglo de estas impresiones, no es la primera vez que pasa este inconveniente y el proveedor puede durar hasta meses sin solucionar esto; si no contamos con esta herramienta incurrimos en una sobrecarga operativa y generamos un riesgo muy alto al realizar cheques de forma manual que no están sistematizados y aplicados directamente a cada operación del asociado como debe ser. Anexo soporte de la imagen de cómo esta imprimiendo en este momento. | I42: 0 | J42: 0 | K42: 0 | L42: 7 - Ejecución y Administración de Procesos | M42: 71 - Recepción, Ejecución y Mantenimiento de Operaciones | N42: 712 - Errores en Digitación de Datos, Mantenimiento o Descarga | O42: Ninguna | P42: 45016.836 | Q42: Varios tipos de crédito | R42: Ninguno | S42: 52155644 | T42: DIANA GIOVANNA ESCOBAR SARMIENTO | U42: tesoreria@febor.coop | V42: Aprobado | W42: 27/03/2023 20:07:15: Registro de la primera parte del evento de riesgo | X42: Retrasos por cheques dañados | Z42: =+COUNTIF('Eventos-Tareas'!$D$22:$D$1048576,'Eventos de riesgos'!$B42) -> 1 | AA42: =+'Eventos de riesgos'!$I42-'Eventos de riesgos'!$J42-'Eventos de riesgos'!$K42 -> 0 | AB42: El módulo de impresión de cheques del sistema Wog presentó nuevamente desajuste en el formato, impidiendo la impresión correcta tanto en carta como en A4. El proveedor no ha dado solución definitiva, generando sobrecarga operativa en tesorería. | AC42: El módulo de impresión de cheques del sistema Wog volvió a presentar desajuste en el formato de impresión, sin que fuera posible obtener una impresión correcta en ningún tamaño de papel, representando una recurrencia de una falla ya reportada anteriormente. | AD42: Falla recurrente de configuración en el módulo de impresión de cheques de Wog, sin solución definitiva por parte del proveedor. Las soluciones temporales implementadas anteriormente no resolvieron el problema de fondo. | AE42: Imposibilidad de imprimir cheques correctamente, obligando al área de tesorería a recurrir a procesos manuales. Sobrecarga operativa, riesgo de pérdida de trazabilidad y posibles retrasos en pagos y desembolsos.
B43: 42 | C43: 2023 | D43: Abr | E43: 45026.375 | F43: 45026.375 | G43: 45026.375 | H43: Siguiendo las indicaciones de enviar el equipo de computo dado que se realizo cambio de portátil la funcionaria Lina Susana Herrera de la ciudad de Cali, envía a Bogotá por la empresa de mensajería de Servientrega con el número de guía 1151920637. En la que el area de TI realiza seguimiento del equipo y se evidencia que el equipo fue hurtado en el momento de hacer la entrega Servientrega, la empresa responde mediante correo (anexo archivo) lo sucedido y dado que el equipo fue asegurado por el valor de $1'000.000 pesos.Cabe recordar las políticas de seguridad de la información en la cual las dos particiones de disco duro se encuentran Cifradas por Bit Locker, adicionalmente se realizo cambio de credenciales de los usuarios (Correo, orfeo, Wfs, cooperativa digital). Tareas pendientes: Seguimiento a la ejecución de la póliza por parte de la aseguradora. Respuesta Señor(es) FEBOR ENTIDAD COOPERATIVA CLL. 42 # 08A-80 Teléfono: 3102008291 CALI (VALLE) Ref: CUN : 1163263, Guía No.1151920637 Reciba un cordial saludo de la Organización Servientrega S.A. En atención a su comunicación nos permitimos informarle que, para la Organización Servientrega S.A., las no conformidades en el Servicio reclamado por nuestros Clientes son muy importantes, lo que nos obliga a optimizar la calidad en cada uno de los procesos. En respuesta a su inconformidad enviada en días pasados, en la cual nos expresa la situación presentada con el envío amparado bajo la guía en referencia, y revisando de manera puntual la trazabilidad y los hechos que rodearon el proceso de transporte del envío, nos permitimos informar que han sido agotados los recursos de Busqueda, en apoyo con los procesos de Logistica y seguridad, y no ha sido exitosa la ubicacion del envio por ende se establece EL SINIESTRO EXTERNO del envio, siendo procedente la reclamacion del cliente con base en el contrato de transporte De acuerdo a lo anterior, ofrecemos disculpas por los inconvenientes ocasionados y agradecemos a clientes que como usted nos ayuda a mejorar la calidad de nuestro servicio, de igual manera Servientrega S.A., estará generando una compensación por la suma de CIENTO DIECISEIS MIL CUATROCIENTOS NOVENTA PESOS M/CTE ($116,490. 0oo). Este monto corresponde al valor declarado en el contrato de transporte (guía) Dicho pago se efectuará mediante Nota Crédito, el cual estaremos enviando a la Dirección de Correspondencia. Reiteramos nuestra vocación de servicio y deseamos poder atenderlo nuevamente en el futuro, seguros de brindar, como siempre, nuestro mejor esfuerzo y servicio; agradecemos tener en cuenta que el valor declarado diligenciado o manifestado en la guía debe ser 100% real al valor Comercial del Articulo. Continuamos fortaleciendo nuestro compromiso de eficiencia y calidad integral. Comedidamente; Lizeth Sanchez ArenasProceso de CompensacionesRegional Occidente Cra 34 No. 10-260 Acopi. Conmutador: 6912999 Ext 120051 – 120052 Cali, Valle del Cauca. www.servientrega.com | I43: 1145000 | J43: 116490 | K43: 116490 | L43: 5 - Daños a Activos Fisicos | M43: 51 - Desastres y Otros Acontecimientos | N43: 512 - Pérdida por Causas Externas: Vandalismo, Terrorismo, Etc. | O43: Ninguna | P43: 45044.729 | Q43: Ninguno | R43: Ninguno | S43: 1010200415 | T43: Jasson Cepeda | U43: coordinador.informatica@febor.coop | V43: Aprobado | W43: 16/04/2023 20:30:09: Aceptado el Evento de Riesgo 11/05/2023 10:38:40: Actualización de respuesta por parte de Servientrega | X43: Robo de equipo de computo | Z43: =+COUNTIF('Eventos-Tareas'!$D$22:$D$1048576,'Eventos de riesgos'!$B43) -> 1 | AA43: =+'Eventos de riesgos'!$I43-'Eventos de riesgos'!$J43-'Eventos de riesgos'!$K43 -> 912020 | AB43: Un equipo de cómputo enviado desde Cali a Bogotá por mensajería fue hurtado durante el proceso de entrega por parte de Servientrega. La cobertura del seguro fue solo de $1.000.000, muy inferior al valor real del equipo. | AC43: El portátil de la funcionaria Lina Susana Herrera fue hurtado por Servientrega durante el proceso de entrega en Bogotá, luego de ser enviado desde Cali con la guía 1151920637. La empresa de mensajería confirmó el hurto mediante correo electrónico. | AD43: Hurto del equipo durante el proceso de transporte por parte de la empresa de mensajería Servientrega. El equipo fue asegurado únicamente por $1.000.000, valor muy inferior al costo real del activo. | AE43: Pérdida del equipo de cómputo institucional. La indemnización por parte de Servientrega se limitó a $1.000.000. Se gestionó el cambio de credenciales de los sistemas y se garantizó la seguridad de la información gracias al cifrado BitLocker.
B44: 43 | C44: 2023 | D44: Abr | E44: 45036.46 | F44: 45037.467 | G44: 45037.467 | H44: Caso presentado Asesora Mary Pinzón informa que debe abrir un cdat a un asociado (Sr Ernesto Guerrero Segura cc 5200959) que envia un correo con el valor exacto que tiene disponible en ahorro voluntario sin embargo la asesora al validar que si este al dia en todo para tomar el dinero y abrir el cdat, se da cuenta por taquilla que asociado tiene una porción de pago de aportes pendientes del mes de marzo, pese a ello en el estado de cuenta (que se genera del mismo wog) aparece al día en todo. En aportes aparece fecha de próximo pago 26 de abril, sin embargo, al revisar solamente el estado cuenta el asociado, éste refleja que se encuentra totalmente al día. Previo a que el asociado enviará el correo, se comunico con Febor y le dimos tal cual la información que esta en el estado de cuenta. Hoy cuando validamos con operaciones efectivamente hay un error en la información del estado de cuenta. Causa Existe un error en el sistema Wog, hay inconsistencia entre los reportes y detalles de productos y el estado de cuenta de WFS con el que se brinda información al asociado. Acciones Gestionar el pago del aporte del asociado para que pueda abrir el CDAT Crear incidencia a Wog para solución de error - Jefe de Operaciones Hacer seguimiento a la corrección por parte del Wog - Jefe de Operaciones | I44: 56000 | J44: 0 | K44: 0 | L44: 7 - Ejecución y Administración de Procesos | M44: 71 - Recepción, Ejecución y Mantenimiento de Operaciones | N44: 712 - Errores en Digitación de Datos, Mantenimiento o Descarga | O44: Ninguna | P44: 45046.468 | Q44: CDAT | R44: Atención en oficina | S44: 53166187 | T44: Johana Paola Cortés Gomez | U44: direccion.sas@febor.coop | V44: Aprobado | W44: 21/04/2023 11:27:05: Aprobado el registro 11/05/2023 10:04:07: Actualización de tareas. Se crea la incidencia 58190 - correo: Soporte WOG-Información estado de cuenta VS planes de cuotas vencidos (21 abril 2023) | X44: Informacion errada a los asociados | Z44: =+COUNTIF('Eventos-Tareas'!$D$22:$D$1048576,'Eventos de riesgos'!$B44) -> 3 | AA44: =+'Eventos de riesgos'!$I44-'Eventos de riesgos'!$J44-'Eventos de riesgos'!$K44 -> 56000 | AB44: El sistema Wog mostró el estado de cuenta de un asociado como completamente al día, omitiendo una cuota de aportes pendiente, lo que llevó a la asesora a brindar información incorrecta y casi aperturar un CDAT sin el requisito cumplido. | AC44: Al intentar aperturar un CDAT al asociado Ernesto Guerrero Segura, la asesora detectó en taquilla que tenía una cuota de aportes pendiente de marzo, información que no reflejaba el estado de cuenta del sistema Wog, el cual mostraba al asociado totalmente al día. | AD44: Inconsistencia en el sistema Wog que no reflejaba correctamente el estado real de los aportes del asociado en el estado de cuenta. La información errónea fue comunicada previamente al asociado con base en dicho reporte. | AE44: Riesgo de incumplir la política de requisitos para la apertura de productos. Se brindó información incorrecta al asociado sobre su estado. Se requirió verificación manual adicional para detectar la inconsistencia.
B45: 44 | C45: 2023 | D45: May | E45: 45035.366 | F45: 45049.366 | G45: 45049.366 | H45: Al llevar a cabo una seguimiento a las actividades confiadas al proveedor Contactos y Negocios S.A.S., fue posible detectar las siguientes irregularidades: 1) El proveedor se encarga de prestar el servicio de visitas domiciliarias a Febor Entidad Cooperativa, para lo cual debe visitar a los asociados en mora a nivel nacional y proponer formulas de arreglo para evitar un litigio futuro. En ejercicio de esta tarea, Febor remite un modelo de carta que se modifica todos los meses y debe ser entregada a los asociados en sobre cerrado para proteger su derecho al habeas data. 2) En abril del 2023, el proveedor no solo hizo entrega del modelo equivocado de cartas sino que, además, entregó 89 cartas sin sobre en los lugares de residencia y/o labor de los asociados morosos, exponiendo así los datos personales de los involucrados frente a terceras personas que intervinieran en la cadena de custodia de la misiva de cobro. Acciones 1. Informar inmediatamente al proveedor sobre la falla, trasladando las quejas presentadas por los asociados. 2. Hacer seguimiento a la calidad de información suministrada en adelante por el proveedor | I45: 0 | J45: 0 | K45: 0 | L45: 4 - Asociados o Clientes | M45: 41 - Adecuación, Divulgación de Información y Confianza | N45: 412 - Aspectos de Adecuación, Divulgación de la Información | O45: Ninguna | P45: 45077.728 | Q45: Ninguno | R45: Ninguno | S45: 1016072548 | T45: Andrés Camilo Forero García | U45: juridica@febor.coop | V45: Aprobado | X45: Error en envió de cartas de cobranza | Z45: =+COUNTIF('Eventos-Tareas'!$D$22:$D$1048576,'Eventos de riesgos'!$B45) -> 2 | AA45: =+'Eventos de riesgos'!$I45-'Eventos de riesgos'!$J45-'Eventos de riesgos'!$K45 -> 0 | AB45: El proveedor Contactos y Negocios S.A.S. entregó a 89 asociados morosos cartas de cobro sin sobre y con un modelo desactualizado, exponiendo información confidencial de los deudores y violando el derecho al habeas data. | AC45: En abril de 2023, el proveedor Contactos y Negocios S.A.S., encargado de visitas domiciliarias de cobro de cartera, entregó 89 cartas con el modelo incorrecto del mes y sin sobre cerrado en los lugares de residencia y/o trabajo de los asociados morosos. | AD45: Incumplimiento del proveedor en las instrucciones de entrega de correspondencia, al no usar el modelo vigente y al distribuir las cartas sin sobre cerrado, exponiendo información confidencial de los asociados. | AE45: Violación al derecho de habeas data de 89 asociados morosos. Riesgo legal para Febor por exposición de información financiera confidencial. Afectación reputacional y posibles reclamaciones por incumplimiento normativo en protección de datos.
B46: 45 | C46: 2023 | D46: May | E46: 45072.449 | F46: 45075.449 | G46: 45072.449 | H46: Caso El asociado RAUL EDUARDO CAÑAS DE LIMA manifestó inconformidad porque Febor aplica descuento de su cuenta de ahorros voluntarios para pago de un SOAT que él pagó el 2 de mayo en la caja del edificio anexo en efectivo. Este error se debe a falla de los procedimientos internos en los que está involucrada la intermediaria Yolanda Buitrago quien se encarga de la administración de seguros y el área de contabilidad de Febor quien crea y concilia estos productos. Versión del área contable (Analista Contable) Este caso se presentó en el mes de Mayo debido a que el Asociado Raul Eduardo Cañas de Lima, solicitó la expedición del Soat para la placa CCY 529 para pago por caja el 2 de Mayo y el mismo fue creado en la caja del Centro por la asesora Mary Pinzón y el señor realizó el pago ese mismo día, el 3 de Mayo yo lo cree nuevamente en vista de que Yolanda Buitrago Coordinadora de Seguros, me solicitó la creación en la planilla 230502 nuevamente, la cuota quedó creada el 26 de abril con vencimiento el 26 de mayo y el sistema le realizó descuento de Ahorros Voluntarios al Asociado a finales de Mayo cuando el convenio aparecía en mora, cuando se crean los convenios, el sistema valida únicamente entre los convenios activos de los asociados, las posibles llaves duplicadas o códigos alternos similares que para este caso en particular sería la placa, y el convenio que creó Mary Pinzón ya aparecía cancelado por el pago que se le aplicó y por esta razón el sistema no lanzó alerta de que ya existía un convenio con esa placa. Consulte con Yolanda y me informó que efectivamente el señor había pagado el convenio y no me reportaron la incidencia para no incluirlo nuevamente, por ese motivo, se le realizó el reintegro al asociado a su cuenta de Ahorros Voluntarios. Desde contabilidad, he manifestado a los asesores Jorge Lievano y Mary Pinzon, (que han sido quienes han creado convenios y no se ha informado a contabilidad) que los convenios se crean desde contabilidad por que en ocasiones anteriores se presentó el mismo caso con otros asociados que alcance a evidenciar antes de crear doble el convenio, de igual manera en el procedimiento de convenios está establecido que los ingresos, retiros, modificaciones o gestiones alusivas a los convenios se realizan desde contabilidad y en unos casos puntuales los realiza el analista operativo pero no los asesores Tareas 1. Comunicación inmediata con la persona encargada de gestionar las pólizas para informarle del error. (Dir SAS) - Terminada, correo 14 julio 2023 (Reflexión sobre procesos y puntos de control (seguros / servicios no financieros) 2. Proponer la reformulación del procedimiento de servicios no financieros (Dir SAS - Jefe Operaciones) - Terminada, Correo Operaciones (6 julio 2023) - Procedimiento de Servicios no financieros Reenvió estos procedimientos a Mónica y a José Nelson ya que parte del procedimiento impacta en contabilidad, con el fin que puedan darle un vistazo y puedan dar sus observaciones. 3. Revisión de controles para evitar descuentos dobles de convenios en contabilidad -involucrar estas medidas en el procedimiento de servicios no financieros. Terminada, (Contabilidad y Jefe Operaciones) Correo Re: Tareas pendientes en Eventos de Riesgo registrados a la fecha 2 agosto 2023 | I46: 0 | J46: 0 | K46: 0 | L46: 4 - Asociados o Clientes | M46: 43 - Productos o Servicios Defectuosos | N46: 431 - Defectos del Producto | O46: Ninguna | P46: 45077.524 | Q46: Seguros (SOAT) | R46: Atención en oficina (caja) | S46: 1033706838 | T46: DIANA MARIBEL FONSECA GÓMEZ | U46: direccion.riesgos@febor.coop | V46: Aprobado | W46: 07/06/2023 12:44:12: Actualizar en productos Polizas 07/06/2023 13:37:57: Actualizado a productos SOAT | X46: Error en débitos automáticos | Z46: =+COUNTIF('Eventos-Tareas'!$D$22:$D$1048576,'Eventos de riesgos'!$B46) -> 3 | AA46: =+'Eventos de riesgos'!$I46-'Eventos de riesgos'!$J46-'Eventos de riesgos'!$K46 -> 0 | AB46: Se realizó un doble cobro del SOAT al asociado Raúl Eduardo Cañas, ya que pese a haber pagado en caja, el sistema realizó también un descuento automático de su cuenta de ahorros, evidenciando una falla en la conciliación entre la intermediaria de seguros y el área contable. | AC46: Al asociado Raúl Eduardo Cañas de Lima se le realizó un descuento automático de su cuenta de ahorros voluntarios por el pago de un SOAT que ya había cancelado en caja el 2 de mayo, generando un doble cobro. | AD46: Falla en los procedimientos internos de conciliación entre la intermediaria de seguros Yolanda Buitrago y el área contable de Febor, quienes no coordinaron oportunamente el registro del pago en efectivo antes de ejecutar el débito automático. | AE46: Cobro doble al asociado por el valor del SOAT. Insatisfacción del asociado e inconformidad con el servicio. Necesidad de reproceso y reintegro del valor cobrado indebidamente. Evidencia de debilidades en el proceso de conciliación de seguros.
B47: 46 | C47: 2023 | D47: Jul | E47: 45108.514 | F47: 45108.514 | G47: 45108.514 | H47: Caso Se efectuaron envíos de mensajes de texto inexactos a los asociados, con el propósito de brindar detalles sobre el estado de sus compromisos. El inconveniente radicó en que los mensajes fueron enviados a números de teléfono celular que no coincidían con los receptores previstos. El origen de este problema fue una deficiencia en el manejo de la base de datos de afiliados, que quedó incorrectamente configurada por la persona encargada de su actualización mensual. Varias áreas utilizan frecuentemente esta base de datos para llevar a cabo la comunicación con los asociados. Conclusión en comité de gerencia 10 julio 2023 Es crucial evitar una completa dependencia de la persona que envía la base de datos de afiliados mensualmente. Todas las personas deben contar con la capacidad de familiarizarse con las bases de datos del sistema, ser capaces de descargarlas y utilizar la información para sus propias tareas de gestión. Acciones Se continuará enviando la base social de manera mensual. - Jefe de Control Interno y Calidad Como medida de control se recomienda revisar aleatoriamente la información de correo y/o celular de uno o dos asociados en el estado de cuenta antes de hacer el envío masivo, importante trasladar este mensaje al resto de los funcionarios. - Dir SAS - Jefe de Operaciones - Jefe Jurídica - Comunicaciones. Se realizará una capacitación sobre la importancia en el manejo adecuado de la información y de las bases de datos de la Cooperativa. - Dir Riesgos | I47: 0 | J47: 0 | K47: 0 | L47: 4 - Asociados o Clientes | M47: 41 - Adecuación, Divulgación de Información y Confianza | N47: 412 - Aspectos de Adecuación, Divulgación de la Información | O47: Ninguna | P47: 45138.512 | Q47: Ninguno | R47: Mensajería de texto (SMS) | S47: 1033706838 | T47: Diana Maribel Fonseca Gómez | U47: direccion.riesgos@febor.coop | V47: Aprobado | W47: 08/08/2023 13:29:34: Aprobación del caso 08/08/2023 13:29:42: . 08/08/2023 15:19:28: Actualización de acciones | X47: Error mensajes masivos | Z47: =+COUNTIF('Eventos-Tareas'!$D$22:$D$1048576,'Eventos de riesgos'!$B47) -> 2 | AA47: =+'Eventos de riesgos'!$I47-'Eventos de riesgos'!$J47-'Eventos de riesgos'!$K47 -> 0 | AB47: Se enviaron mensajes de texto con información sobre compromisos de deuda a números celulares incorrectos, por error en la configuración de la base de datos de afiliados, exponiendo información privada de los asociados a terceros. | AC47: Se enviaron mensajes de texto con detalles sobre el estado de compromisos de deuda de los asociados a números celulares que no correspondían a los destinatarios previstos. | AD47: La base de datos de afiliados quedó incorrectamente configurada por la persona encargada de su actualización mensual, generando que los mensajes fueran enviados a números equivocados. | AE47: Exposición de información financiera privada de asociados a terceros no autorizados. Riesgo de incumplimiento normativo en protección de datos. Necesidad de revisar el proceso de actualización y control de la base de datos de afiliados.
B48: 47 | C48: 2023 | D48: Ago | E48: 45156.676 | F48: 45156.676 | G48: 45156.676 | H48: Caso El funcionario Andrés Forero, jefe jurídico de Febor fue victima de atraco en el barrio Hayuelos de Bogotá cuando salía de su residencia para tomar el taxi para la oficina. Varios delincuentes lo asaltaron y le robaron la maleta en la que tenia guardado el portátil de uso laboral. Acciones Disponer otro equipo para el funcionario con los accesos a los sistemas y el respaldo de backup para que pueda continuar con su labores - Dirección TI. Tramitar con la aseguradora la cobertura de la póliza para el hurto de portátiles - Jefe jurídico | I48: 4000000 | J48: 2320000 | K48: 0 | L48: 5 - Daños a Activos Fisicos | M48: 51 - Desastres y Otros Acontecimientos | N48: 512 - Pérdida por Causas Externas: Vandalismo, Terrorismo, Etc. | O48: Ninguna | P48: 45169.684 | Q48: Ninguno | R48: Ninguno | S48: 1033706838 | T48: Diana Maribel Fonseca Gómez | U48: direccion.riesgos@febor.coop | V48: Aprobado | W48: 19/08/2023 16:26:35: Costos aproximados (falta validar valor comercial y cobertura de la aseguradora) | X48: Robo de equipo de computo | Z48: =+COUNTIF('Eventos-Tareas'!$D$22:$D$1048576,'Eventos de riesgos'!$B48) -> 2 | AA48: =+'Eventos de riesgos'!$I48-'Eventos de riesgos'!$J48-'Eventos de riesgos'!$K48 -> 1680000 | AB48: El portátil de uso laboral del jefe jurídico fue hurtado durante un atraco a mano armada en la vía pública al salir de su residencia, exponiendo potencialmente información institucional confidencial. | AC48: El funcionario Andrés Forero, jefe jurídico, fue víctima de atraco en el barrio Hayuelos de Bogotá cuando salía de su residencia, siendo robada la maleta que contenía su portátil de uso laboral. | AD48: Hurto mediante violencia física (atraco) en la vía pública. El equipo de trabajo era transportado fuera de la oficina en la maleta del funcionario. | AE48: Pérdida del equipo de cómputo institucional con posible exposición de información confidencial. Se gestionó la asignación de un equipo de reemplazo, la restauración de accesos desde backup y la reclamación ante la aseguradora por cobertura de hurto.
B49: 48 | C49: 2023 | D49: Ago | E49: 45157.765 | F49: 45161.765 | G49: 45161.765 | H49: Caso El 19 de agosto de 2023 se realizó una transferencia de mi cuenta de ahorros voluntarios por $1.470.000 a una cuenta del Banco Caja Social, la cual aparece a mi nombre, no obstante yo no he abierto cuenta en dicho Banco y por consiguiente no la tengo inscrita en Febor para realizar transacciones. De hecho, en Banco Caja Social me indicaron que esta cuenta fue abierta el 15 de agosto de 20223 y no cumple con los requisitos de seguridad que ellos exigen, por tanto se trata de una cuenta fraudulenta y no se puede hacer ningún movimiento. Quisiera que se investigue quien de Febor autorizó la transferencia y la razón por la que no fui contactado para validar la transacción, así como sucedió ayer que, en horas de la tarde, me contactó Andrea Caicedo de la Sección de Ahorros para validar una transferencia por $20.000 a Daviplata a nombre de Adriana Martinez, persona que no conozco y así lo informé mediante correo a dicha Sección. Por lo anterior solicito se investiguen dichas situaciones y se realice la devolución del dinero a mi cuenta de ahorros voluntarios, puesto que en Banco Caja Social me indicaron que Febor, entidad que hizo el traslado de recursos, debe responderme si yo no he autorizado ni tengo inscrita dicha cuenta para realizar transacciones en Febor. Ustedes podrán constatar que la única cuenta que tengo inscrita en Febor para realizar transacciones es una cuenta en Bancolombia y si revisan el historial de mi cuenta de ahorros voluntarios nunca he realizado transacciones por la banca digital. Siempre las he realizado directamente en las oficinas. Veo con preocupación que se está vulnerando la seguridad de la Cooperativa y tal vez por no cumplir los protocolos pueda haber muchos casos como el mio. Agradezco una pronta respuesta y solución a mi reclamo. Afirmaciones Jefe de Operaciones Ayer Andrea Caycedo se comunico con un asociado para confirmar una transferencia a un tercero de $20.000. En el momento que el asociado informo que no era el quien estaba realizando la operación, se bloqueo el ingreso a Coop digital. Estamos esperando si la transferencia que iba a una cuenta del asociado se devuelve ya que el asegura que no tiene cuentas en Caja Social. Hoy hemos hecho la consulta varias veces pero aun aparece generada no sale ni devuelta ni confirmada El tema es que es por que suplantaran identidad en los bancos y creen cuentas a nombre del asociado es la única para que esa transferencia pase como confirmada ya que el Banco hace match entre numero de cédula, tipo de cuenta y numero de cuenta. Según veo en la transferencia dice APP, lo voy a solicitar a Wog, pues el asociado informa que ha recibido mensajes con clave para actualizar datos, pero que ha hecho caso omiso debido a que él no está haciendo la operación. En Wog no se ha realizado cambio de datos personales, el numero de celular que está en el sistema es correcto y fue donde nos comunicamos y no ha tenido cambio por Coop digital. Acciones Hay que formalizar la situación. Consignamos en la cuenta del asociado y debe ser Caja social quien informe por qué abrió una cuenta a nombre del asociado.(área jurídica - Operaciones) Hay que poner queja en SFC y denuncia del asociado ya que la suplantación fue en el Banco Caja Social y no en Febor. (área jurídica) Responder la PQR 1698 del asociado informando las medidas de control de la Cooperativa. (Servicoi al Asociado - Operaciones) Investigar ingresos desde la App y Coop Digital del asociado durante el año 2023, último cambio de IP o registro de equipos y celulares del asociado con el fin de validar la presunta suplantación.(área TI) | I49: 0 | J49: 0 | K49: 0 | L49: 2 - Fraude Externo | M49: 22 - Hurto y Fraude | N49: 221 - Robo o Hurto | O49: Ninguna | P49: 45169.765 | Q49: Ahorros voluntarios | R49: Cooperativa Digital | S49: 1033706838 | T49: Diana Maribel Fonseca Gómez | U49: direccion.riesgos@febor.coop | V49: Aprobado | W49: 23/08/2023 18:23:41: Primera información del caso | X49: Suplantacion de Identidad y robo a asociados | Z49: =+COUNTIF('Eventos-Tareas'!$D$22:$D$1048576,'Eventos de riesgos'!$B49) -> 4 | AA49: =+'Eventos de riesgos'!$I49-'Eventos de riesgos'!$J49-'Eventos de riesgos'!$K49 -> 0 | AB49: Terceros realizaron una transferencia fraudulenta de $1.470.000 desde la cuenta del asociado hacia una cuenta bancaria externa creada fraudulentamente a su nombre, sin la autorización ni el conocimiento del titular. | AC49: El 19 de agosto de 2023 se realizó una transferencia no autorizada de $1.470.000 desde la cuenta de ahorros voluntarios del asociado hacia una cuenta del Banco Caja Social abierta fraudulentamente a su nombre el 15 de agosto. | AD49: Acceso no autorizado a los sistemas transaccionales del asociado por parte de terceros, quienes crearon una cuenta bancaria fraudulenta a nombre del asociado para recibir la transferencia sin que fuera fácilmente detectada. | AE49: Pérdida de $1.470.000 del asociado. Cuenta destino calificada como fraudulenta por el banco receptor. Se requirió investigación interna para identificar el origen del acceso y determinar responsabilidades en la autorización de la operación.
B50: 49 | C50: 2023 | D50: Nov | E50: 45239.747 | F50: 45239.747 | G50: 45239.747 | H50: Caso Reporte de caída del sitio web de Febor, refleja errores que interrumpen el acceso a la página causado por operaciones dirigidas desde la dirección de informática en la que no se contempló los posibles daños al realizar dichas actividades. Dir de Informática :'por mejorar la seguridad del sitio, el proxi lo hace el firewall, y se debe cambiar la IP, esto se demoró más de lo estimado, y necesitaba en horario de oficina para tener soporte en caso que falle algo, error mío, pensé que era mas rápido y se demoró más de lo esperado, ya ha repicado en algunos ISP, espero que esta noche se normalice, estoy muy pendiente del proceso' Acciones Corregir el error inmediatamente para reanudar la activación de la pagina web.Realizar una estrategia de comunicación y planeación de las actividades del área, analizando las posibles consecuencias de interrupción al servicio. Esta estrategia debe contener los programas de mantenimiento preventivos y/o correctivos , cuando se van a ejecutar y por cuanto tiempo, para que las demás áreas estén preparadas. | I50: 0 | J50: 0 | K50: 0 | L50: 6 - Fallas Tecnologicas | M50: 61 - Sistemas | N50: 611 - Pérdida por Problemas en Software | O50: Ninguna | P50: 45260.753 | Q50: Ninguno | R50: Ninguno | S50: 1033706838 | T50: Diana Maribel Fonseca Gómez | U50: direccion.riesgos@febor.coop | V50: Aprobado | W50: 13/11/2023 18:06:31: Creado 04/12/2023 20:00:57: . | X50: Fallas sitio web | Z50: =+COUNTIF('Eventos-Tareas'!$D$22:$D$1048576,'Eventos de riesgos'!$B50) -> 2 | AA50: =+'Eventos de riesgos'!$I50-'Eventos de riesgos'!$J50-'Eventos de riesgos'!$K50 -> 0 | AB50: Actividades de mantenimiento realizadas por el área de informática sin planificación adecuada generaron la caída del sitio web de Febor, afectando su disponibilidad y acceso para los asociados y el público en general. | AC50: El sitio web de Febor presentó errores e indisponibilidad como consecuencia de actividades de mejora de seguridad realizadas por la Dirección de Informática, que implicaron un cambio de IP no planificado que tardó más de lo estimado. | AD50: Cambio de configuración de seguridad (proxy y cambio de IP) realizado durante horario laboral sin planificación de contingencia ni estimación adecuada del tiempo requerido, generando una interrupción no prevista del sitio web. | AE50: Caída del sitio web de Febor durante un periodo extendido. Afectación en el acceso de asociados y público a la información institucional. Se evidenció la necesidad de planificar con antelación los cambios de infraestructura.
B51: 50 | C51: 2023 | D51: Dic | E51: 45267.638 | F51: 45272.638 | G51: 45267.638 | H51: Caso Luego de la actualización de versión de Wog el pasado 26 de noviembre, se detectó una irregularidad en los cupos de los créditos rotativos, debido a que varios cupos que se cancelaron después de que el asociado realizara el pago total. Esta inconsistencia que se presento después de la instalación de la nueva versión, ocasionó inconformidad de algunos asociados que han estado llamando porque necesitan realizar avances desde su cupo y no lo tienen activo. Acciones Incidencia 61118 reportada. Jefe Operaciones Seguimiento a la incidencia - Activación de productos urgente (Wog- Operaciones)Diseño y programación de pruebas básicas de funcionalidad del sistema posterior a las actualizaciones, desde el área de tecnología solicitar apoyo para la realización de pruebas del sistema. | I51: 0 | J51: 0 | K51: 0 | L51: 6 - Fallas Tecnologicas | M51: 61 - Sistemas | N51: 611 - Pérdida por Problemas en Software | O51: Ninguna | P51: 45291.637 | Q51: Crédito rotativo | R51: Ninguno | S51: 1018433978 | T51: EDNA NATALI MALAGON SIERRA | U51: operaciones@febor.coop | V51: Aprobado | W51: 10/01/2024 12:02:45: Aprobada la creación | X51: Errores por actualizoción Wog | Z51: =+COUNTIF('Eventos-Tareas'!$D$22:$D$1048576,'Eventos de riesgos'!$B51) -> 2 | AA51: =+'Eventos de riesgos'!$I51-'Eventos de riesgos'!$J51-'Eventos de riesgos'!$K51 -> 0 | AB51: La actualización de versión del sistema Wog el 26 de noviembre generó una irregularidad que desactivó cupos de créditos rotativos de varios asociados que ya habían realizado el pago total de su obligación. | AC51: Tras la actualización de versión de Wog del 26 de noviembre, se detectó que los cupos de créditos rotativos de varios asociados que habían completado el pago de su obligación fueron cancelados incorrectamente. | AD51: Falla en la actualización de versión del sistema Wog que generó una inconsistencia en los cupos de los créditos rotativos, desactivándolos aun cuando los asociados habían cumplido sus obligaciones. | AE51: Inconformidad de asociados que no podían acceder a sus cupos de crédito rotativo. Se requirió reportar la incidencia 61118 a Wog y gestionar la activación urgente de los productos afectados. Se evidenció la necesidad de pruebas de funcionalidad tras actualizaciones.
B52: 51 | C52: 2023 | D52: Dic | E52: 45279.51 | F52: 45318.51 | G52: 45279.511 | H52: Caso La Gerencia, la Dirección de SAS y Jefe de operaciones reportan errores en la App de Febor y la Cooperativa Digital, no deja ver algunos productos y muestra avisos de error al momento de efectuar transacciones. Dir SAS: 'D Fernando dice q esta cuenta la inscribió hoy sobre las 2 pm… y lo dejo sin inconveniente inscribirla, al tratar de hacer la transacción se presento el error del cual les compartí pantallazo (…)' Jefe operaciones: 'Nosotros inscribimos el tercero para hacer la transferencia pero eso no se refleja en la coop'Jefe operaciones:' Ya informe a wog que al parecer el problema continua en app se soluciono en coop digital. estoy atenta si alguien reporta que el problema continua en coop digital' Gerencia: informa que el daño puede deberse al consumo de la plataforma BI, según lo conversado con William de Wog. Acciones Solicitar la desconexión de BI a Wog. Responsable Dir TI Monitorear el funcionamiento de la App y Coop Digital. Responsable Dir TI | I52: 0 | J52: 0 | K52: 0 | L52: 6 - Fallas Tecnologicas | M52: 61 - Sistemas | N52: 611 - Pérdida por Problemas en Software | O52: Ninguna | P52: 44957.526 | Q52: Varios tipos de crédito | R52: Aplicación móvil (App Febor) / Cooperativa Digital | S52: 53166187 | T52: Johana Paola Cortés Gómez | U52: direccion.sas@febor.coop | V52: Aprobado | W52: 10/01/2024 12:38:39: Creado | X52: Fallas Cooperativa Digital | Z52: =+COUNTIF('Eventos-Tareas'!$D$22:$D$1048576,'Eventos de riesgos'!$B52) -> 2 | AA52: =+'Eventos de riesgos'!$I52-'Eventos de riesgos'!$J52-'Eventos de riesgos'!$K52 -> 0 | AB52: La App de Febor y la Cooperativa Digital presentaron errores simultáneos que impedían visualizar algunos productos y realizar transacciones, afectando la experiencia de los asociados y la operación. | AC52: Se reportaron errores en la App de Febor y la Cooperativa Digital que impedían ver algunos productos y mostraban avisos de error al intentar realizar transacciones, incluyendo la inscripción y ejecución de transferencias a terceros. | AD52: Falla técnica en las plataformas digitales, posiblemente vinculada al consumo de la plataforma BI, que afectó simultáneamente la App y la Cooperativa Digital administradas por el proveedor Wog. | AE52: Interrupción en la prestación del servicio transaccional digital. Imposibilidad de realizar transacciones por parte de los asociados. Reputación afectada por la indisponibilidad de los canales digitales.
B53: 52 | C53: 2023 | D53: Dic | E53: 45282.583 | F53: 45286.583 | G53: 45282.583 | H53: Caso El Consejo Walter Idárraga solicitó aclaración a la Gerencia sobre la admisión del señor Alfonso Serrano Parra indicando lo siguiente: 'Juan Pablo en relación con las afiliaciones a Febor de esta semana aparece la solicitud del pensionado Alfonso Serrano Parra y en su formato de vinculación indica asociado nuevo, hasta donde recuerdo este señor es uno de los deudores morosos a los que no se le pudo cobrar nada'. Luego de investigar la situación particular, se concluye a que obedece a la omisión de un control desde el área de operaciones por parte del analista que debe verificar la totalidad de requisitos para la admisión de asociados. Jefe de operaciones: 'Buenos días si señor, en la verificación que hizo Andrea la realizó con la información de Orfeo y no le salía nada, pero al validar en wog, el sábado se dio cuenta que si era reingreso. Tiene fecha de retiro 2018-03-28 y el motivo es expulsado. 'Jefe Jurídico: 'Alfonso Serrano fue excluido mediante Resolución 053 del 19 de enero del 2018' Acciones Verificar y corregir (si aplica) el procedimiento de afiliaciones. Responsable Jefe de Operaciones Auditar y verificar que no se hayan filtrado antes más asociados con alguna exclusión. En caso de existir, se debe iniciar proceso de retiro. Responsable Jefe Jurídico y Jefe de Control Interno | I53: 0 | J53: 0 | K53: 0 | L53: 7 - Ejecución y Administración de Procesos | M53: 73 - Aceptación de Clientes y Documentación en Contratación | N53: 731 - Inexistencia de Autorizaciones, Rechazos de Clientes | O53: Ninguna | P53: 45291.583 | Q53: Ninguno | R53: Ninguno | S53: 72179606 | T53: Juan Pablo Vélez Góez | U53: gerencia@febor.coop | V53: Aprobado | W53: 10/01/2024 14:03:04: Creado | X53: Reingreso no permitido por Estatuto | Z53: =+COUNTIF('Eventos-Tareas'!$D$22:$D$1048576,'Eventos de riesgos'!$B53) -> 2 | AA53: =+'Eventos de riesgos'!$I53-'Eventos de riesgos'!$J53-'Eventos de riesgos'!$K53 -> 0 | AB53: Se admitió como nuevo asociado a una persona que tenía deudas morosas previas no saldadas con la Cooperativa, por omisión de controles en la verificación del historial en los sistemas internos durante el proceso de vinculación. | AC53: Se realizó la admisión del señor Alfonso Serrano Parra como nuevo asociado, sin detectar que ya había tenido una relación previa con Febor como deudor moroso sin cobro efectivo, debido a una verificación incompleta. | AD53: El analista responsable de la admisión verificó los requisitos únicamente en el sistema Orfeo, sin consultar los registros históricos de morosidad en otros sistemas disponibles, omitiendo el control completo requerido. | AE53: Admisión de un asociado con historial de mora no saldada. Riesgo crediticio y de cartera para la Cooperativa. Evidencia de debilidades en el proceso de verificación de requisitos de admisión de asociados.
B54: 53 | C54: 2024 | D54: Feb | E54: 45331.99 | F54: 45331.99 | G54: 45331.99 | H54: CasoLa imagen de la Cooperativa se vio afectada al distribuir los calendarios del 2024, los cuales presentaban defectos de calidad provenientes del proveedor, tanto para los calendarios de escritorio como los de pared. El defecto fue detectado por integrantes del Consejo, quienes alertaron a la Gerencia, es decir, no fueron previamente identificados por el área responsable.Acciones Comunicar al proveedor inmediatamente sobre el defecto del producto entregado.El proveedor se compromete a reemplazar los calendarios defectuosos.La muestra de verificación de calidad del producto fue mínima, por lo cual se requiere que en adelante, todos los productos recibidos tengan un proceso de verificación de calidad con una muestra acorde a la cantidad comprada. | I54: 0 | J54: 0 | K54: 0 | L54: 7 - Ejecución y Administración de Procesos | M54: 76 - Proveedores | N54: 763 - Incumplimiento de las Actividades Contratadas | O54: Ninguna | P54: 45351.002 | Q54: Ninguno | R54: Ninguno | S54: 1033706838 | T54: Diana Maribel Fonseca Gómez | U54: direccion.riesgos@febor.coop | V54: Aprobado | W54: 14/02/2024 00:04:41: Generada | X54: Compra de productos defectuosos | Z54: =+COUNTIF('Eventos-Tareas'!$D$22:$D$1048576,'Eventos de riesgos'!$B54) -> 2 | AA54: =+'Eventos de riesgos'!$I54-'Eventos de riesgos'!$J54-'Eventos de riesgos'!$K54 -> 0 | AB54: Se distribuyeron calendarios institucionales 2024 con defectos de calidad provenientes del proveedor, sin que el área responsable los detectara previamente, afectando la imagen de la Cooperativa. | AC54: Se distribuyeron los calendarios institucionales 2024, tanto de escritorio como de pared, los cuales presentaban defectos de calidad provenientes del proveedor. Los defectos fueron detectados por integrantes del Consejo y no por el área responsable de la recepción. | AD54: El proceso de verificación de calidad del producto recibido fue insuficiente, con una muestra de revisión mínima que no permitió detectar los defectos generalizados en los calendarios antes de su distribución. | AE54: Distribución de material institucional defectuoso afectando la imagen de la Cooperativa. Necesidad de reemplazar los calendarios a cargo del proveedor. Evidencia de debilidades en el proceso de control de calidad en la recepción de suministros.
B55: 54 | C55: 2024 | D55: Feb | E55: 45323.651 | F55: 45360.653 | G55: 45334.652 | H55: CasoDurante los procesos mensuales de auditoría llevados a cabo por el área de control interno, se han identificado casos en los que se registran CDATs en el sistema con fechas posteriores al mes de solicitud. Esta situación es más común cuando los CDATs son solicitados hacia finales de mes y su creación se realiza a principios del mes siguiente. Al registrar el producto fuera del mes solicitado, genera afectación sobre la tasa de interés aplicable al depósito. Puede variar, dado que las tasas de interés son actualizadas mensualmente y en ocaciones cambian dependiendo de las propuestas aprobadas por el Consejo de Administración.Los efectos derivados de estas situaciones son:Incumplmiento a las políticas internas en cuanto a la creación de produtos bajo condiciones aprobadas por el consejo.Pérdida de credibilidad por la creación de productos no conformes, fuera de las condiciones inicalmente pactadas con el asociado.Inconformidad de los asociados cuando queda registrada una tasa menor a la pactada y genera menor reconocimeinto de interés por el dinero depositado.Afectación financiera y del margen de intermediación de Febor cuando queda registrada una tasa de interés mayor a la pactada y se debe reconocer más interés por el deposito constituído.AccionesExposición de los casos a gerencia. Jefe de Control Interno y CalidadExposición de los casos a comité de auditoría y consejo de administración. Jefe de Control Interno y CalidadDirectriz en comité de gerencia 26 de febrero de 2024: 'Los funcionarios encargados de crear el producto en el sistema deben hacerlo de inmediato, no se tolera que los dejen para dias posteriores y especialmente a final de mes deben organizar el proceso para que quede cerrado en el mes que corresponde'.Continuar con el monitoreo mensual por parte de control interno. Cerrar el evento de riesgo si no se presentan más casos por lo menos en 6 meses consecutivos. | I55: 0 | J55: 0 | K55: 0 | L55: 4 - Asociados o Clientes | M55: 42 - Prácticas Empresariales o de Mercadeo Improcedentes | N55: 425 - Actividades No Autorizadas | O55: Ninguna | P55: 45351.693 | Q55: CDAT | R55: Ninguno | S55: 1136886706 | T55: Diana Chistina Forero Lopez | U55: controlinterno.calidad@febor.coop | V55: Aprobado | W55: 06/03/2024 16:39:47: Creado 06/03/2024 16:42:23: . | X55: Error tasa CDAT | Z55: =+COUNTIF('Eventos-Tareas'!$D$22:$D$1048576,'Eventos de riesgos'!$B55) -> 3 | AA55: =+'Eventos de riesgos'!$I55-'Eventos de riesgos'!$J55-'Eventos de riesgos'!$K55 -> 0 | AB55: Se identificaron casos recurrentes de registro de CDAT en el sistema con fechas posteriores al mes de solicitud, lo que genera afectación en la tasa de interés aplicada e incumplimiento de políticas internas aprobadas por el Consejo. | AC55: Durante los procesos de auditoría mensual de control interno, se identificaron casos en los que los CDAT fueron registrados en el sistema en un mes diferente al de su solicitud, especialmente cuando se solicitaban a final de mes. | AD55: Los CDAT solicitados a finales de mes eran creados en el sistema a principios del mes siguiente, generando una diferencia entre la fecha de solicitud y la fecha de registro que afecta la tasa de interés vigente. | AE55: Afectación de la tasa de interés reconocida a los asociados por sus depósitos. Incumplimiento de las políticas internas de creación de productos bajo condiciones aprobadas por el Consejo de Administración. Riesgo de reclamaciones por parte de los asociados afectados.
B56: 55 | C56: 2024 | D56: Mar | E56: 45359.448 | F56: 45359.448 | G56: 45369.448 | H56: CasoDurante el proceso de verificación de documentos para la declaración de origen de fondos de las operaciones en efectivo en las instalaciones de la Cooperativa, se identificaron (2) declaraciones inusuales en febrero de 2024. Estas presentaban una aparente falsificación de firma y huella, al detectar recuadros que indicaban que dichas autenticaciones habían sido cortadas y pegadas de otros documentos. Las declaraciones correspondían a los asociados Gonzalo Sánchez Hurtado identificado con CC 87.430.991 y Félix Alfredo Cortés Rincón identificado con CC 10.518479, quienes realizaron la operación presencialmente en la caja los días 6 y 9 de febrero de 2024. La funcionaria encargada y responsable era la Sra. Mary Gisell Pinzón Manrique. AccionesSe expuso el caso al equipo directivo en comité de gerenciaLa Sra Mary Pinzon fue citada a descargos el 14 de marzo, aceptó haber realizado falsificacion defirmas y huellas sin fines fraudelentos, sólo por cubrir fallas operativas indicando que no pudo hacer firrmar oportunamente los formatos en caja y procedio a formalizarlos de esta manera.Debido al tipo de falta, la cual se considera grave, se procedió a la terminación de contrato de Sra Mary Pinzon con causa justificada.Los anexos del caso están en el expediente de la Sra Mary Pinzón - Reserva de Talento Humano. (Acta de descargos y termnación de contrato) | I56: 0 | J56: 0 | K56: 0 | L56: 1 - Fraude Interno | M56: 11 - Actividades No Autorizadas | N56: 111 - Operaciones No Reveladas Intencionalmente | O56: Ninguna | P56: 45382.449 | Q56: Ninguno | R56: Atención en oficina (caja) | S56: 1033706838 | T56: Diana Maribel Fonseca gómez | U56: direccion.riesgos@febor.coop | V56: Aprobado | W56: 22/03/2024 10:49:35: Creado. 12/04/2024 04:50:37: Complementado el caso | X56: Falsificación de firmas y/o huellas | Y56: RCA005 | Z56: =+COUNTIF('Eventos-Tareas'!$D$22:$D$1048576,'Eventos de riesgos'!$B56) -> 2 | AA56: =+'Eventos de riesgos'!$I56-'Eventos de riesgos'!$J56-'Eventos de riesgos'!$K56 -> 0 | AB56: Se identificaron dos declaraciones de origen de fondos con presuntas falsificaciones de firma y huella en operaciones en efectivo, realizadas en caja por dos asociados los días 6 y 9 de febrero de 2024. | AC56: Durante la verificación de documentos de origen de fondos en operaciones en efectivo, se detectaron dos declaraciones con aparente falsificación de firma y huella, con indicios de autenticaciones cortadas y pegadas de otros documentos, correspondientes a dos asociados atendidos en caja. | AD56: Posible falsificación de firma y huella por parte de los asociados en las declaraciones de origen de fondos, sin que la funcionaria de caja detectara las inconsistencias durante la atención presencial. | AE56: Riesgo de incumplimiento normativo en procesos de prevención de lavado de activos (LAFT). Exposición legal y reputacional para la Cooperativa. El caso fue expuesto al equipo directivo para la toma de acciones pertinentes.
B57: 56 | C57: 2024 | D57: Abr | E57: 45383.204 | F57: 45383.204 | G57: 45412.204 | H57: CasoEl 20 de marzo de 2024 el Consejo de Administracion aprobó la exclusión de 26 asociados, los cuales debian tener el debido proceso de cruce de cuentas de sus productos de aportes y Daes. Desde el área jurídica se envió la instrucción al área de operaciones, sin embargo, esta instrución no fue completa en cuanto a la forma de aplicacion del cruce de cuentas, ya que la exlución fue aprobada con la condición de condonar los intereses y reducir el capital de la deuda con los saldosAcciones El área de operaciones y contabilidad deberá realizar el reproceso de la aplicación contable de dichos saldos para el cierre de abril de 2024.El área jurídica y de riesgos deben proponer acciones preventivas para mejorar los métodos de comunicación y asegurar su efectividad. | I57: 0 | J57: 0 | K57: 0 | L57: 7 - Ejecución y Administración de Procesos | M57: 71 - Recepción, Ejecución y Mantenimiento de Operaciones | N57: 718 - Error en Otras Tareas, Falla en la Entrega | O57: Ninguna | P57: 45382.203 | Q57: Ninguno | R57: Ninguno | S57: 1033706838 | T57: Diana Maribel Fonseca gómez | U57: direccion.riesgos@febor.coop | V57: Aprobado | W57: 12/04/2024 04:55:08: Aprobado 24/04/2024 17:45:38: Completar evento. | X57: Falla en aplicación DAES | Z57: =+COUNTIF('Eventos-Tareas'!$D$22:$D$1048576,'Eventos de riesgos'!$B57) -> 2 | AA57: =+'Eventos de riesgos'!$I57-'Eventos de riesgos'!$J57-'Eventos de riesgos'!$K57 -> 0 | AB57: La instrucción enviada por el área jurídica al área de operaciones para el proceso de cruce de cuentas en la exclusión de 26 asociados fue incompleta, generando una aplicación contable incorrecta que requirió reproceso. | AC57: El área jurídica envió instrucciones incompletas al área de operaciones para ejecutar el cruce de cuentas de aportes y DAES de 26 asociados cuya exclusión fue aprobada el 20 de marzo de 2024, omitiendo la condición de condonar intereses y reducir capital. | AD57: La instrucción del área jurídica al área de operaciones no incluyó de forma completa las condiciones aprobadas por el Consejo para la exclusión, generando una aplicación contable incorrecta. | AE57: Necesidad de reprocesar la aplicación contable de los saldos de los 26 asociados para el cierre de abril de 2024. Riesgo de errores en los estados financieros y en el reconocimiento de las exclusiones aprobadas.
B58: 57 | C58: 2024 | D58: May | E58: 45382.59 | F58: 45429.59 | G58: 45422.59 | H58: CasoEl comité de auditoría reveló un caso de fraude interno relacionado con la falsificación de un certificado de pensión necesario para el proceso de crédito del asociado José Agustín Martínez Cristancho, identificado con CC 17.140.819. La falsificación implicó alterar la fecha de recepción de la nómina del mes de enero de 2024, y fue realizada por la funcionaria Alejandra Rodríguez. Aunque ella admitió haber modificado el documento, aclaró que posteriormente solicitó al asociado que enviara el documento original y físico, pero este no fue el documento que quedó registrado en el sistema, sino el modificado. Declaración de la funcionaria Alejandra Rodriguez: 'Lo que pasó con el señor, el señor me había traído los papeles, y cuándo yo radique el de enero no lo encontré y si, yo le cambié el mes, pero luego dije mejor con el señor mejor sacamos uno nuevo de enero, pero cuándo radiqué, radique el del documento malo'.La señorita Alejandra presentó dichos documentos físicos como evidencia de lo declarado, sin embargo, se llevó a cabo el correspondiente proceso disciplinario.AccionesProceso disciplinario a cargo del área jurídica, dirigido a la funcionaria Alejandra. Se concluyó el 17 de mayo de 2024 con la suspensión de 3 días.De igual manera se desarrolló una capacitación sobre delitos de fraude al personal el 20 de junio de 2024. Grabación Teams: Capacitación sobre delitos de fraude-20240620_090729-Grabación de la reunión. Capacitación sobre delitos de fraude-20240620_090729-Grabación de la reunión.mp4 | I58: 0 | J58: 0 | K58: 0 | L58: 1 - Fraude Interno | M58: 11 - Actividades No Autorizadas | N58: 111 - Operaciones No Reveladas Intencionalmente | O58: Ninguna | P58: 45427.604 | Q58: Crédito de consumo | R58: Ninguno | S58: 1136886706 | T58: DIANA CHRISTINA FORERO LOPEZ | U58: controlinterno.calidad@febor.coop | V58: Aprobado | W58: 15/05/2024 14:31:30: Creado 15/05/2024 14:33:22: . 02/07/2024 12:35:23: Complemento | X58: Modificación de documentos | Y58: RCA005 | Z58: =+COUNTIF('Eventos-Tareas'!$D$22:$D$1048576,'Eventos de riesgos'!$B58) -> 2 | AA58: =+'Eventos de riesgos'!$I58-'Eventos de riesgos'!$J58-'Eventos de riesgos'!$K58 -> 0 | AB58: Una funcionaria modificó la fecha del certificado de pensión de un asociado para facilitar el proceso de crédito, constituyendo un caso de fraude interno por falsificación documental, detectado en el comité de auditoría. | AC58: La funcionaria Alejandra Rodríguez modificó la fecha del certificado de pensión del asociado José Agustín Martínez Cristancho en el proceso de crédito, alterando el documento para incluir la nómina de enero de 2024, sin registrar el documento original en el sistema. | AD58: Decisión unilateral de la funcionaria de modificar un documento oficial para facilitar el trámite de crédito del asociado, sin seguir el proceso correcto de solicitud del documento original y sin autorización de sus superiores. | AE58: Fraude interno por falsificación de documento oficial. Riesgo de pérdida crediticia por vinculación de un asociado con documentos alterados. Proceso disciplinario y legal contra la funcionaria. Riesgo reputacional para la Cooperativa.
B59: 58 | C59: 2024 | D59: May | E59: 45442.568 | F59: 45447.569 | G59: 45447.569 | H59: CasoFraude Externo. Robo y suplantación de identidad por medio transaccionalCaso AConsejera María Elvira Molano Tamayo Fecha de descubrimiento 4 de junio de 2024 Id asociado 41.683.566 Fechas del evento Entre el 30 de mayo y el 4 de junio Cuantía $ 2.100.000 Cuantía recuperada $0 Caso BConsejero Jaime Albeiro Martínez Mora Fecha de descubrimiento 7 de junio de 2024 Id asociado 15.401.254 Fechas del evento Entre el 30 de mayo y el 4 de junio Cuantía $ 27.000.000 Cuantía recuperada $0 Reporte de alerta del Caso A el día 4 de junio 2024Reunión del equipo directivo en horas de la tarde para conocer el Caso A presentado relacionado con el fraude de la consejera María Elvira Molano. En esta reunión se revisó lo siguiente:· La señora María Elvira se comunicó el jueves 30 de mayo con la Dirección de Servicio al Asociado y con el analista de informática para comentar acerca de unos códigos OTP que estaban llegando a su celular y luego de ello a informar que no podía acceder a la Cooperativa Digital. · Se identificó una transferencia a través de Cooperativa Digital por $2.100.000 a la cuenta de ahorros del Banco Coopcentral No. 119035172, cuya titular es Luz Mary Herrera León, quien había sido creada inicialmente como Luz Dary Herrera León, la cual no había sido realizada realmente por la señora maría Elvira.· Se evaluaron los audios iniciales, a fin de identificar el método de fraude utilizado por la persona suplantadora.· La Gerencia se comunicó con Banco Coopcentral para alertar la situación para que el banco lograra activar un bloqueo de la cuenta.· La Dirección de Riesgos reportó por correo al Oficial de Cumplimiento del Banco y otros destinatarios sobre el fraude y alertó la necesidad de confirmar el bloqueo de la cuenta de la Sra Luz Mary. ( Ronny Ramirez Garcia ; Andres Alfonso Uribe Maldonado ; Edna Karina Duran Anaya .El Banco confirmó que el caso ya estaba reportado por la Oficina Bogotá centro y de manera inmediata realizaron el bloqueo preventivo de la cuenta y de los canales digitales. Sin embargo, los recursos fueron retirados inmediatamente y no fue posible retenerlos.· La jefe de Control Interno reversó la actualización del correo electrónico y número de celular de la asociada María Elvira.Nuevas alertas reportadas el 6 de junio 2024Desde Servicio al Asociado, la asesora Manuela Vélez informó que iba a bloquear al consejero César Cárdenas debido a que se estaba recibiendo una solicitud de reinicio de contraseña para acceder a la Cooperativa Digital. El correo desde el cual se envió la solicitud había sido actualizado previamente por el asesor Jhon Mantilla, cambiando de cesarc655@gmail.com a cesarc2655@gmail.com. Cuando se contactó al Sr. César, se identificó que se trataba de otro intento de suplantación.Después de recibir esta nueva alerta, se procedió a revisar los cambios recientes en la actualización de datos, especialmente los correos electrónicos y números de celular, con el fin de identificar otras posibles víctimas. Detallen en Anexo 1. ACTUALIZACION CORREOS Y CELULARES.Otra alerta reportada el 7 de junio de 2024Nuevamente el área de servicio reportó otro intento de suplantación de identidad del consejero Ever Antonio Díaz Salcedo. Iniciaron solicitando información de saldo de créditos y fechas de facturación. Las siguientes imágenes corresponden a chats de los asesores Estiven Labrador y Manuela Vélez.Reunión 7 de junio 2024 del equipo directivoDe la revisión de los asociados con cambio de datos, se observó que, en los 3 casos relacionados con cambio de celular y correo al mismo tiempo, se encontraba otro fraude al consejero Jaime Albeiro Martínez Mora (Caso B), quien se encontraba fuera del país y no tenía conocimiento de la situación. Al analizar las transacciones realizadas, se identificó la participación nuevamente de la señora Luz Mary Herrera León con la Cédula de Ciudadanía No. 46.649.336, y del señor Edier Alexander Hernández Nivia con la Cédula de Ciudadanía No. 79.640.612. En esta ocasión, se observaron las siguientes acciones:· Se realizaron 2 transferencias desde Multiportal de Visionamos a la cuenta de ahorros del Banco Coopcentral N°119035172 a nombre de Luz Dary Herrera León con CC 46.649.336. La primera fue el 4 de junio de 2024 por un monto de $2.200.000, y la segunda el 5 de junio de 2024 por $2.000.000. · Adicionalmente, mediante Cooperativo Digital los días 4 y 5 de junio de 2024, se trasladaron los cupos del crédito rotativo a la cuenta de ahorros voluntarios.· Posteriormente, se efectuó un retiro a través de Cooperativo Digital desde la cuenta de ahorro voluntario del Sr. Jaime hacia la cuenta 488430645421 del Banco Davivienda, a nombre de Edier Alexander Hernández Nivia con CC 79.640.612, por un valor de $9.200.000.· Finalmente, se realizaron 13 retiros sin tarjeta débito desde la aplicación Multiportal de Visionamos por un total de $7.730.000. Asimismo, el día 5 de junio se efectuaron otros 13 retiros sin tarjeta débito desde la misma aplicación, alcanzando un total de $7.210.000. · Estos retiros fueron identificados en Bogotá en cajeros ubicados en la calle 125 y Calle 42. Durante la reunión se analizaron y concluyó lo siguiente:Se revisó las grabaciones de las llamadas de la persona que suplantó al Sr Jaime. Se identificó la modalidad de fraude en los casos materializados y los alertados. Se identificó que el sistema de Evidente no está generando los OTP en algunas situaciones.También se evalúo que el porcentaje de acierto de las preguntas era del 50%, luego de hacer unas pruebas entre los miembros del equipo directivo y revisar la parametrización de preguntas contratada con Experian. Se identificaron errores humanos desde la asesoría al momento de confirmar información sensible de los asociados, donde no se evidenció control dual.Se observó casos de omisión de la activación de las preguntas de seguridad del Evidente de Experian.Acciones Las acciones correctivas que se determinaron son: Acción Responsable Estado Revisar grabaciones del PBX Equipo directivo OK 4 y 7 de junio Alerta a Coopcentral para bloqueo de cuenta fraudulenta de tercero. Gerencia Dirección de Riesgos OK 4 y 5 de junio Confirmación de bloqueo preventivo por parte de Coopcentral. Banco Coopcentral OK 4 y 5 de junio Reverso de datos actualizados de correo y celular de la Sra María Elvira. Jefe de Control Interno OK 4 de junio Analizar los cambios de información reciente en la base de asociados y determinar los que requieren verificación especial. Dirección de Riesgos OK 6 y 7 de junio 2024 Verificar si el grupo de asociados para verificación especial presentaron transferencias recientemente y realizar las confirmaciones correspondientes. Anexo 2. Revisión transferencias terceros mayo junio Jefe Operaciones Jefe de Control Interno OK 7 de junio 2024 Bloquear la Cooperativa Digital inmediatamente de todos los asociados con actualización reciente de correo y/o celulares en verificación especial. Jefe Operaciones OK 7 de junio 2024 Reverso de datos actualizados de correo y celular del Sr Jaime Martínez Jefe Operaciones OK 7 de junio 2024 Instaurar las demandas correspondientes, tanto del caso del Sr Jaime como de la Sra María Elvira. Jefe Jurídico OK 7 de junio de 2024 Número de radicado # 2024061101549 Contactar a cada uno de los asociados bloqueados, con el fin de verificar posibles intentos de fraude o reversar el bloqueo de la Cooperativa Digital. Dirección Servicio al Asociado OK 8 de junio 2024 Bloquear el acceso a los documentos publicados en página web, especialmente en el link de asamblea 2024. Jefe Jurídico Dirección de Informática OK 7 de junio de 2024 Analizar detalladamente las grabaciones y documentarlas. Dirección de Riesgos OK entre 13 y 14 de junio Reunión con Experian para revisar las condiciones de oferta comercial versus el servicio real, exponer los casos de fraude y revisar una parametrización más segura. Dirección Servicio al Asociado OK 13 de junio 2024 Gestionar la devolución del dinero a los asociados afectados. Anexo 3. Histórico transacciones JM visionamos Jefe Operaciones OK 19 de junio de 2024 Proceso disciplinario a funcionaria Leidy Delgado, funcionaria que actualizó los datos del asociado Jaime Albeiro. Jefe Jurídico OK 20 de junio de 2024 Las acciones preventivas que se determinaron son: · Revisar la implementación de un CRM · Exigir el código OTP siempre o redireccionar a actualización en oficina. · Buscar tecnologías para identificación de identidad remota. · Mejorar el esquema de seguridad para el acceso a asociado digital. · Contratar una capacitación especializada en antifraude y reconocimiento de alertas y formas de verificación efectiva.Reunión Experian 1Se llevó a cabo el día 13 de junio de 2024 3:30 pmAsistentes de Experian: Loren Mendieta, Andrea franco y Vania Soto Asistentes de Febor: Juan Pablo Vélez, Johana Paola Cortés, Edna Nataly Malagón, Fabian Jordán y Diana Maribel Fonseca. El Dr Juan Pablo Vélez manifestó algunas inconformidades que se evidenciaron del servicio de evidente:· El código OTP no es funcional en todos los casos. · Se percibió que las preguntas presentaron un nivel de acierto muy bajo luego de elaborar algunas pruebas de suplantación entre los miembros del equipo directivo. La gerente de Experian, Andrea Franco, confirmó que la parametría de Febor es muy suave y recomienda aumentar el número de aciertos exigidos. Además, indicó que el OTP no será efectivo cuando los números de celular no estén registrados en el buró. En estos casos, la cooperativa deberá considerar otras alternativas. También mencionó que existe una versión adicional de Febor que podría implementarse, ya que actualmente están utilizando la versión 3 de las 4 disponibles.El compromiso de Experian es la revisión de las estadísticas sobre el nivel de aceptación, rechazo, la parametría y las recomendaciones.Reunión Experian 1 Se llevo a cabo el 21 de junio de 2024, en la cual se analizó las estadísticas de aceptación, de rechazo, la parametría y algunas recomendaciones para configurar el servicio de manera más segura. El compromiso de Febor es formalizar la nueva parametrización. | I59: 29100000 | J59: 0 | K59: 0 | L59: 2 - Fraude Externo | M59: 22 - Hurto y Fraude | N59: 221 - Robo o Hurto | O59: Ninguna | P59: 45473.623 | Q59: Ahorros voluntarios | R59: Cooperativa Digital | S59: 1033706838 | T59: Diana Maribel Fonseca Gómez | U59: direccion.riesgos@febor.coop | V59: Aprobado | W59: 05/06/2024 15:04:09: Creado 02/07/2024 15:00:15: Registro completo | X59: Suplantacion de Identidad y robo a asociados | Y59: RTI022 | Z59: =+COUNTIF('Eventos-Tareas'!$D$22:$D$1048576,'Eventos de riesgos'!$B59) -> 18 | AA59: =+'Eventos de riesgos'!$I59-'Eventos de riesgos'!$J59-'Eventos de riesgos'!$K59 -> 29100000 | AB59: Dos consejeros de Febor fueron víctimas de fraude externo por robo y suplantación de identidad a través de canales transaccionales digitales, resultando en pérdidas por $2.100.000 y $27.000.000 respectivamente. | AC59: Entre el 30 de mayo y el 7 de junio de 2024, dos consejeros de Febor, María Elvira Molano ($2.100.000) y Jaime Albeiro Martínez ($27.000.000), fueron víctimas de fraude externo mediante robo y suplantación de identidad por medios transaccionales digitales. | AD59: Acceso fraudulento a las cuentas de los consejeros a través de los canales transaccionales digitales de la Cooperativa, mediante técnicas de suplantación de identidad por parte de terceros. | AE59: Pérdida total de $29.100.000 entre los dos casos. Afectación directa a miembros del Consejo de Administración. Riesgo reputacional y de confianza en los canales digitales de la Cooperativa.
B60: 59 | C60: 2024 | D60: Jun | E60: 45461.703 | F60: 45462.703 | G60: 45462.703 | H60: CasoNuevo caso de fraude presentado al asociado 19468241 - Fernando Arciniegas Guzmán. Desde ayer, han intentado transferir dinero a una cuenta Nequi. El dinero fue reintegrado debido a que no se logró comunicación con el asociado para verificar la transferencia.Posteriormente, crearon una cuenta Daviplata a nombre del asociado, y realizaron una nueva transferencia, esta vez exitosa al tratarse de una cuenta a su nombre.Al evaluar el caso, se observó que días antes había llegado una solicitud de desbloqueo de contraseña a la Cooperativa Digital del asociado. La funcionaria Erika realizó el desbloqueo pero no asignó una nueva clave. Sin embargo, como la persona suplantadora ya tenían acceso al correo del asociado, logró ingresar y realizar la transacción. Estos hechos evidencian la alta posibilidad de hackeo de correo y presunta clonación de la línea de celular.El jefe de operaciones confirmó: 'Nos dimos cuenta porque el asociado estaba tramitando un crédito con Manuela a través del chat. Le envió los desprendibles y otros documentos, pero Manuela lo llamó porque faltaba algo, y el asociado le dijo que él no estaba tramitando nada mediante la Cooperativa Digital'. AccionesInformar al asociado que hay una cuenta falsa de Daviplata a su nombre para que instaure la demanda correspondiente. Jefe de OperacionesRestringir la salida de todas las transacciones a cuentas simplificadas como Nequi y Daviplata e impartir esta instrucción a los analistas de operaciones. Jefe de Operaciones Se revisó la cobertura de la póliza para tramitar la devolución del dinero y para este caso, no aplica ya que es una vulneración directa a acceso del propio asociado tanto a su correo como celular. (Jefe Jurídico) | I60: 300000 | J60: 0 | K60: 0 | L60: 2 - Fraude Externo | M60: 22 - Hurto y Fraude | N60: 221 - Robo o Hurto | O60: Ninguna | P60: 45473.7 | Q60: Ahorros voluntarios | R60: Cooperativa Digital | S60: 1018433978 | T60: EDNA NATALI MALAGON SIERRA | U60: operaciones@febor.coop | V60: Aprobado | W60: 02/07/2024 16:53:40: Registro 15/07/2024 10:32:16: . | X60: Suplantacion de Identidad y robo a asociados | Y60: RSAS034 | Z60: =+COUNTIF('Eventos-Tareas'!$D$22:$D$1048576,'Eventos de riesgos'!$B60) -> 3 | AA60: =+'Eventos de riesgos'!$I60-'Eventos de riesgos'!$J60-'Eventos de riesgos'!$K60 -> 300000 | AB60: Terceros suplantaron al asociado Fernando Arciniegas en la Cooperativa Digital, primero intentando transferir a cuenta Nequi y luego creando una cuenta Daviplata a su nombre para ejecutar una transferencia exitosa, aprovechando un proceso de desbloqueo mal ejecutado. | AC60: Terceros intentaron y lograron transferir dinero desde la cuenta del asociado Fernando Arciniegas, primero a una cuenta Nequi (bloqueada) y luego a una cuenta Daviplata creada fraudulentamente a su nombre, aprovechando el acceso al correo del asociado. | AD60: La funcionaria Erika realizó el desbloqueo de contraseña de la Cooperativa Digital del asociado sin asignar una nueva clave. El suplantador, que ya tenía acceso al correo del asociado, pudo ingresar y ejecutar las transferencias. | AE60: Pérdida económica del asociado por la transferencia exitosa a la cuenta Daviplata fraudulenta. Evidencia de fallas en el proceso de desbloqueo de contraseñas de la Cooperativa Digital. Riesgo reputacional por vulneración de la seguridad en el canal digital.
B61: 60 | C61: 2024 | D61: Jul | E61: 45504.483 | F61: 45506.483 | G61: 45506.484 | H61: CasoEl 31 de julio de 2024, se procesaron incorrectamente 153 pagos, incluyendo 100 aplicaciones de pago de DAES a un mismo asociado. Este error se originó debido al manejo manual de la plantilla que se utiliza habitualmente para la aplicación de pagos.AccionesUna vez se identificó el error, se procedió a reversar las operaciones correspondientes. Johan - Analista de OperacionesOrganizar y automatizar una plantilla de pagos para reducir el error manual. Johan - Analista de Operaciones y Dirección de RiesgosRevisar alternativas de automatización para la aplicación de pagos directamente en Wog | I61: 0 | J61: 0 | K61: 0 | L61: 7 - Ejecución y Administración de Procesos | M61: 71 - Recepción, Ejecución y Mantenimiento de Operaciones | N61: 711 - Exceso de Manualidad | O61: Ninguna | P61: 45504.51 | Q61: Depósito de Ahorro con Estímulo (DAES) | R61: Ninguno | S61: 1033706838 | T61: Diana Maribel Fonseca Gómez | U61: direccion.riesgos@febor.coop | V61: Aprobado | W61: 20/08/2024 12:20:27: Registrado. | X61: Error en aplicación de pagos | Z61: =+COUNTIF('Eventos-Tareas'!$D$22:$D$1048576,'Eventos de riesgos'!$B61) -> 3 | AA61: =+'Eventos de riesgos'!$I61-'Eventos de riesgos'!$J61-'Eventos de riesgos'!$K61 -> 0 | AB61: El 31 de julio de 2024 se procesaron incorrectamente 153 pagos, incluyendo 100 aplicaciones duplicadas de DAES a un mismo asociado, originadas por errores en el manejo manual de la plantilla de pagos. | AC61: El 31 de julio de 2024 se procesaron erróneamente 153 pagos, incluyendo 100 aplicaciones de pago de DAES duplicadas para un mismo asociado, originadas por errores en la manipulación manual de la plantilla de pagos. | AD61: Error humano en el manejo manual de la plantilla de pagos utilizada habitualmente para la aplicación de pagos de DAES, que no cuenta con controles automatizados para prevenir duplicidades. | AE61: Procesamiento incorrecto de 153 pagos. Necesidad de reversar todas las operaciones afectadas. Sobrecarga operativa para el equipo de operaciones. Se evidenció la necesidad de automatizar el proceso de aplicación de pagos.
B62: 61 | C62: 2024 | D62: Jul | E62: 45482.558 | F62: 45512.558 | G62: 45524.558 | H62: CasoEl pasado 9 de julio se registraron 24 casos de aplicación doble en los pagos de tarjeta de crédito, sumando un total de $7.568.355,00. Estos errores fueron causados por fallas del sistema, especialmente entre Wog y ASNET. Así mismo, el área de operaciones reportó un nuevo caso e de pago doble en agosto.AccionesEl 14 de agosto se ordenó lo siguiente desde la gerencia:1. Transacciones Menores a $50.000 No se realizarán ajustes en las transacciones menores a $50.000. El doble abono se dejará a favor del asociado, y la cooperativa asumirá el costo. Esto reduce el problema a aproximadamente 11 asociados. En total se asume el error de 13 asociados por un total de $156.118.2. Transacciones Mayores a $50.000 Contactaremos a los asociados afectados para informarles del error y proponer una refinanciación de su deuda ajustando el mayor valor pagado. El asociado podrá elegir un nuevo plazo para la refinanciación (con cuotas a 6, 12, 24, hasta 60 meses), y se aplicará la tasa de interés correspondiente a la compra de cartera con tarjeta de crédito.3. Oferta de Compra de Cartera Durante la llamada, se ofrecerá la opción de compra de cartera para los saldos de tarjetas vigentes, hasta el 100% del cupo de la tarjeta, según lo reportado en Datacrédito o Cifin. Se brindará una explicación breve de la falla que causó el problema.4. Ejecución de las Llamadas El servicio al asociado, bajo la supervisión de su Directora, se encargará de las llamadas, dado que la atención al asociado es una función clave de esta área. Es necesario que todo esté resuelto para el día siguiente, incluyendo una nueva compra por el valor total de la deuda más el valor abonado doble, junto con la compra de cartera que el asociado elija, con apoyo prioritario de Operaciones.Nota: Es importante que toda la información y las soluciones estén listas antes de iniciar las llamadas, por lo que la responsabilidad recaerá en la Directora de Servicio.5. Revisar con los proveedores de los sistemas el origen de la falla, ¿porqué ejecutó doblo pago? y plantear algún método para restringir la salida de pagos dobles. Director TI. | I62: 7568355 | J62: 7412237 | K62: 0 | L62: 6 - Fallas Tecnologicas | M62: 61 - Sistemas | N62: 611 - Pérdida por Problemas en Software | O62: Ninguna | P62: 45535.563 | Q62: Tarjeta crédito | R62: Ninguno | S62: 1033706838 | T62: Diana Maribel Fonseca Gómez | U62: direccion.riesgos@febor.coop | V62: Aprobado | W62: 20/08/2024 13:33:05: Registrado 10/09/2024 12:53:39: Actualizado | X62: Pago doble de TC por error del sistema | Y62: RTI036 | Z62: =+COUNTIF('Eventos-Tareas'!$D$22:$D$1048576,'Eventos de riesgos'!$B62) -> 5 | AA62: =+'Eventos de riesgos'!$I62-'Eventos de riesgos'!$J62-'Eventos de riesgos'!$K62 -> 156118 | AB62: En julio y agosto de 2024 se registraron casos de doble aplicación en pagos de tarjeta de crédito por fallas entre Wog y ASNET, afectando a 24 asociados en julio por $7.568.355 y casos adicionales en agosto. | AC62: El 9 de julio se registraron 24 casos de doble aplicación en pagos de tarjeta de crédito por $7.568.355, causados por fallas entre los sistemas Wog y ASNET. En agosto se reportaron nuevos casos de la misma naturaleza. | AD62: Fallas en la comunicación entre los sistemas Wog y ASNET que generaron la aplicación duplicada de pagos de tarjeta de crédito. | AE62: Doble abono en las cuentas de 24 asociados en julio. La Cooperativa asumió el costo de los casos menores ($156.118 en 13 asociados) y gestionó la devolución con los restantes. Riesgo de pérdida económica y necesidad de corrección manual de los registros.
B63: 62 | C63: 2024 | D63: Ago | E63: 45513.578 | F63: 45535.578 | G63: 45513.578 | H63: CasoLa asociada Ingrid Frederick Obregón C.C. 1.020.723.306 registro una queja a la Cooperativa por no obtener solución oportuna acerca del endoso de una póliza sobre su préstamo, solicitada en abril de 2024:SolicitudBogotá, 09 de abril de 2024 Señores Febor Entidad Cooperativa Ciudad Referencia: Radicación Endoso Póliza Vida a mi Medida Deudor – Descontar cobros Cuota Crédito No. 1250738 Comunicado Jefe Jurídico 26 de abril 2024 Buenas tardes, Yolanda:De manera atenta solicitamos su amable apoyo con la validación de la solicitud de endoso de la póliza de vida que nos formula la empresa Telefectivos en nombre y representación de nuestra asociada Ingrid Frederick Obregon C.C. 1.020.723.306. Adjunto el documento con el que se pretende el endoso, donde constan sus condiciones de cobertura y beneficiario. Cordialmente, Comunicado Yolanda 26 de abril 2024 Buenas tardes Sr. Andrés Camilo La póliza vida deudores presentada por la señora Ingrid Frederick cumple con la cobertura actual de la póliza Vida Deudores La Equidad-Febor: Amparo de vida - Muerte por cualquier causa hasta el saldo insoluto de la deuda Incapacidad total y permanente, por incapacidad laboral superior al 50% Cordial saludo, YOLANDA BUITRAGO Coordinadora de cuenta Comunicado Jefe Jurídico 26 de abril 2024 Buenas tardes, Nata:De manera atenta, solicito el procesamiento del endoso de la póliza vida deudores de la asociada Ingrid Frederick Obregón C.C. 1.020.723.306, de acuerdo con las condiciones del documento adjunto y el Vo.Bo. de Yolanda que consta en la trazabilidad. Quedo atento a tus inquietudes. Cordialmente, Comunicado de Febor a Tanefectivos 15 de mayo 2024Aceptación del endoso a Axa ColpatriaComunicado Jefe Jurídico 9 de agosto 2024 Buenos días, estimado equipo de operaciones: De manera atenta, solicito su apoyo para poder materializar el endoso de la póliza de vida deudores de la asociada Ingrid Frederick Obregón, quien desde abril del 2024, contrató la cobertura con AXA Colpatria tal como consta en el documento adjunto. Igualmente, desde mayo se le notificó a la asociada y al intermediario que Febor Entidad Cooperativa aceptaba el endoso de la póliza en cumplimiento del numeral 2 del Artículo 100 de Estatuto Orgánico del Sistema Financiero (EOSF). No obstante, a la fecha, aun no se ha completado en el sistema el endoso de la mentada póliza para el crédito No. 1250738, a pesar de que cumple los condicionamientos legales para su procedencia, circunstancia que nos pone en una presunta situación de incumplimiento y nos expone a las multas de las que trata el Artículo 2.363.2.5.5 y siguientes del Decreto 1084 del 2021. Adjunto remito el correo donde se notificó al área operativa del endoso ya que contábamos con el Vo.Bo. previo de Yolanda. En consecuencia, todo dinero que se le haya descontado doblemente a la asociada por este concepto desde la fecha de su notificación debe ser restituido de inmediato y en adelante trasladar los dineros al beneficario del endoso. Quedo atento a cualquier duda y/o inquietud sobre el particular. Cordialmente, Acciones Responder la PQR en los tiempos establecidos. Área de Operaciones y área jurídicaTramitar el endoso de la póliza con prioridad. Área de Operaciones | I63: 0 | J63: 0 | K63: 0 | L63: 7 - Ejecución y Administración de Procesos | M63: 71 - Recepción, Ejecución y Mantenimiento de Operaciones | N63: 713 - Incumplimiento de Plazos o Responsabilidades | O63: Ninguna | P63: 45535.576 | Q63: Crédito de consumo | R63: Buzón Quejas y Reclamos | S63: 1033706838 | T63: Diana Maribel Fonseca Gómez | U63: direccion.riesgos@febor.coop | V63: Aprobado | W63: 20/08/2024 13:53:43: Registrado | X63: Queja de asociado por demora en trámites | Z63: =+COUNTIF('Eventos-Tareas'!$D$22:$D$1048576,'Eventos de riesgos'!$B63) -> 2 | AA63: =+'Eventos de riesgos'!$I63-'Eventos de riesgos'!$J63-'Eventos de riesgos'!$K63 -> 0 | AB63: La asociada Ingrid Frederick Obregón no obtuvo respuesta oportuna a su solicitud de endoso de póliza de vida radicada en abril de 2024, lo que la llevó a registrar una queja formal ante la Cooperativa por falta de gestión. | AC63: La asociada Ingrid Frederick Obregón radicó en abril de 2024 una solicitud de endoso de póliza de vida deudor sobre su crédito, sin recibir respuesta ni solución oportuna, lo que la llevó a registrar una queja formal por falta de atención. | AD63: Falta de seguimiento y gestión oportuna por parte de las áreas responsables (jurídica y de seguros) ante la solicitud de endoso de la póliza, generando demoras que superaron los tiempos de respuesta esperados. | AE63: Insatisfacción de la asociada y pérdida de confianza en el servicio. Radicación de queja formal. Seguimiento de cobros de cuotas sin el ajuste del endoso, afectando la situación financiera del crédito de la asociada.
B64: 63 | C64: 2024 | D64: Ago | E64: 45526.581 | F64: 45527.582 | G64: 45527.582 | H64: CasoEl 22 de agosto de 2024, el área de operaciones suspendió temporalmente el análisis de crédito tras detectar un error en el cálculo de la capacidad de pago para descuentos por nómina. Este error se originó debido a una discrepancia entre la retención en la fuente calculada por el modelo y la reportada en los desprendibles de pago de los asociados, afectando la precisión de la evaluación crediticia en cuatro casos específicos, correspondientes a empleados o pensionados.Asimismo, se identificó una deficiencia en la comunicación inmediata para resolver la situación, ya que, tras reportarse el error, no se activó un plan de contingencia. En su lugar, se optó por suspender el proceso, asumiendo que los créditos en espera podrían presentar la misma falla de los cuatro casos iniciales. Esta decisión fue tomada sin la debida consulta con la gerencia y los directores de área.CausaEl modelo utilizado para calcular la capacidad de pago estima la retención en la fuente de manera total, mientras que el desprendible de pago muestra una retención que varía según las deducciones y excepciones aplicables a cada empleado.Como resultado, la capacidad de pago calculada por el modelo no coincide con la retención real reportada, afectando la evaluación final de la capacidad de pago. Al realizar las validaciones de aparecieron 4 casos detenidos en la etapa de análisis por esta diferencia. A continuación se ilustra el ejemplo relacionado con la diferencia: ImpactoSuspensión de la operación de análisis de crédito por aproximadamente un día y medio. hasta detectar el origen de las diferencias encontradas y llevar a cabo el ajuste del modelo.Se detectaron 4 casos que fueron detenidos en la etapa de análisis debido a esta discrepancia.La variación en el cálculo de la retención en la fuente influye en la capacidad de pago final, lo que podría llevar a errores en la aprobación de créditos o en la evaluación de la capacidad financiera de los empleados. AccionesDesde la gerencia se enfatiza la importancia de establecer un plan de contingencia o activar el comité de crisis en situaciones críticas, como la posible falla del modelo de cálculo de capacidad de pago. En ese escenario, resulta esencial contar con una alternativa claramente definida que permita mantener la continuidad operativa sin interrupciones. Esto asegura que, ante un eventual fallo en el modelo, la cooperativa pueda recurrir a estrategias adicionales que mitiguen el impacto, garantizando la fluidez de las operaciones y el cumplimiento de sus objetivos. (informado comité de gerencia 13-09-2024).Asimismo, se establece que el único autorizado para suspender la operación es el gerente, quien tomará esta decisión solo después de haber sido informado detalladamente sobre la situación presentada. (informado comité de gerencia 13-09-2024).Al detectar esta novedad, se revisa y ajusta el modelo de cálculo de capacidad de pago para alinear la retención en la fuente calculada con la que se reporta en los desprendibles de pago. (Director de Riesgos)Se comunica el ajuste del modelo y sus razones al área de servicio al asociado para que puedan usar este último y no tener más inconvenientes. Este comunicado se puede evidenciar como: Correo a Funcionarios: Modelo Capacidad de Pago V3 del viernes 23 de agosto 2024 11:33 amDice lo siguiente:'Estimados compañeros,Como es de su conocimiento, hemos identificado discrepancias entre el cálculo de capacidad de pago del modelo y las verificaciones realizadas con el comprobante, especialmente en lo que respecta al valor de retención en la fuente. El modelo calcula este valor neto sin considerar excepciones o deducciones. Por ello, hemos decidido adoptar el valor de retención indicado en el comprobante.En la próxima versión del modelo, se incluirá un campo para ingresar este valor de forma manual:' Realizar una revisión mensual del modelo de cálculo de capacidad de pago para verificar la exactitud de los cálculos y asegurar que las tablas de descuentos para salud y pensión estén actualizadas conforme a la normativa vigente. Esta revisión debe incluir la auditoría de los procedimientos y fórmulas utilizados para identificar y corregir posibles errores, garantizando así la precisión en el análisis de la capacidad de pago y el cumplimiento de las regulaciones aplicables. (Director y/o Analista de Riesgos) | I64: 0 | J64: 0 | K64: 0 | L64: 7 - Ejecución y Administración de Procesos | M64: 71 - Recepción, Ejecución y Mantenimiento de Operaciones | N64: 714 - Ejecución Errónea de Modelos o de Sistemas | O64: Ninguna | P64: 45535.582 | Q64: Varios tipos de crédito | R64: Ninguno | S64: 1033706838 | T64: Diana Maribel Fonseca Gómez | U64: direccion.riesgos@febor.coop | V64: Aprobado | W64: 20/08/2024 13:59:12: Registrado 10/09/2024 16:09:58: Creado 14/09/2024 23:22:20: Actualizado 18/09/2024 08:53:39: Acrualizado | X64: Suspensión de la operación de crédito | Y64: RGOP051 | Z64: =+COUNTIF('Eventos-Tareas'!$D$22:$D$1048576,'Eventos de riesgos'!$B64) -> 3 | AA64: =+'Eventos de riesgos'!$I64-'Eventos de riesgos'!$J64-'Eventos de riesgos'!$K64 -> 0 | AB64: El 22 de agosto de 2024 se suspendió el proceso de análisis de crédito por un error en el cálculo de la capacidad de pago, originado por discrepancias en la retención en la fuente, afectando cuatro casos de nómina. | AC64: El 22 de agosto de 2024 se detectó un error en el cálculo de capacidad de pago para créditos con descuento por nómina en cuatro casos, por discrepancias entre la retención en la fuente calculada por el modelo y la reportada en los desprendibles, lo que llevó a suspender el análisis de crédito. | AD64: Discrepancia entre la retención en la fuente calculada por el modelo interno de capacidad de pago y la reportada en los desprendibles de pago de los asociados afectados, generando imprecisiones en la evaluación crediticia. | AE64: Suspensión temporal del proceso de análisis de crédito. Retraso en la aprobación de créditos en espera. Falta de un plan de contingencia activo para dar continuidad al proceso durante la corrección del error.
B65: 64 | C65: 2024 | D65: Sep | E65: 45516.409 | F65: 45516.41 | G65: 45518.41 | H65: CasoEl 12 de agosto de 2024 se detectó una falla en el proceso de renovación automática de los Certificados de Depósito a Término (CDAT), lo que generó un reproceso en el pago de intereses del mes y afectó a 72 CDAT con vencimiento entre el 1 y el 11 de agosto. Estos títulos no fueron renovados automáticamente, por lo que fue necesario realizar el proceso de renovación manual el 12 de agosto. Aunque entre el 12 y el 13 de agosto no hubo vencimientos adicionales, y los títulos con vencimiento el 14 de agosto se renovaron correctamente, los 72 títulos afectados quedaron registrados con fecha de renovación del 14 de agosto, en lugar de la fecha originalmente pactada.Por lo anterior se formalizó la incidencia 64338 Solicitud Johan Cruz - Analista de OperacionesPosteriormente, se reportó la incidencia 64760 respecto de CDATs sin liquidación de intereses en la fecha correspondiente, este caso asociado al anterior, cuando se modificó la fecha de vencimiento del título. De esta novedad, se presentó una queja de una asociada: Correo Dirección SASBuenas tardes;Teniendo en cuenta que el pago de los intereses que esta haciendo el sistema quedo errado (esta pagando 30 días y no 44 como corresponde) agradezco si es posible podamos pagar la diferencia : $104.402 La Sra. Piedad desde hace días ha manifestado su preocupación y desconfianza por lo que ocurre con sus CDATS.Muchas gracias CausaLa falla se atribuye a la desactivación del proceso automático de renovación en el sistema, sin registro claro de cuándo ni por qué se desmarcó la opción de renovación automática del producto CDAT. ImpactoLa no renovación automática de los 72 CDAT en las fechas pactadas provocó un desajuste tanto en los registros de renovación como en las fechas de vencimiento acordadas. Esto impactó negativamente la percepción de los asociados sobre la gestión de sus inversiones. Además, el reproceso manual de estas fallas no sólo disminuye la productividad, sino que también incrementa el riesgo de imprecisiones en la administración de los productos financieros. AccionesAuditoría del sistema de renovación automática: Solicitar una auditoría detallada para determinar en qué momento se desmarcó el TAP de renovación automática del producto CDAT, identificar fallas en la trazabilidad del sistema y evitar futuras desactivaciones sin registro adecuado. La respuesta del proveedor fue que la auditoria deja evidenciar la marca del último usuario que operó pero no específicamente de quien levantó el Tap de renovación.(Analista de operaciones - Johan Cruz y Director de TI -Fabian Jordán)Corrección manual de renovaciones de CDAT: una vez se evidenció el error, se procedió a realizar las renovaciones de forma manual en el sistema. (Analista de operaciones - Johan Cruz)Corrección de la fecha de renovación: El sistema no permite realizar el cambio de fecha de la renovación, sin embargo se determinó que si el asociado desea retirar su CDAT en la fecha inicialmente pactada, lo podrá hacer con el reconocimiento normal de sus intereses.Pago de interesesPara el caso de la asociada relacionada en la queja, se le reconoció la totalidad de los intereses, en compensación de la falla presentada.A los demás asociados también se les realizó el pago de los intereses:CEDULA -NOMBRE -CDAT- DESTINO DE LOS INTERESES32624900 BEATRIZ CECILIA TEJADA DE CARDONA 21183 Voluntario80412765 JOSE FERNANDO GUTIERREZ HERNANDEZ 21857 Cdat36177961 ROCIO VILLEGAS TRUJILLO 21859 Cdat9073894 FERNANDO VELANDIA 17188 Voluntario41778348 NUBIA ESPERANZA TOVAR AGUILAR 20559 Cdat9511557 OSCAR FABIO ANGARITA OJEDA 22566 Voluntario91243120 JUAN JAIMES MANTILLA 22568 Cdat38235694 LAURA LUCIA TORRES PEREZ 20392 Cdat1010218901 LAURA LILIANA MURCIA MONTENEGRO 22574 Voluntario35407117 MARIA INES ALFONSO PRADA 22575 Cdat4325195 FABIO OLARTE ECHEVERRI 12430 Cdat1032389124 ANDRES JULIAN HURTADO PEREZ 18673 CdatAcción preventiva. Designar un funcionario que monitoree los vencimientos diarios de los CDATs y su respectiva verificación del estado de renovación. | I65: 104402 | J65: 0 | K65: 0 | L65: 7 - Ejecución y Administración de Procesos | M65: 71 - Recepción, Ejecución y Mantenimiento de Operaciones | N65: 714 - Ejecución Errónea de Modelos o de Sistemas | O65: Ninguna | P65: 45535.55 | Q65: CDAT | R65: Ninguno | S65: 1016071699 | T65: Johan Santiago Cruz | U65: analista.operativo2@febor.coop | V65: Aprobado | W65: 18/09/2024 10:02:45: Creación 17/10/2024 12:34:31: . 17/10/2024 16:58:51: Actualizado 18/10/2024 13:14:29: Actualizado | X65: Falla en renovación automática de CDATs | Y65: RGOP050 | Z65: =+COUNTIF('Eventos-Tareas'!$D$22:$D$1048576,'Eventos de riesgos'!$B65) -> 5 | AA65: =+'Eventos de riesgos'!$I65-'Eventos de riesgos'!$J65-'Eventos de riesgos'!$K65 -> 104402 | AB65: Una falla en el proceso de renovación automática de CDAT el 12 de agosto de 2024 afectó a 72 títulos con vencimiento entre el 1 y el 11 de agosto, los cuales quedaron registrados con fecha de renovación incorrecta, generando afectación en el pago de intereses. | AC65: El 12 de agosto de 2024 se detectó que 72 CDAT con vencimiento entre el 1 y el 11 de agosto no fueron renovados automáticamente, requiriendo renovación manual y quedando registrados con fecha de renovación del 14 de agosto en lugar de la fecha originalmente pactada. | AD65: Falla en el proceso de renovación automática de CDAT en el sistema, cuyo origen no fue completamente esclarecido, generando que un grupo de títulos no fuera procesado en las fechas correspondientes. | AE65: Reproceso en el pago de intereses del mes para 72 CDAT. Afectación de las condiciones originalmente pactadas con los asociados al registrar fechas de renovación incorrectas. Necesidad de gestión adicional con el proveedor para la corrección y formalización de las incidencias.
B66: 65 | C66: 2024 | D66: Sep | E66: 45548.417 | F66: 45566.647 | G66: 45548.417 | H66: CasoEl 27 de agosto de 2024, el asociado Rodrigo Alzate Mejía, con C.C. 71598485, reportó la liquidación anticipada de su ahorro programado Nro. 01424000000003852, originalmente pactado para retiro el 23 de septiembre de 2024. El ahorro fue liquidado un mes antes de la fecha establecida debido a un error en la configuración del sistema, que programó incorrectamente el plan de pagos. Este error afectó no solo a este asociado, sino a otros 10 ahorros programados con características similares, lo que generó una incidencia mayor, registrada bajo el número 64672.A continuación se relacionan los 10 ahorros que se han identificado presentan la misma novedad:IDENTIFICACION NOMBRE_CLIENTE COD_AHORRO DESCRIPCION NRO_CUENTA TASA PLAZO MONTO_APERTURA FECHA_APERTURA FECHA_VENCIMIENTO8709861 JOSE LUIS MONTANA PENATE 424 AHORRO CONTRACTUAL POSTGRADO 01424000000003854 7,5 360 300000 4/10/2023 26/09/202441712549 MARY LUCY RUBIO RAMIREZ 423 AHORRADOR POR SIEMPRE 01423000000000506 7,5 360 0 9/10/2023 1/10/202419241936 GERMAN ORLANDO MOYANO MARTINEZ 423 AHORRADOR POR SIEMPRE 01423000000000518 7,5 360 0 9/11/2023 1/11/20249774442 CARLOS ANDRES MOLINA MOLINA 423 AHORRADOR POR SIEMPRE 01423000000000519 7,5 360 0 10/11/2023 26/10/202451593844 ANA ROCIO SUAREZ BALLESTEROS 423 AHORRADOR POR SIEMPRE 01423000000000520 7,5 360 300000 15/11/2023 1/11/202441885408 LUDIVIA FRANCO GIRALDO 431 AHORRO CONTRACTUAL VACIONES INOLVID 01431000000000332 7,5 360 400000 21/11/2023 1/11/202471598485 RODRIGO ALZATE MEJIA 424 AHORRO CONTRACTUAL POSTGRADO 01424000000003858 7,5 360 0 29/11/2023 30/10/202451737788 NOHORA ALBA BUSTAMANTE SALAZAR 423 AHORRADOR POR SIEMPRE 01423000000000509 7,5 360 0 23/10/2023 26/09/202423273189 OLGA MARINA VILLAMIL DE RONDON 424 AHORRO CONTRACTUAL POSTGRADO 01424000000003849 7,5 720 200000 12/09/2023 26/08/202579834651 JUAN RODRIGUEZ CUELLAR 426 AHORRO CONTRACTUAL EMPRENDEDOR 01426000000000029 7,5 720 0 20/10/2023 26/09/202531271973 MARTHA LUCIA VELASQUEZ LOPEZ 426 AHORRO CONTRACTUAL EMPRENDEDOR 01426000000000030 7,5 720 0 28/11/2023 1/11/2025CausaEl sistema de administración de ahorros, proporcionado por el proveedor WOG, configuró de manera incorrecta el plan de pagos, asignando la primera cuota a una fecha que no correspondía con el acuerdo pactado. Esto ocurrió debido a una falla en la parametrización del producto, lo cual se encuentra en proceso de investigación por parte del proveedor y del área de Operaciones.ImpactoAsociados: Aunque no hubo impacto económico, ya que los intereses fueron pagados correctamente, un asociado manifestó inconformidad por la liquidación anticipada de sus ahorros.Operativo: La corrección de los productos afectados implica un reproceso operativo, lo cual incrementa la carga de trabajo para las áreas involucradas y podría afectar la eficiencia del equipo.Reputacional: La situación genera una percepción negativa entre los asociados sobre la confiabilidad del sistema y la capacidad de la cooperativa para gestionar adecuadamente sus productos financieros.Acciones Correctivas:Identificación y Reporte del Error: Se registró la incidencia el 06 de septiembre de 2024 y se solicitó respuesta inmediata al proveedor del sistema WOG. (Responsable: Analista de Operaciones).Revisión de Procedimientos: El equipo de Calidad y Operaciones revisará los procedimientos de configuración de ahorros programados para evitar errores similares en el futuro. (Responsables: Jefe de Calidad y Analista de Operaciones).Comunicación: Se informará a los asociados afectados, garantizando que sus intereses no han sido perjudicados, y se les brindará una explicación clara sobre la situación. (Responsable: Servicio al Asociado). Seguimiento a la Solución: Se llevará a cabo un seguimiento constante a la resolución de la incidencia por parte del proveedor. (Responsables: Dirección TI y Analista de Operaciones). | I66: 0 | J66: 0 | K66: 0 | L66: 4 - Asociados o Clientes | M66: 43 - Productos o Servicios Defectuosos | N66: 431 - Defectos del Producto | O66: Ninguna | P66: 45565.622 | Q66: Ahorro programado | R66: Ninguno | S66: 53166187 | T66: JOHANA PAOLA CORTES GOMEZ | U66: direccion.sas@febor.coop | V66: Aprobado | W66: 01/10/2024 15:36:36: Recibido 17/10/2024 19:49:57: Actualización | X66: Liquidación anticipada de ahorros programados por error del sistema | Y66: RGOP040 | Z66: =+COUNTIF('Eventos-Tareas'!$D$22:$D$1048576,'Eventos de riesgos'!$B66) -> 4 | AA66: =+'Eventos de riesgos'!$I66-'Eventos de riesgos'!$J66-'Eventos de riesgos'!$K66 -> 0 | AB66: Un error de configuración en el sistema generó la liquidación anticipada de 11 ahorros programados, incluyendo el del asociado Rodrigo Alzate, cuyo ahorro fue liquidado un mes antes de la fecha de vencimiento pactada. | AC66: El 27 de agosto de 2024 el asociado Rodrigo Alzate reportó la liquidación anticipada de su ahorro programado No. 01424000000003852, originalmente pactado para retiro el 23 de septiembre. La revisión evidenció que otros 10 ahorros programados presentaban la misma situación. | AD66: Error en la configuración del sistema que programó incorrectamente el plan de pagos de los ahorros programados afectados, generando su liquidación antes de la fecha de vencimiento pactada. | AE66: 11 asociados vieron liquidados anticipadamente sus ahorros programados. Riesgo de incumplimiento de las condiciones pactadas con los asociados. Se formalizó la incidencia 64672 ante el proveedor para la corrección y el reproceso de los productos afectados.
B67: 66 | C67: 2024 | D67: Sep | E67: 45557.636 | F67: 45557.636 | G67: 45558.636 | H67: CasoEl 22 de septiembre, el asociado Fabián Díaz Urrea, identificado con cédula de ciudadanía N.° 19.412.168, se comunicó con el Dr. Juan Pablo Vélez para informarle que su madre había fallecido esa misma madrugada. Sin embargo, el asociado no pudo acceder oportunamente al servicio funerario de Coorserpark, lo que le impidió gestionar adecuadamente la velación y los trámites correspondientes.CausaLa situación se originó debido a que, tras el cambio de condición del asociado de empleado a pensionado, no se reactivó el servicio funerario de cortesía que ofrece FEBOR. Este incumplimiento se debió a la falta de seguimiento por parte de las áreas responsables de gestionar la transición y continuidad de los beneficios.ImpactoEl hecho generó insatisfacción y malestar en el asociado, afectando negativamente la imagen y reputación de la cooperativa, al no cumplir con un servicio fundamental en un momento crítico.AccionesSe consideraron acciones para mitigar el impacto negativo en el asociado afectado, como la reactivación inmediata del servicio funerario con una tarifa especial, junto con una disculpa formal por parte del mismo gerente. Se contemplan otras acciones preventivas para reducir la posibilidad de que esta situación se repita con otros asociados:Se identificaron 203 asociados a los cuales se les identificó como empleados, siendo pensionados. Se procedió al ajuste de la novedad en E-broker para que tengan el plan de cortesía. Se considera la definición de un procedimiento para el manejo del cambio de novedades: | I67: 0 | J67: 0 | K67: 0 | L67: 7 - Ejecución y Administración de Procesos | M67: 71 - Recepción, Ejecución y Mantenimiento de Operaciones | N67: 713 - Incumplimiento de Plazos o Responsabilidades | O67: Ninguna | P67: 45565.637 | Q67: Beneficio funerario (Coorserpark) | R67: Comunicación por PBX | S67: 72179606 | T67: Juan Pablo Vélez Góez | U67: gerencia@febor.coop | V67: Aprobado | W67: 17/10/2024 15:19:21: Actualizado 08/11/2024 16:30:35: Actualización con la información del comité de gerencia a cierre de septiembre | X67: Fallas en la renovación del servicio funerario Coorserpark | Y67: RSAS040 | Z67: =+COUNTIF('Eventos-Tareas'!$D$22:$D$1048576,'Eventos de riesgos'!$B67) -> 4 | AA67: =+'Eventos de riesgos'!$I67-'Eventos de riesgos'!$J67-'Eventos de riesgos'!$K67 -> 0 | AB67: Al cambiar de condición de empleado a pensionado, el servicio funerario de cortesía de Febor no fue reactivado para el asociado Fabián Díaz, lo que le impidió acceder oportunamente al servicio tras el fallecimiento de su madre. | AC67: El 22 de septiembre, el asociado Fabián Díaz Urrea reportó que no pudo acceder oportunamente al servicio funerario de Coorserpark para atender el fallecimiento de su madre, al no encontrar activo el beneficio en su perfil. | AD67: Tras el cambio de condición del asociado de empleado a pensionado, no se realizó el seguimiento necesario para reactivar el servicio funerario de cortesía que ofrece Febor, por falta de controles entre las áreas responsables de gestionar la transición de beneficios. | AE67: El asociado no pudo acceder oportunamente al servicio funerario para gestionar la velación y trámites del fallecimiento de su madre. Insatisfacción y malestar del asociado. Daño a la imagen de la Cooperativa por incumplimiento del beneficio.
B68: 67 | C68: 2024 | D68: Sep | E68: 45548.417 | F68: 45565.694 | G68: 45566.694 | H68: Caso:Se llevó a cabo el envío de publicidad a personas que previamente habían manifestado su deseo de no recibir este tipo de comunicaciones. Tras consultar con la Jefe de Comunicaciones, se identificaron tres asociados que habían solicitado la exclusión de estas comunicaciones: dos lo hicieron a través de la Dirección de Servicio al Asociado y uno mediante el canal de PQRSF.La Jefatura de Comunicaciones, en su proceso habitual de filtrado de bases de datos, excluye a los asociados mencionados; sin embargo, durante el envío de mensajes de texto publicitarios referentes a la preaprobación de tarjetas de crédito en el mes de agosto, no se aplicó el filtro de manera adecuada debido a una omisión en el proceso, asumiendo erróneamente que la base ya contenía a estas personas excluidas. Esto pone de manifiesto que la exclusión de asociados que no desean recibir publicidad no está adecuadamente socializada con las áreas que también envían notificaciones por mensajes de texto y correos electrónicos.Causa:El incidente se debió a una omisión en el proceso de filtrado de la base de datos de tarjetas de crédito preaprobadas, derivada de la suposición errónea de que los asociados que habían solicitado la exclusión ya estaban debidamente registrados en la base de datos. ImpactoEl envío de publicidad no solicitada afectó la satisfacción de los asociados y dañó la reputación de la cooperativa en cuanto al respeto por las preferencias de comunicación de sus asociados. Además, puede generar quejas formales, posibles sanciones regulatorias por incumplimiento de la normatividad de protección de datos, y una percepción negativa sobre la eficiencia en la gestión de los datos de los asociados.Acciones:Atención a las quejas formales: Responder de manera oportuna y formal a las quejas recibidas a través de los canales oficiales, ofreciendo disculpas y explicando las medidas correctivas adoptadas para evitar la repetición del error. (Jefe de Comunicaciones – Director de Servicio al Asociado)Registro centralizado de solicitudes de exclusión: Crear un sistema de registro único y centralizado que permita mapear y consolidar todas las solicitudes de exclusión recibidas a través de diferentes canales, asegurando que estas se implementen correctamente en todas las bases de datos relevantes.Clarificación de la naturaleza de las comunicaciones: Definir criterios específicos y claros que permitan distinguir entre comunicaciones publicitarias y notificaciones relevantes, con el fin de evitar confusiones en la gestión de los envíos y respetar las preferencias de los asociados. (Jefe de Comunicaciones – Jefe Jurídico)Coordinación y socialización: Realizar una socialización formal con todas las áreas involucradas en el envío de comunicaciones, como mensajes de texto y correos electrónicos, para asegurar un cumplimiento uniforme de las solicitudes de exclusión. Esto debe incluir capacitaciones periódicas y la implementación de controles de verificación antes del envío de cualquier tipo de mensaje.( Jefe de Comunicaciones)Revisión de procesos tecnológicos: Implementar mejoras en los sistemas de gestión de bases de datos, incluyendo la automatización de las exclusiones para garantizar que cualquier asociado que haya solicitado no recibir comunicaciones sea filtrado adecuadamente y de manera consistente. (Jefe de Comunicaciones – Director TI) | I68: 0 | J68: 0 | K68: 0 | L68: 4 - Asociados o Clientes | M68: 41 - Adecuación, Divulgación de Información y Confianza | N68: 415 - Ventas / Colocaciones Agresivas | O68: Ninguna | P68: 45565.637 | Q68: Tarjeta crédito | R68: Mensajería de texto (SMS) | S68: 53166187 | T68: JOHANA PAOLA CORTES GOMEZ | U68: direccion.sas@febor.coop | V68: Aprobado | W68: null 17/10/2024 17:12:33: Actualizado | X68: Inconformidad de asociados que reciben publicidad por mensajes de texto | Y68: RCOM015 | Z68: =+COUNTIF('Eventos-Tareas'!$D$22:$D$1048576,'Eventos de riesgos'!$B68) -> 4 | AA68: =+'Eventos de riesgos'!$I68-'Eventos de riesgos'!$J68-'Eventos de riesgos'!$K68 -> 0 | AB68: Se enviaron mensajes de texto publicitarios de preaprobación de tarjetas de crédito a tres asociados que habían solicitado expresamente no recibir este tipo de comunicaciones, por omisión del filtro de exclusión en la base de datos. | AC68: En agosto, durante el envío de mensajes de texto publicitarios sobre preaprobación de tarjetas de crédito, se incluyó a tres asociados que habían solicitado previamente ser excluidos de este tipo de comunicaciones. | AD68: Omisión en el proceso de filtrado de la base de datos por parte de la Jefatura de Comunicaciones, al asumir erróneamente que la base ya contenía la exclusión de estos asociados sin verificarlo. | AE68: Vulneración de la voluntad de tres asociados de no recibir publicidad. Riesgo de incumplimiento normativo en protección de datos y respeto a solicitudes de exclusión de comunicaciones comerciales.
